Workbook

Sheet Budget
A1: Weekly Income | E1: Monthy Expenses | J1: Credit Card Expenses | O1: Subscriptions
A2: Bill | B2: Amount | C2: DayOfMonth | E2: Bill | F2: Amount | G2: DayOfMonth | J2: Bill | K2: Amount | L2: Month | M2: DayOfMonth | O2: Bill | P2: Amount | Q2: DayOfYear
A3: PAY-LM | B3: 1453 | C3: 6 | E3: Rent | F3: =1682+12+7+20+12 -> 1733 | G3: 1 | H3: Extra: | J3: Capital One | K3: 467.61 | L3: 12 | M3: 7 | O3: Amazon Prime | P3: 7.48 | Q3: 8
E4: Car | F4: 503.35 | G4: 2 | H4: 0 | J4: Chase | K4: 406 | L4: 12 | M4: 4 | O4: YT Premium | P4: 22.99 | Q4: 9
E5: Mom Rent | F5: 850 | G5: 20 | J5: NFCU | K5: 72 | L5: 12 | M5: 6 | O5: Netflix | P5: 24.6 | Q5: 29
E6: Groceries | F6: =180+120 -> 300 | G6: 2 | J6: TOTAL | K6: =SUM(K3:K5) -> 945.61 | L6: - | M6: - | O6: Spotify | P6: 11.99 | Q6: 8
E7: Savings | F7: =1000 -> 1000 | G7: 28 | O7: Rocket Money | P7: 6 | Q7: 12
E8: AT&T | F8: 65 | G8: 18 | O8: Little4Much | P8: 150 | Q8: 28
E9: GA Power | F9: 70 | G9: 5 | O9: None
E10: TH | F10: =400 -> 400 | G10: 26 | O10: Subscriptions (Deactivated)
O11: Crunchyroll | P11: 8.53 | Q11: 27
E12: Annual Expenses | O12: Audible | P12: 0 | Q12: 11
E13: Bill | F13: Amount | G13: DayOfYear
E14: Car Insurance | F14: 1999.1 | G14: 45643
E15: Phone Bill | F15: 300 | G15: 45915

Sheet Detailed Monthy Sim
D1: Miscellaneous | E1: Monthly Expenses | N1: =Budget!$E$12 -> Annual Expenses | Q1: Credit Card | T1: Subscriptions | AA1: TOTAL | AC1: =SUMIF(D3:Z32,"<0") -> -6090.06 | AD1: =SUM(E3:E32) -> 5812
A2: 45658 | E2: =Budget!$A$3 -> PAY-LM | F2: =Budget!$E$3 -> Rent | G2: =Budget!$E$4 -> Car | H2: =Budget!$E$5 -> Mom Rent | I2: =Budget!$E$8 -> AT&T | J2: =Budget!$E$9 -> GA Power | K2: =Budget!$E$10 -> TH | L2: =Budget!$E$6 -> Groceries | M2: =Budget!$E$7 -> Savings | N2: =Budget!$E$14 -> Car Insurance | O2: =Budget!$E$15 -> Phone Bill | Q2: =Budget!$J$3 -> Capital One | R2: =Budget!$J$4 -> Chase | S2: =Budget!$J$5 -> NFCU | T2: =Budget!$O$3 -> Amazon Prime | U2: =Budget!$O$12 -> Audible | V2: =Budget!$O$5 -> Netflix | W2: =Budget!$O$6 -> Spotify | X2: =Budget!$O$7 -> Rocket Money | Y2: =Budget!$O$8 -> Little4Much | Z2: =Budget!$O$9 -> None | AC2: =AD1+AC1 -> -278.06
A3: =A2 -> 45658 | B3: 473.69 | C3: 0 | D3: 0 | E3: =N("PAY-LM")+IF(WEEKDAY(A3)=Budget!$C$3,Budget!$B$3,0) -> 0 | F3: =N("Rent")-IF(DAY(A3)=Budget!$G$3,Budget!$F$3,0) -> -1733 | G3: =N("Car")-IF(DAY(A3)=Budget!$G$4,Budget!$F$4+Budget!$H$4,0) -> 0 | H3: =N("Mom Rent")-IF(DAY(A3)=Budget!$G$5,Budget!$F$5,0) -> 0 | I3: =N("AT&T")-IF(DAY(A3)=Budget!$G$8,Budget!$F$8,0) -> 0 | J3: =N("GA Power")-IF(DAY(A3)=Budget!$G$9,Budget!$F$9,0) -> 0 | K3: =N("Haircut")-IF(DAY(A3)=Budget!$G$10,Budget!$F$10,0) -> 0 | L3: =N("Groceries")-IF(DAY(A3)=Budget!$G$6,Budget!$F$6,0) -> 0 | M3: =N("Savings")-IF(DAY(A3)=Budget!$G$7,Budget!$F$7,0) -> 0 | N3: =N("Car Insurance")-COUNTIF(Budget!$G$14,A3)*Budget!$F$14 -> 0 | O3: =N("Phone Bill")-COUNTIF(Budget!$G$15, A3)*Budget!$F$15 -> 0 | Q3: =N("Spotify")-IF(AND(DAY($A3)=Budget!$M$3, MONTH($A3)=Budget!$L$3),Budget!$K$3,0) -> 0 | R3: =N("Spotify")-IF(AND(DAY($A3)=Budget!$M$4, MONTH($A3)=Budget!$L$4),Budget!$K$4,0) -> 0 | S3: =N("Spotify")-IF(AND(DAY($A3)=Budget!$M$5, MONTH($A3)=Budget!$L$5),Budget!$K$5,0) -> 0 | T3: =N("Amazon Prime")-IF(DAY(A3)=Budget!$Q$3,Budget!$P$3,0) -> 0 | U3: =N("Audible")-IF(DAY(A3)=Budget!$Q$12,Budget!$P$12,0) -> 0 | V3: =N("Crunchyroll")-IF(DAY(A3)=Budget!$Q$5,Budget!$P$5,0) -> 0 | W3: =N("HBO Max")-IF(DAY(A3)=Budget!$Q$6,Budget!$P$6,0) -> 0 | X3: =N("Netflix")-IF(DAY(A3)=Budget!$Q$7,Budget!$P$7,0) -> 0 | Y3: =N("Spotify")-IF(DAY(A3)=Budget!$Q$8,Budget!$P$8,0) -> 0 | Z3: =N("Truebill")-IF(DAY(A3)=Budget!$Q$9,Budget!$P$9,0) -> 0 | AA3: =SUM(D3:Z3) -> -1733
A4: =A3+1 -> 45659 | B4: =B3+AA4 -> -329.66 | C4: =IF(B4>B3,2,IF(B4=B3, 1,0)) -> 0 | D4: 0 | E4: =N("PAY-LM")+IF(WEEKDAY(A4)=Budget!$C$3,Budget!$B$3,0) -> 0 | F4: =N("Rent")-IF(DAY(A4)=Budget!$G$3,Budget!$F$3,0) -> 0 | G4: =N("Car")-IF(DAY(A4)=Budget!$G$4,Budget!$F$4+Budget!$H$4,0) -> -503.35 | H4: =N("Mom Rent")-IF(DAY(A4)=Budget!$G$5,Budget!$F$5,0) -> 0 | I4: =N("AT&T")-IF(DAY(A4)=Budget!$G$8,Budget!$F$8,0) -> 0 | J4: =N("GA Power")-IF(DAY(A4)=Budget!$G$9,Budget!$F$9,0) -> 0 | K4: =N("Haircut")-IF(DAY(A4)=Budget!$G$10,Budget!$F$10,0) -> 0 | L4: =N("Groceries")-IF(DAY(A4)=Budget!$G$6,Budget!$F$6,0) -> -300 | M4: =N("Savings")-IF(DAY(A4)=Budget!$G$7,Budget!$F$7,0) -> 0 | N4: =N("Car Insurance")-COUNTIF(Budget!$G$14,A4)*Budget!$F$14 -> 0 | O4: =N("Phone Bill")-COUNTIF(Budget!$G$15, A4)*Budget!$F$15 -> 0 | Q4: =N("Spotify")-IF(AND(DAY($A4)=Budget!$M$3, MONTH($A4)=Budget!$L$3),Budget!$K$3,0) -> 0 | R4: =N("Spotify")-IF(AND(DAY($A4)=Budget!$M$4, MONTH($A4)=Budget!$L$4),Budget!$K$4,0) -> 0 | S4: =N("Spotify")-IF(AND(DAY($A4)=Budget!$M$5, MONTH($A4)=Budget!$L$5),Budget!$K$5,0) -> 0 | T4: =N("Amazon Prime")-IF(DAY(A4)=Budget!$Q$3,Budget!$P$3,0) -> 0 | U4: =N("Audible")-IF(DAY(A4)=Budget!$Q$12,Budget!$P$12,0) -> 0 | V4: =N("Crunchyroll")-IF(DAY(A4)=Budget!$Q$5,Budget!$P$5,0) -> 0 | W4: =N("HBO Max")-IF(DAY(A4)=Budget!$Q$6,Budget!$P$6,0) -> 0 | X4: =N("Netflix")-IF(DAY(A4)=Budget!$Q$7,Budget!$P$7,0) -> 0 | Y4: =N("Spotify")-IF(DAY(A4)=Budget!$Q$8,Budget!$P$8,0) -> 0 | Z4: =N("Truebill")-IF(DAY(A4)=Budget!$Q$9,Budget!$P$9,0) -> 0 | AA4: =SUM(D4:Z4) -> -803.35
A5: =A4+1 -> 45660 | B5: =B4+AA5 -> 1123.34 | C5: =IF(B5>B4,2,IF(B5=B4, 1,0)) -> 2 | D5: 0 | E5: =N("PAY-LM")+IF(WEEKDAY(A5)=Budget!$C$3,Budget!$B$3,0) -> 1453 | F5: =N("Rent")-IF(DAY(A5)=Budget!$G$3,Budget!$F$3,0) -> 0 | G5: =N("Car")-IF(DAY(A5)=Budget!$G$4,Budget!$F$4+Budget!$H$4,0) -> 0 | H5: =N("Mom Rent")-IF(DAY(A5)=Budget!$G$5,Budget!$F$5,0) -> 0 | I5: =N("AT&T")-IF(DAY(A5)=Budget!$G$8,Budget!$F$8,0) -> 0 | J5: =N("GA Power")-IF(DAY(A5)=Budget!$G$9,Budget!$F$9,0) -> 0 | K5: =N("Haircut")-IF(DAY(A5)=Budget!$G$10,Budget!$F$10,0) -> 0 | L5: =N("Groceries")-IF(DAY(A5)=Budget!$G$6,Budget!$F$6,0) -> 0 | M5: =N("Savings")-IF(DAY(A5)=Budget!$G$7,Budget!$F$7,0) -> 0 | N5: =N("Car Insurance")-COUNTIF(Budget!$G$14,A5)*Budget!$F$14 -> 0 | O5: =N("Phone Bill")-COUNTIF(Budget!$G$15, A5)*Budget!$F$15 -> 0 | Q5: =N("Spotify")-IF(AND(DAY($A5)=Budget!$M$3, MONTH($A5)=Budget!$L$3),Budget!$K$3,0) -> 0 | R5: =N("Spotify")-IF(AND(DAY($A5)=Budget!$M$4, MONTH($A5)=Budget!$L$4),Budget!$K$4,0) -> 0 | S5: =N("Spotify")-IF(AND(DAY($A5)=Budget!$M$5, MONTH($A5)=Budget!$L$5),Budget!$K$5,0) -> 0 | T5: =N("Amazon Prime")-IF(DAY(A5)=Budget!$Q$3,Budget!$P$3,0) -> 0 | U5: =N("Audible")-IF(DAY(A5)=Budget!$Q$12,Budget!$P$12,0) -> 0 | V5: =N("Crunchyroll")-IF(DAY(A5)=Budget!$Q$5,Budget!$P$5,0) -> 0 | W5: =N("HBO Max")-IF(DAY(A5)=Budget!$Q$6,Budget!$P$6,0) -> 0 | X5: =N("Netflix")-IF(DAY(A5)=Budget!$Q$7,Budget!$P$7,0) -> 0 | Y5: =N("Spotify")-IF(DAY(A5)=Budget!$Q$8,Budget!$P$8,0) -> 0 | Z5: =N("Truebill")-IF(DAY(A5)=Budget!$Q$9,Budget!$P$9,0) -> 0 | AA5: =SUM(D5:Z5) -> 1453
A6: =A5+1 -> 45661 | B6: =B5+AA6 -> 686.27 | C6: =IF(B6>B5,2,IF(B6=B5, 1,0)) -> 0 | D6: 0 | E6: =N("PAY-LM")+IF(WEEKDAY(A6)=Budget!$C$3,Budget!$B$3,0) -> 0 | F6: =N("Rent")-IF(DAY(A6)=Budget!$G$3,Budget!$F$3,0) -> 0 | G6: =N("Car")-IF(DAY(A6)=Budget!$G$4,Budget!$F$4+Budget!$H$4,0) -> 0 | H6: =N("Mom Rent")-IF(DAY(A6)=Budget!$G$5,Budget!$F$5,0) -> 0 | I6: =N("AT&T")-IF(DAY(A6)=Budget!$G$8,Budget!$F$8,0) -> 0 | J6: =N("GA Power")-IF(DAY(A6)=Budget!$G$9,Budget!$F$9,0) -> 0 | K6: =N("Haircut")-IF(DAY(A6)=Budget!$G$10,Budget!$F$10,0) -> 0 | L6: =N("Groceries")-IF(DAY(A6)=Budget!$G$6,Budget!$F$6,0) -> 0 | M6: =N("Savings")-IF(DAY(A6)=Budget!$G$7,Budget!$F$7,0) -> 0 | N6: =N("Car Insurance")-COUNTIF(Budget!$G$14,A6)*Budget!$F$14 -> 0 | O6: =N("Phone Bill")-COUNTIF(Budget!$G$15, A6)*Budget!$F$15 -> 0 | Q6: =N("Spotify")-IF(AND(DAY($A6)=Budget!$M$3, MONTH($A6)=Budget!$L$3),Budget!$K$3,0) -> 0 | R6: -437.07 | S6: =N("Spotify")-IF(AND(DAY($A6)=Budget!$M$5, MONTH($A6)=Budget!$L$5),Budget!$K$5,0) -> 0 | T6: =N("Amazon Prime")-IF(DAY(A6)=Budget!$Q$3,Budget!$P$3,0) -> 0 | U6: =N("Audible")-IF(DAY(A6)=Budget!$Q$12,Budget!$P$12,0) -> 0 | V6: =N("Crunchyroll")-IF(DAY(A6)=Budget!$Q$5,Budget!$P$5,0) -> 0 | W6: =N("HBO Max")-IF(DAY(A6)=Budget!$Q$6,Budget!$P$6,0) -> 0 | X6: =N("Netflix")-IF(DAY(A6)=Budget!$Q$7,Budget!$P$7,0) -> 0 | Y6: =N("Spotify")-IF(DAY(A6)=Budget!$Q$8,Budget!$P$8,0) -> 0 | Z6: =N("Truebill")-IF(DAY(A6)=Budget!$Q$9,Budget!$P$9,0) -> 0 | AA6: =SUM(D6:Z6) -> -437.07
A7: =A6+1 -> 45662 | B7: =1519.79 -> 1519.79 | C7: =IF(B7>B6,2,IF(B7=B6, 1,0)) -> 2 | D7: 0 | E7: =N("PAY-LM")+IF(WEEKDAY(A7)=Budget!$C$3,Budget!$B$3,0) -> 0 | F7: =N("Rent")-IF(DAY(A7)=Budget!$G$3,Budget!$F$3,0) -> 0 | G7: =N("Car")-IF(DAY(A7)=Budget!$G$4,Budget!$F$4+Budget!$H$4,0) -> 0 | H7: =N("Mom Rent")-IF(DAY(A7)=Budget!$G$5,Budget!$F$5,0) -> 0 | I7: =N("AT&T")-IF(DAY(A7)=Budget!$G$8,Budget!$F$8,0) -> 0 | J7: =N("GA Power")-IF(DAY(A7)=Budget!$G$9,Budget!$F$9,0) -> -70 | K7: =N("Haircut")-IF(DAY(A7)=Budget!$G$10,Budget!$F$10,0) -> 0 | L7: =N("Groceries")-IF(DAY(A7)=Budget!$G$6,Budget!$F$6,0) -> 0 | M7: =N("Savings")-IF(DAY(A7)=Budget!$G$7,Budget!$F$7,0) -> 0 | N7: =N("Car Insurance")-COUNTIF(Budget!$G$14,A7)*Budget!$F$14 -> 0 | O7: =N("Phone Bill")-COUNTIF(Budget!$G$15, A7)*Budget!$F$15 -> 0 | Q7: =N("Spotify")-IF(AND(DAY($A7)=Budget!$M$3, MONTH($A7)=Budget!$L$3),Budget!$K$3,0) -> 0 | R7: =N("Spotify")-IF(AND(DAY($A7)=Budget!$M$4, MONTH($A7)=Budget!$L$4),Budget!$K$4,0) -> 0 | S7: =N("Spotify")-IF(AND(DAY($A7)=Budget!$M$5, MONTH($A7)=Budget!$L$5),Budget!$K$5,0) -> 0 | T7: =N("Amazon Prime")-IF(DAY(A7)=Budget!$Q$3,Budget!$P$3,0) -> 0 | U7: =N("Audible")-IF(DAY(A7)=Budget!$Q$12,Budget!$P$12,0) -> 0 | V7: =N("Crunchyroll")-IF(DAY(A7)=Budget!$Q$5,Budget!$P$5,0) -> 0 | W7: =N("HBO Max")-IF(DAY(A7)=Budget!$Q$6,Budget!$P$6,0) -> 0 | X7: =N("Netflix")-IF(DAY(A7)=Budget!$Q$7,Budget!$P$7,0) -> 0 | Y7: =N("Spotify")-IF(DAY(A7)=Budget!$Q$8,Budget!$P$8,0) -> 0 | Z7: =N("Truebill")-IF(DAY(A7)=Budget!$Q$9,Budget!$P$9,0) -> 0 | AA7: =SUM(D7:Z7) -> -70
A8: =A7+1 -> 45663 | B8: =1082.72 -> 1082.72 | C8: =IF(B8>B7,2,IF(B8=B7, 1,0)) -> 0 | D8: 0 | E8: =N("PAY-LM")+IF(WEEKDAY(A8)=Budget!$C$3,Budget!$B$3,0) -> 0 | F8: =N("Rent")-IF(DAY(A8)=Budget!$G$3,Budget!$F$3,0) -> 0 | G8: =N("Car")-IF(DAY(A8)=Budget!$G$4,Budget!$F$4+Budget!$H$4,0) -> 0 | H8: =N("Mom Rent")-IF(DAY(A8)=Budget!$G$5,Budget!$F$5,0) -> 0 | I8: =N("AT&T")-IF(DAY(A8)=Budget!$G$8,Budget!$F$8,0) -> 0 | J8: =N("GA Power")-IF(DAY(A8)=Budget!$G$9,Budget!$F$9,0) -> 0 | K8: =N("Haircut")-IF(DAY(A8)=Budget!$G$10,Budget!$F$10,0) -> 0 | L8: =N("Groceries")-IF(DAY(A8)=Budget!$G$6,Budget!$F$6,0) -> 0 | M8: =N("Savings")-IF(DAY(A8)=Budget!$G$7,Budget!$F$7,0) -> 0 | N8: =N("Car Insurance")-COUNTIF(Budget!$G$14,A8)*Budget!$F$14 -> 0 | O8: =N("Phone Bill")-COUNTIF(Budget!$G$15, A8)*Budget!$F$15 -> 0 | Q8: =N("Spotify")-IF(AND(DAY($A8)=Budget!$M$3, MONTH($A8)=Budget!$L$3),Budget!$K$3,0) -> 0 | R8: =N("Spotify")-IF(AND(DAY($A8)=Budget!$M$4, MONTH($A8)=Budget!$L$4),Budget!$K$4,0) -> 0 | S8: -49.57 | T8: =N("Amazon Prime")-IF(DAY(A8)=Budget!$Q$3,Budget!$P$3,0) -> 0 | U8: =N("Audible")-IF(DAY(A8)=Budget!$Q$12,Budget!$P$12,0) -> 0 | V8: =N("Crunchyroll")-IF(DAY(A8)=Budget!$Q$5,Budget!$P$5,0) -> 0 | W8: =N("HBO Max")-IF(DAY(A8)=Budget!$Q$6,Budget!$P$6,0) -> 0 | X8: =N("Netflix")-IF(DAY(A8)=Budget!$Q$7,Budget!$P$7,0) -> 0 | Y8: =N("Spotify")-IF(DAY(A8)=Budget!$Q$8,Budget!$P$8,0) -> 0 | Z8: =N("Truebill")-IF(DAY(A8)=Budget!$Q$9,Budget!$P$9,0) -> 0 | AA8: =SUM(D8:Z8) -> -49.57
A9: =A8+1 -> 45664 | B9: =B8+AA9 -> 710.72 | C9: =IF(B9>B8,2,IF(B9=B8, 1,0)) -> 0 | D9: =-172-200 -> -372 | E9: =N("PAY-LM")+IF(WEEKDAY(A9)=Budget!$C$3,Budget!$B$3,0) -> 0 | F9: =N("Rent")-IF(DAY(A9)=Budget!$G$3,Budget!$F$3,0) -> 0 | G9: =N("Car")-IF(DAY(A9)=Budget!$G$4,Budget!$F$4+Budget!$H$4,0) -> 0 | H9: =N("Mom Rent")-IF(DAY(A9)=Budget!$G$5,Budget!$F$5,0) -> 0 | I9: =N("AT&T")-IF(DAY(A9)=Budget!$G$8,Budget!$F$8,0) -> 0 | J9: =N("GA Power")-IF(DAY(A9)=Budget!$G$9,Budget!$F$9,0) -> 0 | K9: =N("Haircut")-IF(DAY(A9)=Budget!$G$10,Budget!$F$10,0) -> 0 | L9: =N("Groceries")-IF(DAY(A9)=Budget!$G$6,Budget!$F$6,0) -> 0 | M9: =N("Savings")-IF(DAY(A9)=Budget!$G$7,Budget!$F$7,0) -> 0 | N9: =N("Car Insurance")-COUNTIF(Budget!$G$14,A9)*Budget!$F$14 -> 0 | O9: =N("Phone Bill")-COUNTIF(Budget!$G$15, A9)*Budget!$F$15 -> 0 | Q9: =N("Spotify")-IF(AND(DAY($A9)=Budget!$M$3, MONTH($A9)=Budget!$L$3),Budget!$K$3,0) -> 0 | R9: =N("Spotify")-IF(AND(DAY($A9)=Budget!$M$4, MONTH($A9)=Budget!$L$4),Budget!$K$4,0) -> 0 | S9: =N("Spotify")-IF(AND(DAY($A9)=Budget!$M$5, MONTH($A9)=Budget!$L$5),Budget!$K$5,0) -> 0 | T9: =N("Amazon Prime")-IF(DAY(A9)=Budget!$Q$3,Budget!$P$3,0) -> 0 | U9: =N("Audible")-IF(DAY(A9)=Budget!$Q$12,Budget!$P$12,0) -> 0 | V9: =N("Crunchyroll")-IF(DAY(A9)=Budget!$Q$5,Budget!$P$5,0) -> 0 | W9: =N("HBO Max")-IF(DAY(A9)=Budget!$Q$6,Budget!$P$6,0) -> 0 | X9: =N("Netflix")-IF(DAY(A9)=Budget!$Q$7,Budget!$P$7,0) -> 0 | Y9: =N("Spotify")-IF(DAY(A9)=Budget!$Q$8,Budget!$P$8,0) -> 0 | Z9: =N("Truebill")-IF(DAY(A9)=Budget!$Q$9,Budget!$P$9,0) -> 0 | AA9: =SUM(D9:Z9) -> -372
A10: =A9+1 -> 45665 | B10: =B9+AA10 -> 581.25 | C10: =IF(B10>B9,2,IF(B10=B9, 1,0)) -> 0 | D10: -110 | E10: =N("PAY-LM")+IF(WEEKDAY(A10)=Budget!$C$3,Budget!$B$3,0) -> 0 | F10: =N("Rent")-IF(DAY(A10)=Budget!$G$3,Budget!$F$3,0) -> 0 | G10: =N("Car")-IF(DAY(A10)=Budget!$G$4,Budget!$F$4+Budget!$H$4,0) -> 0 | H10: =N("Mom Rent")-IF(DAY(A10)=Budget!$G$5,Budget!$F$5,0) -> 0 | I10: =N("AT&T")-IF(DAY(A10)=Budget!$G$8,Budget!$F$8,0) -> 0 | J10: =N("GA Power")-IF(DAY(A10)=Budget!$G$9,Budget!$F$9,0) -> 0 | K10: =N("Haircut")-IF(DAY(A10)=Budget!$G$10,Budget!$F$10,0) -> 0 | L10: =N("Groceries")-IF(DAY(A10)=Budget!$G$6,Budget!$F$6,0) -> 0 | M10: =N("Savings")-IF(DAY(A10)=Budget!$G$7,Budget!$F$7,0) -> 0 | N10: =N("Car Insurance")-COUNTIF(Budget!$G$14,A10)*Budget!$F$14 -> 0 | O10: =N("Phone Bill")-COUNTIF(Budget!$G$15, A10)*Budget!$F$15 -> 0 | Q10: =N("Spotify")-IF(AND(DAY($A10)=Budget!$M$3, MONTH($A10)=Budget!$L$3),Budget!$K$3,0) -> 0 | R10: =N("Spotify")-IF(AND(DAY($A10)=Budget!$M$4, MONTH($A10)=Budget!$L$4),Budget!$K$4,0) -> 0 | S10: =N("Spotify")-IF(AND(DAY($A10)=Budget!$M$5, MONTH($A10)=Budget!$L$5),Budget!$K$5,0) -> 0 | T10: =N("Amazon Prime")-IF(DAY(A10)=Budget!$Q$3,Budget!$P$3,0) -> -7.48 | U10: =N("Audible")-IF(DAY(A10)=Budget!$Q$12,Budget!$P$12,0) -> 0 | V10: =N("Crunchyroll")-IF(DAY(A10)=Budget!$Q$5,Budget!$P$5,0) -> 0 | W10: =N("HBO Max")-IF(DAY(A10)=Budget!$Q$6,Budget!$P$6,0) -> -11.99 | X10: =N("Netflix")-IF(DAY(A10)=Budget!$Q$7,Budget!$P$7,0) -> 0 | Y10: =N("Spotify")-IF(DAY(A10)=Budget!$Q$8,Budget!$P$8,0) -> 0 | Z10: =N("Truebill")-IF(DAY(A10)=Budget!$Q$9,Budget!$P$9,0) -> 0 | AA10: =SUM(D10:Z10) -> -129.47
A11: =A10+1 -> 45666 | B11: =B10+AA11 -> 581.25 | C11: =IF(B11>B10,2,IF(B11=B10, 1,0)) -> 1 | D11: 0 | E11: =N("PAY-LM")+IF(WEEKDAY(A11)=Budget!$C$3,Budget!$B$3,0) -> 0 | F11: =N("Rent")-IF(DAY(A11)=Budget!$G$3,Budget!$F$3,0) -> 0 | G11: =N("Car")-IF(DAY(A11)=Budget!$G$4,Budget!$F$4+Budget!$H$4,0) -> 0 | H11: =N("Mom Rent")-IF(DAY(A11)=Budget!$G$5,Budget!$F$5,0) -> 0 | I11: =N("AT&T")-IF(DAY(A11)=Budget!$G$8,Budget!$F$8,0) -> 0 | J11: =N("GA Power")-IF(DAY(A11)=Budget!$G$9,Budget!$F$9,0) -> 0 | K11: =N("Haircut")-IF(DAY(A11)=Budget!$G$10,Budget!$F$10,0) -> 0 | L11: =N("Groceries")-IF(DAY(A11)=Budget!$G$6,Budget!$F$6,0) -> 0 | M11: =N("Savings")-IF(DAY(A11)=Budget!$G$7,Budget!$F$7,0) -> 0 | N11: =N("Car Insurance")-COUNTIF(Budget!$G$14,A11)*Budget!$F$14 -> 0 | O11: =N("Phone Bill")-COUNTIF(Budget!$G$15, A11)*Budget!$F$15 -> 0 | Q11: =N("Spotify")-IF(AND(DAY($A11)=Budget!$M$3, MONTH($A11)=Budget!$L$3),Budget!$K$3,0) -> 0 | R11: =N("Spotify")-IF(AND(DAY($A11)=Budget!$M$4, MONTH($A11)=Budget!$L$4),Budget!$K$4,0) -> 0 | S11: =N("Spotify")-IF(AND(DAY($A11)=Budget!$M$5, MONTH($A11)=Budget!$L$5),Budget!$K$5,0) -> 0 | T11: =N("Amazon Prime")-IF(DAY(A11)=Budget!$Q$3,Budget!$P$3,0) -> 0 | U11: =N("Audible")-IF(DAY(A11)=Budget!$Q$12,Budget!$P$12,0) -> 0 | V11: =N("Crunchyroll")-IF(DAY(A11)=Budget!$Q$5,Budget!$P$5,0) -> 0 | W11: =N("HBO Max")-IF(DAY(A11)=Budget!$Q$6,Budget!$P$6,0) -> 0 | X11: =N("Netflix")-IF(DAY(A11)=Budget!$Q$7,Budget!$P$7,0) -> 0 | Y11: =N("Spotify")-IF(DAY(A11)=Budget!$Q$8,Budget!$P$8,0) -> 0 | Z11: =N("Truebill")-IF(DAY(A11)=Budget!$Q$9,Budget!$P$9,0) -> 0 | AA11: =SUM(D11:Z11) -> 0
A12: =A11+1 -> 45667 | B12: =B11+AA12 -> 2034.25 | C12: =IF(B12>B11,2,IF(B12=B11, 1,0)) -> 2 | D12: 0 | E12: =N("PAY-LM")+IF(WEEKDAY(A12)=Budget!$C$3,Budget!$B$3,0) -> 1453 | F12: =N("Rent")-IF(DAY(A12)=Budget!$G$3,Budget!$F$3,0) -> 0 | G12: =N("Car")-IF(DAY(A12)=Budget!$G$4,Budget!$F$4+Budget!$H$4,0) -> 0 | H12: =N("Mom Rent")-IF(DAY(A12)=Budget!$G$5,Budget!$F$5,0) -> 0 | I12: =N("AT&T")-IF(DAY(A12)=Budget!$G$8,Budget!$F$8,0) -> 0 | J12: =N("GA Power")-IF(DAY(A12)=Budget!$G$9,Budget!$F$9,0) -> 0 | K12: =N("Haircut")-IF(DAY(A12)=Budget!$G$10,Budget!$F$10,0) -> 0 | L12: =N("Groceries")-IF(DAY(A12)=Budget!$G$6,Budget!$F$6,0) -> 0 | M12: =N("Savings")-IF(DAY(A12)=Budget!$G$7,Budget!$F$7,0) -> 0 | N12: =N("Car Insurance")-COUNTIF(Budget!$G$14,A12)*Budget!$F$14 -> 0 | O12: =N("Phone Bill")-COUNTIF(Budget!$G$15, A12)*Budget!$F$15 -> 0 | Q12: =N("Spotify")-IF(AND(DAY($A12)=Budget!$M$3, MONTH($A12)=Budget!$L$3),Budget!$K$3,0) -> 0 | R12: =N("Spotify")-IF(AND(DAY($A12)=Budget!$M$4, MONTH($A12)=Budget!$L$4),Budget!$K$4,0) -> 0 | S12: =N("Spotify")-IF(AND(DAY($A12)=Budget!$M$5, MONTH($A12)=Budget!$L$5),Budget!$K$5,0) -> 0 | T12: =N("Amazon Prime")-IF(DAY(A12)=Budget!$Q$3,Budget!$P$3,0) -> 0 | U12: =N("Audible")-IF(DAY(A12)=Budget!$Q$12,Budget!$P$12,0) -> 0 | V12: =N("Crunchyroll")-IF(DAY(A12)=Budget!$Q$5,Budget!$P$5,0) -> 0 | W12: =N("HBO Max")-IF(DAY(A12)=Budget!$Q$6,Budget!$P$6,0) -> 0 | X12: =N("Netflix")-IF(DAY(A12)=Budget!$Q$7,Budget!$P$7,0) -> 0 | Y12: =N("Spotify")-IF(DAY(A12)=Budget!$Q$8,Budget!$P$8,0) -> 0 | Z12: =N("Truebill")-IF(DAY(A12)=Budget!$Q$9,Budget!$P$9,0) -> 0 | AA12: =SUM(D12:Z12) -> 1453
A13: =A12+1 -> 45668 | B13: =B12+AA13 -> 2034.25 | C13: =IF(B13>B12,2,IF(B13=B12, 1,0)) -> 1 | D13: 0 | E13: =N("PAY-LM")+IF(WEEKDAY(A13)=Budget!$C$3,Budget!$B$3,0) -> 0 | F13: =N("Rent")-IF(DAY(A13)=Budget!$G$3,Budget!$F$3,0) -> 0 | G13: =N("Car")-IF(DAY(A13)=Budget!$G$4,Budget!$F$4+Budget!$H$4,0) -> 0 | H13: =N("Mom Rent")-IF(DAY(A13)=Budget!$G$5,Budget!$F$5,0) -> 0 | I13: =N("AT&T")-IF(DAY(A13)=Budget!$G$8,Budget!$F$8,0) -> 0 | J13: =N("GA Power")-IF(DAY(A13)=Budget!$G$9,Budget!$F$9,0) -> 0 | K13: =N("Haircut")-IF(DAY(A13)=Budget!$G$10,Budget!$F$10,0) -> 0 | L13: =N("Groceries")-IF(DAY(A13)=Budget!$G$6,Budget!$F$6,0) -> 0 | M13: =N("Savings")-IF(DAY(A13)=Budget!$G$7,Budget!$F$7,0) -> 0 | N13: =N("Car Insurance")-COUNTIF(Budget!$G$14,A13)*Budget!$F$14 -> 0 | O13: =N("Phone Bill")-COUNTIF(Budget!$G$15, A13)*Budget!$F$15 -> 0 | Q13: =N("Spotify")-IF(AND(DAY($A13)=Budget!$M$3, MONTH($A13)=Budget!$L$3),Budget!$K$3,0) -> 0 | R13: =N("Spotify")-IF(AND(DAY($A13)=Budget!$M$4, MONTH($A13)=Budget!$L$4),Budget!$K$4,0) -> 0 | S13: =N("Spotify")-IF(AND(DAY($A13)=Budget!$M$5, MONTH($A13)=Budget!$L$5),Budget!$K$5,0) -> 0 | T13: =N("Amazon Prime")-IF(DAY(A13)=Budget!$Q$3,Budget!$P$3,0) -> 0 | U13: =N("Audible")-IF(DAY(A13)=Budget!$Q$12,Budget!$P$12,0) -> 0 | V13: =N("Crunchyroll")-IF(DAY(A13)=Budget!$Q$5,Budget!$P$5,0) -> 0 | W13: =N("HBO Max")-IF(DAY(A13)=Budget!$Q$6,Budget!$P$6,0) -> 0 | X13: =N("Netflix")-IF(DAY(A13)=Budget!$Q$7,Budget!$P$7,0) -> 0 | Y13: =N("Spotify")-IF(DAY(A13)=Budget!$Q$8,Budget!$P$8,0) -> 0 | Z13: =N("Truebill")-IF(DAY(A13)=Budget!$Q$9,Budget!$P$9,0) -> 0 | AA13: =SUM(D13:Z13) -> 0
A14: =A13+1 -> 45669 | B14: =B13+AA14 -> 2028.25 | C14: =IF(B14>B13,2,IF(B14=B13, 1,0)) -> 0 | D14: 0 | E14: =N("PAY-LM")+IF(WEEKDAY(A14)=Budget!$C$3,Budget!$B$3,0) -> 0 | F14: =N("Rent")-IF(DAY(A14)=Budget!$G$3,Budget!$F$3,0) -> 0 | G14: =N("Car")-IF(DAY(A14)=Budget!$G$4,Budget!$F$4+Budget!$H$4,0) -> 0 | H14: =N("Mom Rent")-IF(DAY(A14)=Budget!$G$5,Budget!$F$5,0) -> 0 | I14: =N("AT&T")-IF(DAY(A14)=Budget!$G$8,Budget!$F$8,0) -> 0 | J14: =N("GA Power")-IF(DAY(A14)=Budget!$G$9,Budget!$F$9,0) -> 0 | K14: =N("Haircut")-IF(DAY(A14)=Budget!$G$10,Budget!$F$10,0) -> 0 | L14: =N("Groceries")-IF(DAY(A14)=Budget!$G$6,Budget!$F$6,0) -> 0 | M14: =N("Savings")-IF(DAY(A14)=Budget!$G$7,Budget!$F$7,0) -> 0 | N14: =N("Car Insurance")-COUNTIF(Budget!$G$14,A14)*Budget!$F$14 -> 0 | O14: =N("Phone Bill")-COUNTIF(Budget!$G$15, A14)*Budget!$F$15 -> 0 | Q14: =N("Spotify")-IF(AND(DAY($A14)=Budget!$M$3, MONTH($A14)=Budget!$L$3),Budget!$K$3,0) -> 0 | R14: =N("Spotify")-IF(AND(DAY($A14)=Budget!$M$4, MONTH($A14)=Budget!$L$4),Budget!$K$4,0) -> 0 | S14: =N("Spotify")-IF(AND(DAY($A14)=Budget!$M$5, MONTH($A14)=Budget!$L$5),Budget!$K$5,0) -> 0 | T14: =N("Amazon Prime")-IF(DAY(A14)=Budget!$Q$3,Budget!$P$3,0) -> 0 | U14: =N("Audible")-IF(DAY(A14)=Budget!$Q$12,Budget!$P$12,0) -> 0 | V14: =N("Crunchyroll")-IF(DAY(A14)=Budget!$Q$5,Budget!$P$5,0) -> 0 | W14: =N("HBO Max")-IF(DAY(A14)=Budget!$Q$6,Budget!$P$6,0) -> 0 | X14: =N("Netflix")-IF(DAY(A14)=Budget!$Q$7,Budget!$P$7,0) -> -6 | Y14: =N("Spotify")-IF(DAY(A14)=Budget!$Q$8,Budget!$P$8,0) -> 0 | Z14: =N("Truebill")-IF(DAY(A14)=Budget!$Q$9,Budget!$P$9,0) -> 0 | AA14: =SUM(D14:Z14) -> -6
A15: =A14+1 -> 45670 | B15: =B14+AA15 -> 2028.25 | C15: =IF(B15>B14,2,IF(B15=B14, 1,0)) -> 1 | D15: 0 | E15: =N("PAY-LM")+IF(WEEKDAY(A15)=Budget!$C$3,Budget!$B$3,0) -> 0 | F15: =N("Rent")-IF(DAY(A15)=Budget!$G$3,Budget!$F$3,0) -> 0 | G15: =N("Car")-IF(DAY(A15)=Budget!$G$4,Budget!$F$4+Budget!$H$4,0) -> 0 | H15: =N("Mom Rent")-IF(DAY(A15)=Budget!$G$5,Budget!$F$5,0) -> 0 | I15: =N("AT&T")-IF(DAY(A15)=Budget!$G$8,Budget!$F$8,0) -> 0 | J15: =N("GA Power")-IF(DAY(A15)=Budget!$G$9,Budget!$F$9,0) -> 0 | K15: =N("Haircut")-IF(DAY(A15)=Budget!$G$10,Budget!$F$10,0) -> 0 | L15: =N("Groceries")-IF(DAY(A15)=Budget!$G$6,Budget!$F$6,0) -> 0 | M15: =N("Savings")-IF(DAY(A15)=Budget!$G$7,Budget!$F$7,0) -> 0 | N15: =N("Car Insurance")-COUNTIF(Budget!$G$14,A15)*Budget!$F$14 -> 0 | O15: =N("Phone Bill")-COUNTIF(Budget!$G$15, A15)*Budget!$F$15 -> 0 | Q15: =N("Spotify")-IF(AND(DAY($A15)=Budget!$M$3, MONTH($A15)=Budget!$L$3),Budget!$K$3,0) -> 0 | R15: =N("Spotify")-IF(AND(DAY($A15)=Budget!$M$4, MONTH($A15)=Budget!$L$4),Budget!$K$4,0) -> 0 | S15: =N("Spotify")-IF(AND(DAY($A15)=Budget!$M$5, MONTH($A15)=Budget!$L$5),Budget!$K$5,0) -> 0 | T15: =N("Amazon Prime")-IF(DAY(A15)=Budget!$Q$3,Budget!$P$3,0) -> 0 | U15: =N("Audible")-IF(DAY(A15)=Budget!$Q$12,Budget!$P$12,0) -> 0 | V15: =N("Crunchyroll")-IF(DAY(A15)=Budget!$Q$5,Budget!$P$5,0) -> 0 | W15: =N("HBO Max")-IF(DAY(A15)=Budget!$Q$6,Budget!$P$6,0) -> 0 | X15: =N("Netflix")-IF(DAY(A15)=Budget!$Q$7,Budget!$P$7,0) -> 0 | Y15: =N("Spotify")-IF(DAY(A15)=Budget!$Q$8,Budget!$P$8,0) -> 0 | Z15: =N("Truebill")-IF(DAY(A15)=Budget!$Q$9,Budget!$P$9,0) -> 0 | AA15: =SUM(D15:Z15) -> 0
A16: =A15+1 -> 45671 | B16: =B15+AA16 -> 2028.25 | C16: =IF(B16>B15,2,IF(B16=B15, 1,0)) -> 1 | D16: 0 | E16: =N("PAY-LM")+IF(WEEKDAY(A16)=Budget!$C$3,Budget!$B$3,0) -> 0 | F16: =N("Rent")-IF(DAY(A16)=Budget!$G$3,Budget!$F$3,0) -> 0 | G16: =N("Car")-IF(DAY(A16)=Budget!$G$4,Budget!$F$4+Budget!$H$4,0) -> 0 | H16: =N("Mom Rent")-IF(DAY(A16)=Budget!$G$5,Budget!$F$5,0) -> 0 | I16: =N("AT&T")-IF(DAY(A16)=Budget!$G$8,Budget!$F$8,0) -> 0 | J16: =N("GA Power")-IF(DAY(A16)=Budget!$G$9,Budget!$F$9,0) -> 0 | K16: =N("Haircut")-IF(DAY(A16)=Budget!$G$10,Budget!$F$10,0) -> 0 | L16: =N("Groceries")-IF(DAY(A16)=Budget!$G$6,Budget!$F$6,0) -> 0 | M16: =N("Savings")-IF(DAY(A16)=Budget!$G$7,Budget!$F$7,0) -> 0 | N16: =N("Car Insurance")-COUNTIF(Budget!$G$14,A16)*Budget!$F$14 -> 0 | O16: =N("Phone Bill")-COUNTIF(Budget!$G$15, A16)*Budget!$F$15 -> 0 | Q16: =N("Spotify")-IF(AND(DAY($A16)=Budget!$M$3, MONTH($A16)=Budget!$L$3),Budget!$K$3,0) -> 0 | R16: =N("Spotify")-IF(AND(DAY($A16)=Budget!$M$4, MONTH($A16)=Budget!$L$4),Budget!$K$4,0) -> 0 | S16: =N("Spotify")-IF(AND(DAY($A16)=Budget!$M$5, MONTH($A16)=Budget!$L$5),Budget!$K$5,0) -> 0 | T16: =N("Amazon Prime")-IF(DAY(A16)=Budget!$Q$3,Budget!$P$3,0) -> 0 | U16: =N("Audible")-IF(DAY(A16)=Budget!$Q$12,Budget!$P$12,0) -> 0 | V16: =N("Crunchyroll")-IF(DAY(A16)=Budget!$Q$5,Budget!$P$5,0) -> 0 | W16: =N("HBO Max")-IF(DAY(A16)=Budget!$Q$6,Budget!$P$6,0) -> 0 | X16: =N("Netflix")-IF(DAY(A16)=Budget!$Q$7,Budget!$P$7,0) -> 0 | Y16: =N("Spotify")-IF(DAY(A16)=Budget!$Q$8,Budget!$P$8,0) -> 0 | Z16: =N("Truebill")-IF(DAY(A16)=Budget!$Q$9,Budget!$P$9,0) -> 0 | AA16: =SUM(D16:Z16) -> 0
A17: =A16+1 -> 45672 | B17: =B16+AA17 -> 2028.25 | C17: =IF(B17>B16,2,IF(B17=B16, 1,0)) -> 1 | D17: 0 | E17: =N("PAY-LM")+IF(WEEKDAY(A17)=Budget!$C$3,Budget!$B$3,0) -> 0 | F17: =N("Rent")-IF(DAY(A17)=Budget!$G$3,Budget!$F$3,0) -> 0 | G17: =N("Car")-IF(DAY(A17)=Budget!$G$4,Budget!$F$4+Budget!$H$4,0) -> 0 | H17: =N("Mom Rent")-IF(DAY(A17)=Budget!$G$5,Budget!$F$5,0) -> 0 | I17: =N("AT&T")-IF(DAY(A17)=Budget!$G$8,Budget!$F$8,0) -> 0 | J17: =N("GA Power")-IF(DAY(A17)=Budget!$G$9,Budget!$F$9,0) -> 0 | K17: =N("Haircut")-IF(DAY(A17)=Budget!$G$10,Budget!$F$10,0) -> 0 | L17: =N("Groceries")-IF(DAY(A17)=Budget!$G$6,Budget!$F$6,0) -> 0 | M17: =N("Savings")-IF(DAY(A17)=Budget!$G$7,Budget!$F$7,0) -> 0 | N17: =N("Car Insurance")-COUNTIF(Budget!$G$14,A17)*Budget!$F$14 -> 0 | O17: =N("Phone Bill")-COUNTIF(Budget!$G$15, A17)*Budget!$F$15 -> 0 | Q17: =N("Spotify")-IF(AND(DAY($A17)=Budget!$M$3, MONTH($A17)=Budget!$L$3),Budget!$K$3,0) -> 0 | R17: =N("Spotify")-IF(AND(DAY($A17)=Budget!$M$4, MONTH($A17)=Budget!$L$4),Budget!$K$4,0) -> 0 | S17: =N("Spotify")-IF(AND(DAY($A17)=Budget!$M$5, MONTH($A17)=Budget!$L$5),Budget!$K$5,0) -> 0 | T17: =N("Amazon Prime")-IF(DAY(A17)=Budget!$Q$3,Budget!$P$3,0) -> 0 | U17: =N("Audible")-IF(DAY(A17)=Budget!$Q$12,Budget!$P$12,0) -> 0 | V17: =N("Crunchyroll")-IF(DAY(A17)=Budget!$Q$5,Budget!$P$5,0) -> 0 | W17: =N("HBO Max")-IF(DAY(A17)=Budget!$Q$6,Budget!$P$6,0) -> 0 | X17: =N("Netflix")-IF(DAY(A17)=Budget!$Q$7,Budget!$P$7,0) -> 0 | Y17: =N("Spotify")-IF(DAY(A17)=Budget!$Q$8,Budget!$P$8,0) -> 0 | Z17: =N("Truebill")-IF(DAY(A17)=Budget!$Q$9,Budget!$P$9,0) -> 0 | AA17: =SUM(D17:Z17) -> 0
A18: =A17+1 -> 45673 | B18: =B17+AA18 -> 2028.25 | C18: =IF(B18>B17,2,IF(B18=B17, 1,0)) -> 1 | D18: 0 | E18: =N("PAY-LM")+IF(WEEKDAY(A18)=Budget!$C$3,Budget!$B$3,0) -> 0 | F18: =N("Rent")-IF(DAY(A18)=Budget!$G$3,Budget!$F$3,0) -> 0 | G18: =N("Car")-IF(DAY(A18)=Budget!$G$4,Budget!$F$4+Budget!$H$4,0) -> 0 | H18: =N("Mom Rent")-IF(DAY(A18)=Budget!$G$5,Budget!$F$5,0) -> 0 | I18: =N("AT&T")-IF(DAY(A18)=Budget!$G$8,Budget!$F$8,0) -> 0 | J18: =N("GA Power")-IF(DAY(A18)=Budget!$G$9,Budget!$F$9,0) -> 0 | K18: =N("Haircut")-IF(DAY(A18)=Budget!$G$10,Budget!$F$10,0) -> 0 | L18: =N("Groceries")-IF(DAY(A18)=Budget!$G$6,Budget!$F$6,0) -> 0 | M18: =N("Savings")-IF(DAY(A18)=Budget!$G$7,Budget!$F$7,0) -> 0 | N18: =N("Car Insurance")-COUNTIF(Budget!$G$14,A18)*Budget!$F$14 -> 0 | O18: =N("Phone Bill")-COUNTIF(Budget!$G$15, A18)*Budget!$F$15 -> 0 | Q18: =N("Spotify")-IF(AND(DAY($A18)=Budget!$M$3, MONTH($A18)=Budget!$L$3),Budget!$K$3,0) -> 0 | R18: =N("Spotify")-IF(AND(DAY($A18)=Budget!$M$4, MONTH($A18)=Budget!$L$4),Budget!$K$4,0) -> 0 | S18: =N("Spotify")-IF(AND(DAY($A18)=Budget!$M$5, MONTH($A18)=Budget!$L$5),Budget!$K$5,0) -> 0 | T18: =N("Amazon Prime")-IF(DAY(A18)=Budget!$Q$3,Budget!$P$3,0) -> 0 | U18: =N("Audible")-IF(DAY(A18)=Budget!$Q$12,Budget!$P$12,0) -> 0 | V18: =N("Crunchyroll")-IF(DAY(A18)=Budget!$Q$5,Budget!$P$5,0) -> 0 | W18: =N("HBO Max")-IF(DAY(A18)=Budget!$Q$6,Budget!$P$6,0) -> 0 | X18: =N("Netflix")-IF(DAY(A18)=Budget!$Q$7,Budget!$P$7,0) -> 0 | Y18: =N("Spotify")-IF(DAY(A18)=Budget!$Q$8,Budget!$P$8,0) -> 0 | Z18: =N("Truebill")-IF(DAY(A18)=Budget!$Q$9,Budget!$P$9,0) -> 0 | AA18: =SUM(D18:Z18) -> 0
A19: =A18+1 -> 45674 | B19: =B18+AA19 -> 3481.25 | C19: =IF(B19>B18,2,IF(B19=B18, 1,0)) -> 2 | D19: 0 | E19: =N("PAY-LM")+IF(WEEKDAY(A19)=Budget!$C$3,Budget!$B$3,0) -> 1453 | F19: =N("Rent")-IF(DAY(A19)=Budget!$G$3,Budget!$F$3,0) -> 0 | G19: =N("Car")-IF(DAY(A19)=Budget!$G$4,Budget!$F$4+Budget!$H$4,0) -> 0 | H19: =N("Mom Rent")-IF(DAY(A19)=Budget!$G$5,Budget!$F$5,0) -> 0 | I19: =N("AT&T")-IF(DAY(A19)=Budget!$G$8,Budget!$F$8,0) -> 0 | J19: =N("GA Power")-IF(DAY(A19)=Budget!$G$9,Budget!$F$9,0) -> 0 | K19: =N("Haircut")-IF(DAY(A19)=Budget!$G$10,Budget!$F$10,0) -> 0 | L19: =N("Groceries")-IF(DAY(A19)=Budget!$G$6,Budget!$F$6,0) -> 0 | M19: =N("Savings")-IF(DAY(A19)=Budget!$G$7,Budget!$F$7,0) -> 0 | N19: =N("Car Insurance")-COUNTIF(Budget!$G$14,A19)*Budget!$F$14 -> 0 | O19: =N("Phone Bill")-COUNTIF(Budget!$G$15, A19)*Budget!$F$15 -> 0 | Q19: =N("Spotify")-IF(AND(DAY($A19)=Budget!$M$3, MONTH($A19)=Budget!$L$3),Budget!$K$3,0) -> 0 | R19: =N("Spotify")-IF(AND(DAY($A19)=Budget!$M$4, MONTH($A19)=Budget!$L$4),Budget!$K$4,0) -> 0 | S19: =N("Spotify")-IF(AND(DAY($A19)=Budget!$M$5, MONTH($A19)=Budget!$L$5),Budget!$K$5,0) -> 0 | T19: =N("Amazon Prime")-IF(DAY(A19)=Budget!$Q$3,Budget!$P$3,0) -> 0 | U19: =N("Audible")-IF(DAY(A19)=Budget!$Q$12,Budget!$P$12,0) -> 0 | V19: =N("Crunchyroll")-IF(DAY(A19)=Budget!$Q$5,Budget!$P$5,0) -> 0 | W19: =N("HBO Max")-IF(DAY(A19)=Budget!$Q$6,Budget!$P$6,0) -> 0 | X19: =N("Netflix")-IF(DAY(A19)=Budget!$Q$7,Budget!$P$7,0) -> 0 | Y19: =N("Spotify")-IF(DAY(A19)=Budget!$Q$8,Budget!$P$8,0) -> 0 | Z19: =N("Truebill")-IF(DAY(A19)=Budget!$Q$9,Budget!$P$9,0) -> 0 | AA19: =SUM(D19:Z19) -> 1453
A20: =A19+1 -> 45675 | B20: =B19+AA20 -> 3416.25 | C20: =IF(B20>B19,2,IF(B20=B19, 1,0)) -> 0 | D20: 0 | E20: =N("PAY-LM")+IF(WEEKDAY(A20)=Budget!$C$3,Budget!$B$3,0) -> 0 | F20: =N("Rent")-IF(DAY(A20)=Budget!$G$3,Budget!$F$3,0) -> 0 | G20: =N("Car")-IF(DAY(A20)=Budget!$G$4,Budget!$F$4+Budget!$H$4,0) -> 0 | H20: =N("Mom Rent")-IF(DAY(A20)=Budget!$G$5,Budget!$F$5,0) -> 0 | I20: =N("AT&T")-IF(DAY(A20)=Budget!$G$8,Budget!$F$8,0) -> -65 | J20: =N("GA Power")-IF(DAY(A20)=Budget!$G$9,Budget!$F$9,0) -> 0 | K20: =N("Haircut")-IF(DAY(A20)=Budget!$G$10,Budget!$F$10,0) -> 0 | L20: =N("Groceries")-IF(DAY(A20)=Budget!$G$6,Budget!$F$6,0) -> 0 | M20: =N("Savings")-IF(DAY(A20)=Budget!$G$7,Budget!$F$7,0) -> 0 | N20: =N("Car Insurance")-COUNTIF(Budget!$G$14,A20)*Budget!$F$14 -> 0 | O20: =N("Phone Bill")-COUNTIF(Budget!$G$15, A20)*Budget!$F$15 -> 0 | Q20: =N("Spotify")-IF(AND(DAY($A20)=Budget!$M$3, MONTH($A20)=Budget!$L$3),Budget!$K$3,0) -> 0 | R20: =N("Spotify")-IF(AND(DAY($A20)=Budget!$M$4, MONTH($A20)=Budget!$L$4),Budget!$K$4,0) -> 0 | S20: =N("Spotify")-IF(AND(DAY($A20)=Budget!$M$5, MONTH($A20)=Budget!$L$5),Budget!$K$5,0) -> 0 | T20: =N("Amazon Prime")-IF(DAY(A20)=Budget!$Q$3,Budget!$P$3,0) -> 0 | U20: =N("Audible")-IF(DAY(A20)=Budget!$Q$12,Budget!$P$12,0) -> 0 | V20: =N("Crunchyroll")-IF(DAY(A20)=Budget!$Q$5,Budget!$P$5,0) -> 0 | W20: =N("HBO Max")-IF(DAY(A20)=Budget!$Q$6,Budget!$P$6,0) -> 0 | X20: =N("Netflix")-IF(DAY(A20)=Budget!$Q$7,Budget!$P$7,0) -> 0 | Y20: =N("Spotify")-IF(DAY(A20)=Budget!$Q$8,Budget!$P$8,0) -> 0 | Z20: =N("Truebill")-IF(DAY(A20)=Budget!$Q$9,Budget!$P$9,0) -> 0 | AA20: =SUM(D20:Z20) -> -65
A21: =A20+1 -> 45676 | B21: =B20+AA21 -> 3416.25 | C21: =IF(B21>B20,2,IF(B21=B20, 1,0)) -> 1 | D21: 0 | E21: =N("PAY-LM")+IF(WEEKDAY(A21)=Budget!$C$3,Budget!$B$3,0) -> 0 | F21: =N("Rent")-IF(DAY(A21)=Budget!$G$3,Budget!$F$3,0) -> 0 | G21: =N("Car")-IF(DAY(A21)=Budget!$G$4,Budget!$F$4+Budget!$H$4,0) -> 0 | H21: =N("Mom Rent")-IF(DAY(A21)=Budget!$G$5,Budget!$F$5,0) -> 0 | I21: =N("AT&T")-IF(DAY(A21)=Budget!$G$8,Budget!$F$8,0) -> 0 | J21: =N("GA Power")-IF(DAY(A21)=Budget!$G$9,Budget!$F$9,0) -> 0 | K21: =N("Haircut")-IF(DAY(A21)=Budget!$G$10,Budget!$F$10,0) -> 0 | L21: =N("Groceries")-IF(DAY(A21)=Budget!$G$6,Budget!$F$6,0) -> 0 | M21: =N("Savings")-IF(DAY(A21)=Budget!$G$7,Budget!$F$7,0) -> 0 | N21: =N("Car Insurance")-COUNTIF(Budget!$G$14,A21)*Budget!$F$14 -> 0 | O21: =N("Phone Bill")-COUNTIF(Budget!$G$15, A21)*Budget!$F$15 -> 0 | Q21: =N("Spotify")-IF(AND(DAY($A21)=Budget!$M$3, MONTH($A21)=Budget!$L$3),Budget!$K$3,0) -> 0 | R21: =N("Spotify")-IF(AND(DAY($A21)=Budget!$M$4, MONTH($A21)=Budget!$L$4),Budget!$K$4,0) -> 0 | S21: =N("Spotify")-IF(AND(DAY($A21)=Budget!$M$5, MONTH($A21)=Budget!$L$5),Budget!$K$5,0) -> 0 | T21: =N("Amazon Prime")-IF(DAY(A21)=Budget!$Q$3,Budget!$P$3,0) -> 0 | U21: =N("Audible")-IF(DAY(A21)=Budget!$Q$12,Budget!$P$12,0) -> 0 | V21: =N("Crunchyroll")-IF(DAY(A21)=Budget!$Q$5,Budget!$P$5,0) -> 0 | W21: =N("HBO Max")-IF(DAY(A21)=Budget!$Q$6,Budget!$P$6,0) -> 0 | X21: =N("Netflix")-IF(DAY(A21)=Budget!$Q$7,Budget!$P$7,0) -> 0 | Y21: =N("Spotify")-IF(DAY(A21)=Budget!$Q$8,Budget!$P$8,0) -> 0 | Z21: =N("Truebill")-IF(DAY(A21)=Budget!$Q$9,Budget!$P$9,0) -> 0 | AA21: =SUM(D21:Z21) -> 0
A22: =A21+1 -> 45677 | B22: 1937.77 | C22: =IF(B22>B21,2,IF(B22=B21, 1,0)) -> 0 | D22: 0 | E22: =N("PAY-LM")+IF(WEEKDAY(A22)=Budget!$C$3,Budget!$B$3,0) -> 0 | F22: =N("Rent")-IF(DAY(A22)=Budget!$G$3,Budget!$F$3,0) -> 0 | G22: =N("Car")-IF(DAY(A22)=Budget!$G$4,Budget!$F$4+Budget!$H$4,0) -> 0 | H22: =N("Mom Rent")-IF(DAY(A22)=Budget!$G$5,Budget!$F$5,0) -> -850 | I22: =N("AT&T")-IF(DAY(A22)=Budget!$G$8,Budget!$F$8,0) -> 0 | J22: =N("GA Power")-IF(DAY(A22)=Budget!$G$9,Budget!$F$9,0) -> 0 | K22: =N("Haircut")-IF(DAY(A22)=Budget!$G$10,Budget!$F$10,0) -> 0 | L22: =N("Groceries")-IF(DAY(A22)=Budget!$G$6,Budget!$F$6,0) -> 0 | M22: =N("Savings")-IF(DAY(A22)=Budget!$G$7,Budget!$F$7,0) -> 0 | N22: =N("Car Insurance")-COUNTIF(Budget!$G$14,A22)*Budget!$F$14 -> 0 | O22: =N("Phone Bill")-COUNTIF(Budget!$G$15, A22)*Budget!$F$15 -> 0 | Q22: =N("Spotify")-IF(AND(DAY($A22)=Budget!$M$3, MONTH($A22)=Budget!$L$3),Budget!$K$3,0) -> 0 | R22: =N("Spotify")-IF(AND(DAY($A22)=Budget!$M$4, MONTH($A22)=Budget!$L$4),Budget!$K$4,0) -> 0 | S22: =N("Spotify")-IF(AND(DAY($A22)=Budget!$M$5, MONTH($A22)=Budget!$L$5),Budget!$K$5,0) -> 0 | T22: =N("Amazon Prime")-IF(DAY(A22)=Budget!$Q$3,Budget!$P$3,0) -> 0 | U22: =N("Audible")-IF(DAY(A22)=Budget!$Q$12,Budget!$P$12,0) -> 0 | V22: =N("Crunchyroll")-IF(DAY(A22)=Budget!$Q$5,Budget!$P$5,0) -> 0 | W22: =N("HBO Max")-IF(DAY(A22)=Budget!$Q$6,Budget!$P$6,0) -> 0 | X22: =N("Netflix")-IF(DAY(A22)=Budget!$Q$7,Budget!$P$7,0) -> 0 | Y22: =N("Spotify")-IF(DAY(A22)=Budget!$Q$8,Budget!$P$8,0) -> 0 | Z22: =N("Truebill")-IF(DAY(A22)=Budget!$Q$9,Budget!$P$9,0) -> 0 | AA22: =SUM(D22:Z22) -> -850
A23: =A22+1 -> 45678 | B23: =B22+AA23 -> 1937.77 | C23: =IF(B23>B22,2,IF(B23=B22, 1,0)) -> 1 | D23: 0 | E23: =N("PAY-LM")+IF(WEEKDAY(A23)=Budget!$C$3,Budget!$B$3,0) -> 0 | F23: =N("Rent")-IF(DAY(A23)=Budget!$G$3,Budget!$F$3,0) -> 0 | G23: =N("Car")-IF(DAY(A23)=Budget!$G$4,Budget!$F$4+Budget!$H$4,0) -> 0 | H23: =N("Mom Rent")-IF(DAY(A23)=Budget!$G$5,Budget!$F$5,0) -> 0 | I23: =N("AT&T")-IF(DAY(A23)=Budget!$G$8,Budget!$F$8,0) -> 0 | J23: =N("GA Power")-IF(DAY(A23)=Budget!$G$9,Budget!$F$9,0) -> 0 | K23: =N("Haircut")-IF(DAY(A23)=Budget!$G$10,Budget!$F$10,0) -> 0 | L23: =N("Groceries")-IF(DAY(A23)=Budget!$G$6,Budget!$F$6,0) -> 0 | M23: =N("Savings")-IF(DAY(A23)=Budget!$G$7,Budget!$F$7,0) -> 0 | N23: =N("Car Insurance")-COUNTIF(Budget!$G$14,A23)*Budget!$F$14 -> 0 | O23: =N("Phone Bill")-COUNTIF(Budget!$G$15, A23)*Budget!$F$15 -> 0 | Q23: =N("Spotify")-IF(AND(DAY($A23)=Budget!$M$3, MONTH($A23)=Budget!$L$3),Budget!$K$3,0) -> 0 | R23: =N("Spotify")-IF(AND(DAY($A23)=Budget!$M$4, MONTH($A23)=Budget!$L$4),Budget!$K$4,0) -> 0 | S23: =N("Spotify")-IF(AND(DAY($A23)=Budget!$M$5, MONTH($A23)=Budget!$L$5),Budget!$K$5,0) -> 0 | T23: =N("Amazon Prime")-IF(DAY(A23)=Budget!$Q$3,Budget!$P$3,0) -> 0 | U23: =N("Audible")-IF(DAY(A23)=Budget!$Q$12,Budget!$P$12,0) -> 0 | V23: =N("Crunchyroll")-IF(DAY(A23)=Budget!$Q$5,Budget!$P$5,0) -> 0 | W23: =N("HBO Max")-IF(DAY(A23)=Budget!$Q$6,Budget!$P$6,0) -> 0 | X23: =N("Netflix")-IF(DAY(A23)=Budget!$Q$7,Budget!$P$7,0) -> 0 | Y23: =N("Spotify")-IF(DAY(A23)=Budget!$Q$8,Budget!$P$8,0) -> 0 | Z23: =N("Truebill")-IF(DAY(A23)=Budget!$Q$9,Budget!$P$9,0) -> 0 | AA23: =SUM(D23:Z23) -> 0
A24: =A23+1 -> 45679 | B24: =B23+AA24 -> 1937.77 | C24: =IF(B24>B23,2,IF(B24=B23, 1,0)) -> 1 | D24: 0 | E24: =N("PAY-LM")+IF(WEEKDAY(A24)=Budget!$C$3,Budget!$B$3,0) -> 0 | F24: =N("Rent")-IF(DAY(A24)=Budget!$G$3,Budget!$F$3,0) -> 0 | G24: =N("Car")-IF(DAY(A24)=Budget!$G$4,Budget!$F$4+Budget!$H$4,0) -> 0 | H24: =N("Mom Rent")-IF(DAY(A24)=Budget!$G$5,Budget!$F$5,0) -> 0 | I24: =N("AT&T")-IF(DAY(A24)=Budget!$G$8,Budget!$F$8,0) -> 0 | J24: =N("GA Power")-IF(DAY(A24)=Budget!$G$9,Budget!$F$9,0) -> 0 | K24: =N("Haircut")-IF(DAY(A24)=Budget!$G$10,Budget!$F$10,0) -> 0 | L24: =N("Groceries")-IF(DAY(A24)=Budget!$G$6,Budget!$F$6,0) -> 0 | M24: =N("Savings")-IF(DAY(A24)=Budget!$G$7,Budget!$F$7,0) -> 0 | N24: =N("Car Insurance")-COUNTIF(Budget!$G$14,A24)*Budget!$F$14 -> 0 | O24: =N("Phone Bill")-COUNTIF(Budget!$G$15, A24)*Budget!$F$15 -> 0 | Q24: =N("Spotify")-IF(AND(DAY($A24)=Budget!$M$3, MONTH($A24)=Budget!$L$3),Budget!$K$3,0) -> 0 | R24: =N("Spotify")-IF(AND(DAY($A24)=Budget!$M$4, MONTH($A24)=Budget!$L$4),Budget!$K$4,0) -> 0 | S24: =N("Spotify")-IF(AND(DAY($A24)=Budget!$M$5, MONTH($A24)=Budget!$L$5),Budget!$K$5,0) -> 0 | T24: =N("Amazon Prime")-IF(DAY(A24)=Budget!$Q$3,Budget!$P$3,0) -> 0 | U24: =N("Audible")-IF(DAY(A24)=Budget!$Q$12,Budget!$P$12,0) -> 0 | V24: =N("Crunchyroll")-IF(DAY(A24)=Budget!$Q$5,Budget!$P$5,0) -> 0 | W24: =N("HBO Max")-IF(DAY(A24)=Budget!$Q$6,Budget!$P$6,0) -> 0 | X24: =N("Netflix")-IF(DAY(A24)=Budget!$Q$7,Budget!$P$7,0) -> 0 | Y24: =N("Spotify")-IF(DAY(A24)=Budget!$Q$8,Budget!$P$8,0) -> 0 | Z24: =N("Truebill")-IF(DAY(A24)=Budget!$Q$9,Budget!$P$9,0) -> 0 | AA24: =SUM(D24:Z24) -> 0
A25: =A24+1 -> 45680 | B25: =B24+AA25 -> 1937.77 | C25: =IF(B25>B24,2,IF(B25=B24, 1,0)) -> 1 | D25: 0 | E25: =N("PAY-LM")+IF(WEEKDAY(A25)=Budget!$C$3,Budget!$B$3,0) -> 0 | F25: =N("Rent")-IF(DAY(A25)=Budget!$G$3,Budget!$F$3,0) -> 0 | G25: =N("Car")-IF(DAY(A25)=Budget!$G$4,Budget!$F$4+Budget!$H$4,0) -> 0 | H25: =N("Mom Rent")-IF(DAY(A25)=Budget!$G$5,Budget!$F$5,0) -> 0 | I25: =N("AT&T")-IF(DAY(A25)=Budget!$G$8,Budget!$F$8,0) -> 0 | J25: =N("GA Power")-IF(DAY(A25)=Budget!$G$9,Budget!$F$9,0) -> 0 | K25: =N("Haircut")-IF(DAY(A25)=Budget!$G$10,Budget!$F$10,0) -> 0 | L25: =N("Groceries")-IF(DAY(A25)=Budget!$G$6,Budget!$F$6,0) -> 0 | M25: =N("Savings")-IF(DAY(A25)=Budget!$G$7,Budget!$F$7,0) -> 0 | N25: =N("Car Insurance")-COUNTIF(Budget!$G$14,A25)*Budget!$F$14 -> 0 | O25: =N("Phone Bill")-COUNTIF(Budget!$G$15, A25)*Budget!$F$15 -> 0 | Q25: =N("Spotify")-IF(AND(DAY($A25)=Budget!$M$3, MONTH($A25)=Budget!$L$3),Budget!$K$3,0) -> 0 | R25: =N("Spotify")-IF(AND(DAY($A25)=Budget!$M$4, MONTH($A25)=Budget!$L$4),Budget!$K$4,0) -> 0 | S25: =N("Spotify")-IF(AND(DAY($A25)=Budget!$M$5, MONTH($A25)=Budget!$L$5),Budget!$K$5,0) -> 0 | T25: =N("Amazon Prime")-IF(DAY(A25)=Budget!$Q$3,Budget!$P$3,0) -> 0 | U25: =N("Audible")-IF(DAY(A25)=Budget!$Q$12,Budget!$P$12,0) -> 0 | V25: =N("Crunchyroll")-IF(DAY(A25)=Budget!$Q$5,Budget!$P$5,0) -> 0 | W25: =N("HBO Max")-IF(DAY(A25)=Budget!$Q$6,Budget!$P$6,0) -> 0 | X25: =N("Netflix")-IF(DAY(A25)=Budget!$Q$7,Budget!$P$7,0) -> 0 | Y25: =N("Spotify")-IF(DAY(A25)=Budget!$Q$8,Budget!$P$8,0) -> 0 | Z25: =N("Truebill")-IF(DAY(A25)=Budget!$Q$9,Budget!$P$9,0) -> 0 | AA25: =SUM(D25:Z25) -> 0
A26: =A25+1 -> 45681 | B26: =B25+AA26 -> 3390.77 | C26: =IF(B26>B25,2,IF(B26=B25, 1,0)) -> 2 | D26: 0 | E26: =N("PAY-LM")+IF(WEEKDAY(A26)=Budget!$C$3,Budget!$B$3,0) -> 1453 | F26: =N("Rent")-IF(DAY(A26)=Budget!$G$3,Budget!$F$3,0) -> 0 | G26: =N("Car")-IF(DAY(A26)=Budget!$G$4,Budget!$F$4+Budget!$H$4,0) -> 0 | H26: =N("Mom Rent")-IF(DAY(A26)=Budget!$G$5,Budget!$F$5,0) -> 0 | I26: =N("AT&T")-IF(DAY(A26)=Budget!$G$8,Budget!$F$8,0) -> 0 | J26: =N("GA Power")-IF(DAY(A26)=Budget!$G$9,Budget!$F$9,0) -> 0 | K26: =N("Haircut")-IF(DAY(A26)=Budget!$G$10,Budget!$F$10,0) -> 0 | L26: =N("Groceries")-IF(DAY(A26)=Budget!$G$6,Budget!$F$6,0) -> 0 | M26: =N("Savings")-IF(DAY(A26)=Budget!$G$7,Budget!$F$7,0) -> 0 | N26: =N("Car Insurance")-COUNTIF(Budget!$G$14,A26)*Budget!$F$14 -> 0 | O26: =N("Phone Bill")-COUNTIF(Budget!$G$15, A26)*Budget!$F$15 -> 0 | Q26: =N("Spotify")-IF(AND(DAY($A26)=Budget!$M$3, MONTH($A26)=Budget!$L$3),Budget!$K$3,0) -> 0 | R26: =N("Spotify")-IF(AND(DAY($A26)=Budget!$M$4, MONTH($A26)=Budget!$L$4),Budget!$K$4,0) -> 0 | S26: =N("Spotify")-IF(AND(DAY($A26)=Budget!$M$5, MONTH($A26)=Budget!$L$5),Budget!$K$5,0) -> 0 | T26: =N("Amazon Prime")-IF(DAY(A26)=Budget!$Q$3,Budget!$P$3,0) -> 0 | U26: =N("Audible")-IF(DAY(A26)=Budget!$Q$12,Budget!$P$12,0) -> 0 | V26: =N("Crunchyroll")-IF(DAY(A26)=Budget!$Q$5,Budget!$P$5,0) -> 0 | W26: =N("HBO Max")-IF(DAY(A26)=Budget!$Q$6,Budget!$P$6,0) -> 0 | X26: =N("Netflix")-IF(DAY(A26)=Budget!$Q$7,Budget!$P$7,0) -> 0 | Y26: =N("Spotify")-IF(DAY(A26)=Budget!$Q$8,Budget!$P$8,0) -> 0 | Z26: =N("Truebill")-IF(DAY(A26)=Budget!$Q$9,Budget!$P$9,0) -> 0 | AA26: =SUM(D26:Z26) -> 1453
A27: =A26+1 -> 45682 | B27: =B26+AA27 -> 3390.77 | C27: =IF(B27>B26,2,IF(B27=B26, 1,0)) -> 1 | D27: 0 | E27: =N("PAY-LM")+IF(WEEKDAY(A27)=Budget!$C$3,Budget!$B$3,0) -> 0 | F27: =N("Rent")-IF(DAY(A27)=Budget!$G$3,Budget!$F$3,0) -> 0 | G27: =N("Car")-IF(DAY(A27)=Budget!$G$4,Budget!$F$4+Budget!$H$4,0) -> 0 | H27: =N("Mom Rent")-IF(DAY(A27)=Budget!$G$5,Budget!$F$5,0) -> 0 | I27: =N("AT&T")-IF(DAY(A27)=Budget!$G$8,Budget!$F$8,0) -> 0 | J27: =N("GA Power")-IF(DAY(A27)=Budget!$G$9,Budget!$F$9,0) -> 0 | K27: =N("Haircut")-IF(DAY(A27)=Budget!$G$10,Budget!$F$10,0) -> 0 | L27: =N("Groceries")-IF(DAY(A27)=Budget!$G$6,Budget!$F$6,0) -> 0 | M27: =N("Savings")-IF(DAY(A27)=Budget!$G$7,Budget!$F$7,0) -> 0 | N27: =N("Car Insurance")-COUNTIF(Budget!$G$14,A27)*Budget!$F$14 -> 0 | O27: =N("Phone Bill")-COUNTIF(Budget!$G$15, A27)*Budget!$F$15 -> 0 | Q27: =N("Spotify")-IF(AND(DAY($A27)=Budget!$M$3, MONTH($A27)=Budget!$L$3),Budget!$K$3,0) -> 0 | R27: =N("Spotify")-IF(AND(DAY($A27)=Budget!$M$4, MONTH($A27)=Budget!$L$4),Budget!$K$4,0) -> 0 | S27: =N("Spotify")-IF(AND(DAY($A27)=Budget!$M$5, MONTH($A27)=Budget!$L$5),Budget!$K$5,0) -> 0 | T27: =N("Amazon Prime")-IF(DAY(A27)=Budget!$Q$3,Budget!$P$3,0) -> 0 | U27: =N("Audible")-IF(DAY(A27)=Budget!$Q$12,Budget!$P$12,0) -> 0 | V27: =N("Crunchyroll")-IF(DAY(A27)=Budget!$Q$5,Budget!$P$5,0) -> 0 | W27: =N("HBO Max")-IF(DAY(A27)=Budget!$Q$6,Budget!$P$6,0) -> 0 | X27: =N("Netflix")-IF(DAY(A27)=Budget!$Q$7,Budget!$P$7,0) -> 0 | Y27: =N("Spotify")-IF(DAY(A27)=Budget!$Q$8,Budget!$P$8,0) -> 0 | Z27: =N("Truebill")-IF(DAY(A27)=Budget!$Q$9,Budget!$P$9,0) -> 0 | AA27: =SUM(D27:Z27) -> 0
A28: =A27+1 -> 45683 | B28: =B27+AA28 -> 2990.77 | C28: =IF(B28>B27,2,IF(B28=B27, 1,0)) -> 0 | D28: 0 | E28: =N("PAY-LM")+IF(WEEKDAY(A28)=Budget!$C$3,Budget!$B$3,0) -> 0 | F28: =N("Rent")-IF(DAY(A28)=Budget!$G$3,Budget!$F$3,0) -> 0 | G28: =N("Car")-IF(DAY(A28)=Budget!$G$4,Budget!$F$4+Budget!$H$4,0) -> 0 | H28: =N("Mom Rent")-IF(DAY(A28)=Budget!$G$5,Budget!$F$5,0) -> 0 | I28: =N("AT&T")-IF(DAY(A28)=Budget!$G$8,Budget!$F$8,0) -> 0 | J28: =N("GA Power")-IF(DAY(A28)=Budget!$G$9,Budget!$F$9,0) -> 0 | K28: =N("Haircut")-IF(DAY(A28)=Budget!$G$10,Budget!$F$10,0) -> -400 | L28: =N("Groceries")-IF(DAY(A28)=Budget!$G$6,Budget!$F$6,0) -> 0 | M28: =N("Savings")-IF(DAY(A28)=Budget!$G$7,Budget!$F$7,0) -> 0 | N28: =N("Car Insurance")-COUNTIF(Budget!$G$14,A28)*Budget!$F$14 -> 0 | O28: =N("Phone Bill")-COUNTIF(Budget!$G$15, A28)*Budget!$F$15 -> 0 | Q28: =N("Spotify")-IF(AND(DAY($A28)=Budget!$M$3, MONTH($A28)=Budget!$L$3),Budget!$K$3,0) -> 0 | R28: =N("Spotify")-IF(AND(DAY($A28)=Budget!$M$4, MONTH($A28)=Budget!$L$4),Budget!$K$4,0) -> 0 | S28: =N("Spotify")-IF(AND(DAY($A28)=Budget!$M$5, MONTH($A28)=Budget!$L$5),Budget!$K$5,0) -> 0 | T28: =N("Amazon Prime")-IF(DAY(A28)=Budget!$Q$3,Budget!$P$3,0) -> 0 | U28: =N("Audible")-IF(DAY(A28)=Budget!$Q$12,Budget!$P$12,0) -> 0 | V28: =N("Crunchyroll")-IF(DAY(A28)=Budget!$Q$5,Budget!$P$5,0) -> 0 | W28: =N("HBO Max")-IF(DAY(A28)=Budget!$Q$6,Budget!$P$6,0) -> 0 | X28: =N("Netflix")-IF(DAY(A28)=Budget!$Q$7,Budget!$P$7,0) -> 0 | Y28: =N("Spotify")-IF(DAY(A28)=Budget!$Q$8,Budget!$P$8,0) -> 0 | Z28: =N("Truebill")-IF(DAY(A28)=Budget!$Q$9,Budget!$P$9,0) -> 0 | AA28: =SUM(D28:Z28) -> -400
A29: =A28+1 -> 45684 | B29: =B28+AA29 -> 2990.77 | C29: =IF(B29>B28,2,IF(B29=B28, 1,0)) -> 1 | D29: 0 | E29: =N("PAY-LM")+IF(WEEKDAY(A29)=Budget!$C$3,Budget!$B$3,0) -> 0 | F29: =N("Rent")-IF(DAY(A29)=Budget!$G$3,Budget!$F$3,0) -> 0 | G29: =N("Car")-IF(DAY(A29)=Budget!$G$4,Budget!$F$4+Budget!$H$4,0) -> 0 | H29: =N("Mom Rent")-IF(DAY(A29)=Budget!$G$5,Budget!$F$5,0) -> 0 | I29: =N("AT&T")-IF(DAY(A29)=Budget!$G$8,Budget!$F$8,0) -> 0 | J29: =N("GA Power")-IF(DAY(A29)=Budget!$G$9,Budget!$F$9,0) -> 0 | K29: =N("Haircut")-IF(DAY(A29)=Budget!$G$10,Budget!$F$10,0) -> 0 | L29: =N("Groceries")-IF(DAY(A29)=Budget!$G$6,Budget!$F$6,0) -> 0 | M29: =N("Savings")-IF(DAY(A29)=Budget!$G$7,Budget!$F$7,0) -> 0 | N29: =N("Car Insurance")-COUNTIF(Budget!$G$14,A29)*Budget!$F$14 -> 0 | O29: =N("Phone Bill")-COUNTIF(Budget!$G$15, A29)*Budget!$F$15 -> 0 | Q29: =N("Spotify")-IF(AND(DAY($A29)=Budget!$M$3, MONTH($A29)=Budget!$L$3),Budget!$K$3,0) -> 0 | R29: =N("Spotify")-IF(AND(DAY($A29)=Budget!$M$4, MONTH($A29)=Budget!$L$4),Budget!$K$4,0) -> 0 | S29: =N("Spotify")-IF(AND(DAY($A29)=Budget!$M$5, MONTH($A29)=Budget!$L$5),Budget!$K$5,0) -> 0 | T29: =N("Amazon Prime")-IF(DAY(A29)=Budget!$Q$3,Budget!$P$3,0) -> 0 | U29: =N("Audible")-IF(DAY(A29)=Budget!$Q$12,Budget!$P$12,0) -> 0 | V29: =N("Crunchyroll")-IF(DAY(A29)=Budget!$Q$5,Budget!$P$5,0) -> 0 | W29: =N("HBO Max")-IF(DAY(A29)=Budget!$Q$6,Budget!$P$6,0) -> 0 | X29: =N("Netflix")-IF(DAY(A29)=Budget!$Q$7,Budget!$P$7,0) -> 0 | Y29: =N("Spotify")-IF(DAY(A29)=Budget!$Q$8,Budget!$P$8,0) -> 0 | Z29: =N("Truebill")-IF(DAY(A29)=Budget!$Q$9,Budget!$P$9,0) -> 0 | AA29: =SUM(D29:Z29) -> 0
A30: =A29+1 -> 45685 | B30: 1216 | C30: =IF(B30>B29,2,IF(B30=B29, 1,0)) -> 0 | D30: 0 | E30: =N("PAY-LM")+IF(WEEKDAY(A30)=Budget!$C$3,Budget!$B$3,0) -> 0 | F30: =N("Rent")-IF(DAY(A30)=Budget!$G$3,Budget!$F$3,0) -> 0 | G30: =N("Car")-IF(DAY(A30)=Budget!$G$4,Budget!$F$4+Budget!$H$4,0) -> 0 | H30: =N("Mom Rent")-IF(DAY(A30)=Budget!$G$5,Budget!$F$5,0) -> 0 | I30: =N("AT&T")-IF(DAY(A30)=Budget!$G$8,Budget!$F$8,0) -> 0 | J30: =N("GA Power")-IF(DAY(A30)=Budget!$G$9,Budget!$F$9,0) -> 0 | K30: =N("Haircut")-IF(DAY(A30)=Budget!$G$10,Budget!$F$10,0) -> 0 | L30: =N("Groceries")-IF(DAY(A30)=Budget!$G$6,Budget!$F$6,0) -> 0 | M30: =N("Savings")-IF(DAY(A30)=Budget!$G$7,Budget!$F$7,0) -> -1000 | N30: =N("Car Insurance")-COUNTIF(Budget!$G$14,A30)*Budget!$F$14 -> 0 | O30: =N("Phone Bill")-COUNTIF(Budget!$G$15, A30)*Budget!$F$15 -> 0 | Q30: =N("Spotify")-IF(AND(DAY($A30)=Budget!$M$3, MONTH($A30)=Budget!$L$3),Budget!$K$3,0) -> 0 | R30: =N("Spotify")-IF(AND(DAY($A30)=Budget!$M$4, MONTH($A30)=Budget!$L$4),Budget!$K$4,0) -> 0 | S30: =N("Spotify")-IF(AND(DAY($A30)=Budget!$M$5, MONTH($A30)=Budget!$L$5),Budget!$K$5,0) -> 0 | T30: =N("Amazon Prime")-IF(DAY(A30)=Budget!$Q$3,Budget!$P$3,0) -> 0 | U30: =N("Audible")-IF(DAY(A30)=Budget!$Q$12,Budget!$P$12,0) -> 0 | V30: =N("Crunchyroll")-IF(DAY(A30)=Budget!$Q$5,Budget!$P$5,0) -> 0 | W30: =N("HBO Max")-IF(DAY(A30)=Budget!$Q$6,Budget!$P$6,0) -> 0 | X30: =N("Netflix")-IF(DAY(A30)=Budget!$Q$7,Budget!$P$7,0) -> 0 | Y30: =N("Spotify")-IF(DAY(A30)=Budget!$Q$8,Budget!$P$8,0) -> -150 | Z30: =N("Truebill")-IF(DAY(A30)=Budget!$Q$9,Budget!$P$9,0) -> 0 | AA30: =SUM(D30:Z30) -> -1150
A31: =A30+1 -> 45686 | B31: =B30+AA31 -> 1191.4 | C31: =IF(B31>B30,2,IF(B31=B30, 1,0)) -> 0 | D31: 0 | E31: =N("PAY-LM")+IF(WEEKDAY(A31)=Budget!$C$3,Budget!$B$3,0) -> 0 | F31: =N("Rent")-IF(DAY(A31)=Budget!$G$3,Budget!$F$3,0) -> 0 | G31: =N("Car")-IF(DAY(A31)=Budget!$G$4,Budget!$F$4+Budget!$H$4,0) -> 0 | H31: =N("Mom Rent")-IF(DAY(A31)=Budget!$G$5,Budget!$F$5,0) -> 0 | I31: =N("AT&T")-IF(DAY(A31)=Budget!$G$8,Budget!$F$8,0) -> 0 | J31: =N("GA Power")-IF(DAY(A31)=Budget!$G$9,Budget!$F$9,0) -> 0 | K31: =N("Haircut")-IF(DAY(A31)=Budget!$G$10,Budget!$F$10,0) -> 0 | L31: =N("Groceries")-IF(DAY(A31)=Budget!$G$6,Budget!$F$6,0) -> 0 | M31: =N("Savings")-IF(DAY(A31)=Budget!$G$7,Budget!$F$7,0) -> 0 | N31: =N("Car Insurance")-COUNTIF(Budget!$G$14,A31)*Budget!$F$14 -> 0 | O31: =N("Phone Bill")-COUNTIF(Budget!$G$15, A31)*Budget!$F$15 -> 0 | Q31: =N("Spotify")-IF(AND(DAY($A31)=Budget!$M$3, MONTH($A31)=Budget!$L$3),Budget!$K$3,0) -> 0 | R31: =N("Spotify")-IF(AND(DAY($A31)=Budget!$M$4, MONTH($A31)=Budget!$L$4),Budget!$K$4,0) -> 0 | S31: =N("Spotify")-IF(AND(DAY($A31)=Budget!$M$5, MONTH($A31)=Budget!$L$5),Budget!$K$5,0) -> 0 | T31: =N("Amazon Prime")-IF(DAY(A31)=Budget!$Q$3,Budget!$P$3,0) -> 0 | U31: =N("Audible")-IF(DAY(A31)=Budget!$Q$12,Budget!$P$12,0) -> 0 | V31: =N("Crunchyroll")-IF(DAY(A31)=Budget!$Q$5,Budget!$P$5,0) -> -24.6 | W31: =N("HBO Max")-IF(DAY(A31)=Budget!$Q$6,Budget!$P$6,0) -> 0 | X31: =N("Netflix")-IF(DAY(A31)=Budget!$Q$7,Budget!$P$7,0) -> 0 | Y31: =N("Spotify")-IF(DAY(A31)=Budget!$Q$8,Budget!$P$8,0) -> 0 | Z31: =N("Truebill")-IF(DAY(A31)=Budget!$Q$9,Budget!$P$9,0) -> 0 | AA31: =SUM(D31:Z31) -> -24.6
A32: =A31+1 -> 45687 | B32: =B31+AA32 -> 1191.4 | C32: =IF(B32>B31,2,IF(B32=B31, 1,0)) -> 1 | D32: 0 | E32: =N("PAY-LM")+IF(WEEKDAY(A32)=Budget!$C$3,Budget!$B$3,0) -> 0 | F32: =N("Rent")-IF(DAY(A32)=Budget!$G$3,Budget!$F$3,0) -> 0 | G32: =N("Car")-IF(DAY(A32)=Budget!$G$4,Budget!$F$4+Budget!$H$4,0) -> 0 | H32: =N("Mom Rent")-IF(DAY(A32)=Budget!$G$5,Budget!$F$5,0) -> 0 | I32: =N("AT&T")-IF(DAY(A32)=Budget!$G$8,Budget!$F$8,0) -> 0 | J32: =N("GA Power")-IF(DAY(A32)=Budget!$G$9,Budget!$F$9,0) -> 0 | K32: =N("Haircut")-IF(DAY(A32)=Budget!$G$10,Budget!$F$10,0) -> 0 | L32: =N("Groceries")-IF(DAY(A32)=Budget!$G$6,Budget!$F$6,0) -> 0 | M32: =N("Savings")-IF(DAY(A32)=Budget!$G$7,Budget!$F$7,0) -> 0 | N32: =N("Car Insurance")-COUNTIF(Budget!$G$14,A32)*Budget!$F$14 -> 0 | O32: =N("Phone Bill")-COUNTIF(Budget!$G$15, A32)*Budget!$F$15 -> 0 | Q32: =N("Spotify")-IF(AND(DAY($A32)=Budget!$M$3, MONTH($A32)=Budget!$L$3),Budget!$K$3,0) -> 0 | R32: =N("Spotify")-IF(AND(DAY($A32)=Budget!$M$4, MONTH($A32)=Budget!$L$4),Budget!$K$4,0) -> 0 | S32: =N("Spotify")-IF(AND(DAY($A32)=Budget!$M$5, MONTH($A32)=Budget!$L$5),Budget!$K$5,0) -> 0 | T32: =N("Amazon Prime")-IF(DAY(A32)=Budget!$Q$3,Budget!$P$3,0) -> 0 | U32: =N("Audible")-IF(DAY(A32)=Budget!$Q$12,Budget!$P$12,0) -> 0 | V32: =N("Crunchyroll")-IF(DAY(A32)=Budget!$Q$5,Budget!$P$5,0) -> 0 | W32: =N("HBO Max")-IF(DAY(A32)=Budget!$Q$6,Budget!$P$6,0) -> 0 | X32: =N("Netflix")-IF(DAY(A32)=Budget!$Q$7,Budget!$P$7,0) -> 0 | Y32: =N("Spotify")-IF(DAY(A32)=Budget!$Q$8,Budget!$P$8,0) -> 0 | Z32: =N("Truebill")-IF(DAY(A32)=Budget!$Q$9,Budget!$P$9,0) -> 0 | AA32: =SUM(D32:Z32) -> 0
A33: =A32+1 -> 45688 | B33: =B32+AA33 -> 2644.4 | C33: =IF(B33>B32,2,IF(B33=B32, 1,0)) -> 2 | D33: 0 | E33: =N("PAY-LM")+IF(WEEKDAY(A33)=Budget!$C$3,Budget!$B$3,0) -> 1453 | F33: =N("Rent")-IF(DAY(A33)=Budget!$G$3,Budget!$F$3,0) -> 0 | G33: =N("Car")-IF(DAY(A33)=Budget!$G$4,Budget!$F$4+Budget!$H$4,0) -> 0 | H33: =N("Mom Rent")-IF(DAY(A33)=Budget!$G$5,Budget!$F$5,0) -> 0 | I33: =N("AT&T")-IF(DAY(A33)=Budget!$G$8,Budget!$F$8,0) -> 0 | J33: =N("GA Power")-IF(DAY(A33)=Budget!$G$9,Budget!$F$9,0) -> 0 | K33: =N("Haircut")-IF(DAY(A33)=Budget!$G$10,Budget!$F$10,0) -> 0 | L33: =N("Groceries")-IF(DAY(A33)=Budget!$G$6,Budget!$F$6,0) -> 0 | M33: =N("Savings")-IF(DAY(A33)=Budget!$G$7,Budget!$F$7,0) -> 0 | N33: =N("Car Insurance")-COUNTIF(Budget!$G$14,A33)*Budget!$F$14 -> 0 | O33: =N("Phone Bill")-COUNTIF(Budget!$G$15, A33)*Budget!$F$15 -> 0 | Q33: =N("Spotify")-IF(AND(DAY($A33)=Budget!$M$3, MONTH($A33)=Budget!$L$3),Budget!$K$3,0) -> 0 | R33: =N("Spotify")-IF(AND(DAY($A33)=Budget!$M$4, MONTH($A33)=Budget!$L$4),Budget!$K$4,0) -> 0 | S33: =N("Spotify")-IF(AND(DAY($A33)=Budget!$M$5, MONTH($A33)=Budget!$L$5),Budget!$K$5,0) -> 0 | T33: =N("Amazon Prime")-IF(DAY(A33)=Budget!$Q$3,Budget!$P$3,0) -> 0 | U33: =N("Audible")-IF(DAY(A33)=Budget!$Q$12,Budget!$P$12,0) -> 0 | V33: =N("Crunchyroll")-IF(DAY(A33)=Budget!$Q$5,Budget!$P$5,0) -> 0 | W33: =N("HBO Max")-IF(DAY(A33)=Budget!$Q$6,Budget!$P$6,0) -> 0 | X33: =N("Netflix")-IF(DAY(A33)=Budget!$Q$7,Budget!$P$7,0) -> 0 | Y33: =N("Spotify")-IF(DAY(A33)=Budget!$Q$8,Budget!$P$8,0) -> 0 | Z33: =N("Truebill")-IF(DAY(A33)=Budget!$Q$9,Budget!$P$9,0) -> 0 | AA33: =SUM(D33:Z33) -> 1453
D35: Miscellaneous | E35: Monthly Expenses | N35: =Budget!$E$12 -> Annual Expenses | Q35: Credit Card | T35: Subscriptions | AA35: TOTAL | AC35: =SUMIF(D37:Z64,"<0") -> -5257.82 | AD35: =SUM(E37:E64) -> 5812
A36: =EDATE(A2,1) -> 45689 | E36: =Budget!$A$3 -> PAY-LM | F36: =Budget!$E$3 -> Rent | G36: =Budget!$E$4 -> Car | H36: =Budget!$E$5 -> Mom Rent | I36: =Budget!$E$8 -> AT&T | J36: =Budget!$E$9 -> GA Power | K36: =Budget!$E$10 -> TH | L36: =Budget!$E$6 -> Groceries | M36: =Budget!$E$7 -> Savings | N36: =Budget!$E$14 -> Car Insurance | O36: =Budget!$E$15 -> Phone Bill | Q36: =Budget!$J$3 -> Capital One | R36: =Budget!$J$4 -> Chase | S36: =Budget!$J$5 -> NFCU | T36: =Budget!$O$3 -> Amazon Prime | U36: =Budget!$O$12 -> Audible | V36: =Budget!$O$5 -> Netflix | W36: =Budget!$O$6 -> Spotify | X36: =Budget!$O$7 -> Rocket Money | Y36: =Budget!$O$8 -> Little4Much | Z36: =Budget!$O$9 -> None | AC36: =AD35+AC35 -> 554.18
A37: =A36 -> 45689 | B37: =B33+AA37 -> 911.4 | C37: =IF(B37>B32,2,IF(B37=B32, 1,0)) -> 0 | D37: 0 | E37: =N("PAY-LM")+IF(WEEKDAY(A37)=Budget!$C$3,Budget!$B$3,0) -> 0 | F37: =N("Rent")-IF(DAY(A37)=Budget!$G$3,Budget!$F$3,0) -> -1733 | G37: =N("Car")-IF(DAY(A37)=Budget!$G$4,Budget!$F$4+Budget!$H$4,0) -> 0 | H37: =N("Mom Rent")-IF(DAY(A37)=Budget!$G$5,Budget!$F$5,0) -> 0 | I37: =N("AT&T")-IF(DAY(A37)=Budget!$G$8,Budget!$F$8,0) -> 0 | J37: =N("GA Power")-IF(DAY(A37)=Budget!$G$9,Budget!$F$9,0) -> 0 | K37: =N("Haircut")-IF(DAY(A37)=Budget!$G$10,Budget!$F$10,0) -> 0 | L37: =N("Groceries")-IF(DAY(A37)=Budget!$G$6,Budget!$F$6,0) -> 0 | M37: =N("Savings")-IF(DAY(A37)=Budget!$G$7,Budget!$F$7,0) -> 0 | N37: =N("Car Insurance")-COUNTIF(Budget!$G$14, A37)*Budget!$F$14 -> 0 | O37: =N("Phone Bill")-COUNTIF(Budget!$G$15, A37)*Budget!$F$15 -> 0 | Q37: =N("Spotify")-IF(AND(DAY($A37)=Budget!$M$3, MONTH($A37)=Budget!$L$3),Budget!$K$3,0) -> 0 | R37: =N("Spotify")-IF(AND(DAY($A37)=Budget!$M$4, MONTH($A37)=Budget!$L$4),Budget!$K$4,0) -> 0 | S37: =N("Spotify")-IF(AND(DAY($A37)=Budget!$M$5, MONTH($A37)=Budget!$L$5),Budget!$K$5,0) -> 0 | T37: =N("Amazon Prime")-IF(DAY(A37)=Budget!$Q$3,Budget!$P$3,0) -> 0 | U37: =N("Audible")-IF(DAY(A37)=Budget!$Q$12,Budget!$P$12,0) -> 0 | V37: =N("Crunchyroll")-IF(DAY(A37)=Budget!$Q$5,Budget!$P$5,0) -> 0 | W37: =N("HBO Max")-IF(DAY(A37)=Budget!$Q$6,Budget!$P$6,0) -> 0 | X37: =N("Netflix")-IF(DAY(A37)=Budget!$Q$7,Budget!$P$7,0) -> 0 | Y37: =N("Spotify")-IF(DAY(A37)=Budget!$Q$8,Budget!$P$8,0) -> 0 | Z37: =N("Truebill")-IF(DAY(A37)=Budget!$Q$9,Budget!$P$9,0) -> 0 | AA37: =SUM(D37:Z37) -> -1733
A38: =A37+1 -> 45690 | B38: =B37+AA38 -> 108.05 | C38: =IF(B38>B37,2,IF(B38=B37, 1,0)) -> 0 | D38: 0 | E38: =N("PAY-LM")+IF(WEEKDAY(A38)=Budget!$C$3,Budget!$B$3,0) -> 0 | F38: =N("Rent")-IF(DAY(A38)=Budget!$G$3,Budget!$F$3,0) -> 0 | G38: =N("Car")-IF(DAY(A38)=Budget!$G$4,Budget!$F$4+Budget!$H$4,0) -> -503.35 | H38: =N("Mom Rent")-IF(DAY(A38)=Budget!$G$5,Budget!$F$5,0) -> 0 | I38: =N("AT&T")-IF(DAY(A38)=Budget!$G$8,Budget!$F$8,0) -> 0 | J38: =N("GA Power")-IF(DAY(A38)=Budget!$G$9,Budget!$F$9,0) -> 0 | K38: =N("Haircut")-IF(DAY(A38)=Budget!$G$10,Budget!$F$10,0) -> 0 | L38: =N("Groceries")-IF(DAY(A38)=Budget!$G$6,Budget!$F$6,0) -> -300 | M38: =N("Savings")-IF(DAY(A38)=Budget!$G$7,Budget!$F$7,0) -> 0 | N38: =N("Car Insurance")-COUNTIF(Budget!$G$14, A38)*Budget!$F$14 -> 0 | O38: =N("Phone Bill")-COUNTIF(Budget!$G$15, A38)*Budget!$F$15 -> 0 | Q38: =N("Spotify")-IF(AND(DAY($A38)=Budget!$M$3, MONTH($A38)=Budget!$L$3),Budget!$K$3,0) -> 0 | R38: =N("Spotify")-IF(AND(DAY($A38)=Budget!$M$4, MONTH($A38)=Budget!$L$4),Budget!$K$4,0) -> 0 | S38: =N("Spotify")-IF(AND(DAY($A38)=Budget!$M$5, MONTH($A38)=Budget!$L$5),Budget!$K$5,0) -> 0 | T38: =N("Amazon Prime")-IF(DAY(A38)=Budget!$Q$3,Budget!$P$3,0) -> 0 | U38: =N("Audible")-IF(DAY(A38)=Budget!$Q$12,Budget!$P$12,0) -> 0 | V38: =N("Crunchyroll")-IF(DAY(A38)=Budget!$Q$5,Budget!$P$5,0) -> 0 | W38: =N("HBO Max")-IF(DAY(A38)=Budget!$Q$6,Budget!$P$6,0) -> 0 | X38: =N("Netflix")-IF(DAY(A38)=Budget!$Q$7,Budget!$P$7,0) -> 0 | Y38: =N("Spotify")-IF(DAY(A38)=Budget!$Q$8,Budget!$P$8,0) -> 0 | Z38: =N("Truebill")-IF(DAY(A38)=Budget!$Q$9,Budget!$P$9,0) -> 0 | AA38: =SUM(D38:Z38) -> -803.35
A39: =A38+1 -> 45691 | B39: =B38+AA39 -> 108.05 | C39: =IF(B39>B38,2,IF(B39=B38, 1,0)) -> 1 | D39: 0 | E39: =N("PAY-LM")+IF(WEEKDAY(A39)=Budget!$C$3,Budget!$B$3,0) -> 0 | F39: =N("Rent")-IF(DAY(A39)=Budget!$G$3,Budget!$F$3,0) -> 0 | G39: =N("Car")-IF(DAY(A39)=Budget!$G$4,Budget!$F$4+Budget!$H$4,0) -> 0 | H39: =N("Mom Rent")-IF(DAY(A39)=Budget!$G$5,Budget!$F$5,0) -> 0 | I39: =N("AT&T")-IF(DAY(A39)=Budget!$G$8,Budget!$F$8,0) -> 0 | J39: =N("GA Power")-IF(DAY(A39)=Budget!$G$9,Budget!$F$9,0) -> 0 | K39: =N("Haircut")-IF(DAY(A39)=Budget!$G$10,Budget!$F$10,0) -> 0 | L39: =N("Groceries")-IF(DAY(A39)=Budget!$G$6,Budget!$F$6,0) -> 0 | M39: =N("Savings")-IF(DAY(A39)=Budget!$G$7,Budget!$F$7,0) -> 0 | N39: =N("Car Insurance")-COUNTIF(Budget!$G$14, A39)*Budget!$F$14 -> 0 | O39: =N("Phone Bill")-COUNTIF(Budget!$G$15, A39)*Budget!$F$15 -> 0 | Q39: =N("Spotify")-IF(AND(DAY($A39)=Budget!$M$3, MONTH($A39)=Budget!$L$3),Budget!$K$3,0) -> 0 | R39: =N("Spotify")-IF(AND(DAY($A39)=Budget!$M$4, MONTH($A39)=Budget!$L$4),Budget!$K$4,0) -> 0 | S39: =N("Spotify")-IF(AND(DAY($A39)=Budget!$M$5, MONTH($A39)=Budget!$L$5),Budget!$K$5,0) -> 0 | T39: =N("Amazon Prime")-IF(DAY(A39)=Budget!$Q$3,Budget!$P$3,0) -> 0 | U39: =N("Audible")-IF(DAY(A39)=Budget!$Q$12,Budget!$P$12,0) -> 0 | V39: =N("Crunchyroll")-IF(DAY(A39)=Budget!$Q$5,Budget!$P$5,0) -> 0 | W39: =N("HBO Max")-IF(DAY(A39)=Budget!$Q$6,Budget!$P$6,0) -> 0 | X39: =N("Netflix")-IF(DAY(A39)=Budget!$Q$7,Budget!$P$7,0) -> 0 | Y39: =N("Spotify")-IF(DAY(A39)=Budget!$Q$8,Budget!$P$8,0) -> 0 | Z39: =N("Truebill")-IF(DAY(A39)=Budget!$Q$9,Budget!$P$9,0) -> 0 | AA39: =SUM(D39:Z39) -> 0
A40: =A39+1 -> 45692 | B40: =B39+AA40 -> 108.05 | C40: =IF(B40>B39,2,IF(B40=B39, 1,0)) -> 1 | D40: 0 | E40: =N("PAY-LM")+IF(WEEKDAY(A40)=Budget!$C$3,Budget!$B$3,0) -> 0 | F40: =N("Rent")-IF(DAY(A40)=Budget!$G$3,Budget!$F$3,0) -> 0 | G40: =N("Car")-IF(DAY(A40)=Budget!$G$4,Budget!$F$4+Budget!$H$4,0) -> 0 | H40: =N("Mom Rent")-IF(DAY(A40)=Budget!$G$5,Budget!$F$5,0) -> 0 | I40: =N("AT&T")-IF(DAY(A40)=Budget!$G$8,Budget!$F$8,0) -> 0 | J40: =N("GA Power")-IF(DAY(A40)=Budget!$G$9,Budget!$F$9,0) -> 0 | K40: =N("Haircut")-IF(DAY(A40)=Budget!$G$10,Budget!$F$10,0) -> 0 | L40: =N("Groceries")-IF(DAY(A40)=Budget!$G$6,Budget!$F$6,0) -> 0 | M40: =N("Savings")-IF(DAY(A40)=Budget!$G$7,Budget!$F$7,0) -> 0 | N40: =N("Car Insurance")-COUNTIF(Budget!$G$14, A40)*Budget!$F$14 -> 0 | O40: =N("Phone Bill")-COUNTIF(Budget!$G$15, A40)*Budget!$F$15 -> 0 | Q40: =N("Spotify")-IF(AND(DAY($A40)=Budget!$M$3, MONTH($A40)=Budget!$L$3),Budget!$K$3,0) -> 0 | R40: =N("Spotify")-IF(AND(DAY($A40)=Budget!$M$4, MONTH($A40)=Budget!$L$4),Budget!$K$4,0) -> 0 | S40: =N("Spotify")-IF(AND(DAY($A40)=Budget!$M$5, MONTH($A40)=Budget!$L$5),Budget!$K$5,0) -> 0 | T40: =N("Amazon Prime")-IF(DAY(A40)=Budget!$Q$3,Budget!$P$3,0) -> 0 | U40: =N("Audible")-IF(DAY(A40)=Budget!$Q$12,Budget!$P$12,0) -> 0 | V40: =N("Crunchyroll")-IF(DAY(A40)=Budget!$Q$5,Budget!$P$5,0) -> 0 | W40: =N("HBO Max")-IF(DAY(A40)=Budget!$Q$6,Budget!$P$6,0) -> 0 | X40: =N("Netflix")-IF(DAY(A40)=Budget!$Q$7,Budget!$P$7,0) -> 0 | Y40: =N("Spotify")-IF(DAY(A40)=Budget!$Q$8,Budget!$P$8,0) -> 0 | Z40: =N("Truebill")-IF(DAY(A40)=Budget!$Q$9,Budget!$P$9,0) -> 0 | AA40: =SUM(D40:Z40) -> 0
A41: =A40+1 -> 45693 | B41: =B40+AA41 -> 38.05 | C41: =IF(B41>B40,2,IF(B41=B40, 1,0)) -> 0 | D41: 0 | E41: =N("PAY-LM")+IF(WEEKDAY(A41)=Budget!$C$3,Budget!$B$3,0) -> 0 | F41: =N("Rent")-IF(DAY(A41)=Budget!$G$3,Budget!$F$3,0) -> 0 | G41: =N("Car")-IF(DAY(A41)=Budget!$G$4,Budget!$F$4+Budget!$H$4,0) -> 0 | H41: =N("Mom Rent")-IF(DAY(A41)=Budget!$G$5,Budget!$F$5,0) -> 0 | I41: =N("AT&T")-IF(DAY(A41)=Budget!$G$8,Budget!$F$8,0) -> 0 | J41: =N("GA Power")-IF(DAY(A41)=Budget!$G$9,Budget!$F$9,0) -> -70 | K41: =N("Haircut")-IF(DAY(A41)=Budget!$G$10,Budget!$F$10,0) -> 0 | L41: =N("Groceries")-IF(DAY(A41)=Budget!$G$6,Budget!$F$6,0) -> 0 | M41: =N("Savings")-IF(DAY(A41)=Budget!$G$7,Budget!$F$7,0) -> 0 | N41: =N("Car Insurance")-COUNTIF(Budget!$G$14, A41)*Budget!$F$14 -> 0 | O41: =N("Phone Bill")-COUNTIF(Budget!$G$15, A41)*Budget!$F$15 -> 0 | Q41: =N("Spotify")-IF(AND(DAY($A41)=Budget!$M$3, MONTH($A41)=Budget!$L$3),Budget!$K$3,0) -> 0 | R41: =N("Spotify")-IF(AND(DAY($A41)=Budget!$M$4, MONTH($A41)=Budget!$L$4),Budget!$K$4,0) -> 0 | S41: =N("Spotify")-IF(AND(DAY($A41)=Budget!$M$5, MONTH($A41)=Budget!$L$5),Budget!$K$5,0) -> 0 | T41: =N("Amazon Prime")-IF(DAY(A41)=Budget!$Q$3,Budget!$P$3,0) -> 0 | U41: =N("Audible")-IF(DAY(A41)=Budget!$Q$12,Budget!$P$12,0) -> 0 | V41: =N("Crunchyroll")-IF(DAY(A41)=Budget!$Q$5,Budget!$P$5,0) -> 0 | W41: =N("HBO Max")-IF(DAY(A41)=Budget!$Q$6,Budget!$P$6,0) -> 0 | X41: =N("Netflix")-IF(DAY(A41)=Budget!$Q$7,Budget!$P$7,0) -> 0 | Y41: =N("Spotify")-IF(DAY(A41)=Budget!$Q$8,Budget!$P$8,0) -> 0 | Z41: =N("Truebill")-IF(DAY(A41)=Budget!$Q$9,Budget!$P$9,0) -> 0 | AA41: =SUM(D41:Z41) -> -70
A42: =A41+1 -> 45694 | B42: 362.43 | C42: =IF(B42>B41,2,IF(B42=B41, 1,0)) -> 2 | D42: 0 | E42: =N("PAY-LM")+IF(WEEKDAY(A42)=Budget!$C$3,Budget!$B$3,0) -> 0 | F42: =N("Rent")-IF(DAY(A42)=Budget!$G$3,Budget!$F$3,0) -> 0 | G42: =N("Car")-IF(DAY(A42)=Budget!$G$4,Budget!$F$4+Budget!$H$4,0) -> 0 | H42: =N("Mom Rent")-IF(DAY(A42)=Budget!$G$5,Budget!$F$5,0) -> 0 | I42: =N("AT&T")-IF(DAY(A42)=Budget!$G$8,Budget!$F$8,0) -> 0 | J42: =N("GA Power")-IF(DAY(A42)=Budget!$G$9,Budget!$F$9,0) -> 0 | K42: =N("Haircut")-IF(DAY(A42)=Budget!$G$10,Budget!$F$10,0) -> 0 | L42: =N("Groceries")-IF(DAY(A42)=Budget!$G$6,Budget!$F$6,0) -> 0 | M42: =N("Savings")-IF(DAY(A42)=Budget!$G$7,Budget!$F$7,0) -> 0 | N42: =N("Car Insurance")-COUNTIF(Budget!$G$14, A42)*Budget!$F$14 -> 0 | O42: =N("Phone Bill")-COUNTIF(Budget!$G$15, A42)*Budget!$F$15 -> 0 | Q42: =N("Spotify")-IF(AND(DAY($A42)=Budget!$M$3, MONTH($A42)=Budget!$L$3),Budget!$K$3,0) -> 0 | R42: =N("Spotify")-IF(AND(DAY($A42)=Budget!$M$4, MONTH($A42)=Budget!$L$4),Budget!$K$4,0) -> 0 | S42: =N("Spotify")-IF(AND(DAY($A42)=Budget!$M$5, MONTH($A42)=Budget!$L$5),Budget!$K$5,0) -> 0 | T42: =N("Amazon Prime")-IF(DAY(A42)=Budget!$Q$3,Budget!$P$3,0) -> 0 | U42: =N("Audible")-IF(DAY(A42)=Budget!$Q$12,Budget!$P$12,0) -> 0 | V42: =N("Crunchyroll")-IF(DAY(A42)=Budget!$Q$5,Budget!$P$5,0) -> 0 | W42: =N("HBO Max")-IF(DAY(A42)=Budget!$Q$6,Budget!$P$6,0) -> 0 | X42: =N("Netflix")-IF(DAY(A42)=Budget!$Q$7,Budget!$P$7,0) -> 0 | Y42: =N("Spotify")-IF(DAY(A42)=Budget!$Q$8,Budget!$P$8,0) -> 0 | Z42: =N("Truebill")-IF(DAY(A42)=Budget!$Q$9,Budget!$P$9,0) -> 0 | AA42: =SUM(D42:Z42) -> 0
A43: =A42+1 -> 45695 | B43: =B42+AA43 -> 1815.43 | C43: =IF(B43>B42,2,IF(B43=B42, 1,0)) -> 2 | D43: 0 | E43: =N("PAY-LM")+IF(WEEKDAY(A43)=Budget!$C$3,Budget!$B$3,0) -> 1453 | F43: =N("Rent")-IF(DAY(A43)=Budget!$G$3,Budget!$F$3,0) -> 0 | G43: =N("Car")-IF(DAY(A43)=Budget!$G$4,Budget!$F$4+Budget!$H$4,0) -> 0 | H43: =N("Mom Rent")-IF(DAY(A43)=Budget!$G$5,Budget!$F$5,0) -> 0 | I43: =N("AT&T")-IF(DAY(A43)=Budget!$G$8,Budget!$F$8,0) -> 0 | J43: =N("GA Power")-IF(DAY(A43)=Budget!$G$9,Budget!$F$9,0) -> 0 | K43: =N("Haircut")-IF(DAY(A43)=Budget!$G$10,Budget!$F$10,0) -> 0 | L43: =N("Groceries")-IF(DAY(A43)=Budget!$G$6,Budget!$F$6,0) -> 0 | M43: =N("Savings")-IF(DAY(A43)=Budget!$G$7,Budget!$F$7,0) -> 0 | N43: =N("Car Insurance")-COUNTIF(Budget!$G$14, A43)*Budget!$F$14 -> 0 | O43: =N("Phone Bill")-COUNTIF(Budget!$G$15, A43)*Budget!$F$15 -> 0 | Q43: =N("Spotify")-IF(AND(DAY($A43)=Budget!$M$3, MONTH($A43)=Budget!$L$3),Budget!$K$3,0) -> 0 | R43: =N("Spotify")-IF(AND(DAY($A43)=Budget!$M$4, MONTH($A43)=Budget!$L$4),Budget!$K$4,0) -> 0 | S43: =N("Spotify")-IF(AND(DAY($A43)=Budget!$M$5, MONTH($A43)=Budget!$L$5),Budget!$K$5,0) -> 0 | T43: =N("Amazon Prime")-IF(DAY(A43)=Budget!$Q$3,Budget!$P$3,0) -> 0 | U43: =N("Audible")-IF(DAY(A43)=Budget!$Q$12,Budget!$P$12,0) -> 0 | V43: =N("Crunchyroll")-IF(DAY(A43)=Budget!$Q$5,Budget!$P$5,0) -> 0 | W43: =N("HBO Max")-IF(DAY(A43)=Budget!$Q$6,Budget!$P$6,0) -> 0 | X43: =N("Netflix")-IF(DAY(A43)=Budget!$Q$7,Budget!$P$7,0) -> 0 | Y43: =N("Spotify")-IF(DAY(A43)=Budget!$Q$8,Budget!$P$8,0) -> 0 | Z43: =N("Truebill")-IF(DAY(A43)=Budget!$Q$9,Budget!$P$9,0) -> 0 | AA43: =SUM(D43:Z43) -> 1453
A44: =A43+1 -> 45696 | B44: =B43+AA44 -> 1795.96 | C44: =IF(B44>B43,2,IF(B44=B43, 1,0)) -> 0 | D44: 0 | E44: =N("PAY-LM")+IF(WEEKDAY(A44)=Budget!$C$3,Budget!$B$3,0) -> 0 | F44: =N("Rent")-IF(DAY(A44)=Budget!$G$3,Budget!$F$3,0) -> 0 | G44: =N("Car")-IF(DAY(A44)=Budget!$G$4,Budget!$F$4+Budget!$H$4,0) -> 0 | H44: =N("Mom Rent")-IF(DAY(A44)=Budget!$G$5,Budget!$F$5,0) -> 0 | I44: =N("AT&T")-IF(DAY(A44)=Budget!$G$8,Budget!$F$8,0) -> 0 | J44: =N("GA Power")-IF(DAY(A44)=Budget!$G$9,Budget!$F$9,0) -> 0 | K44: =N("Haircut")-IF(DAY(A44)=Budget!$G$10,Budget!$F$10,0) -> 0 | L44: =N("Groceries")-IF(DAY(A44)=Budget!$G$6,Budget!$F$6,0) -> 0 | M44: =N("Savings")-IF(DAY(A44)=Budget!$G$7,Budget!$F$7,0) -> 0 | N44: =N("Car Insurance")-COUNTIF(Budget!$G$14, A44)*Budget!$F$14 -> 0 | O44: =N("Phone Bill")-COUNTIF(Budget!$G$15, A44)*Budget!$F$15 -> 0 | Q44: =N("Spotify")-IF(AND(DAY($A44)=Budget!$M$3, MONTH($A44)=Budget!$L$3),Budget!$K$3,0) -> 0 | R44: =N("Spotify")-IF(AND(DAY($A44)=Budget!$M$4, MONTH($A44)=Budget!$L$4),Budget!$K$4,0) -> 0 | S44: =N("Spotify")-IF(AND(DAY($A44)=Budget!$M$5, MONTH($A44)=Budget!$L$5),Budget!$K$5,0) -> 0 | T44: =N("Amazon Prime")-IF(DAY(A44)=Budget!$Q$3,Budget!$P$3,0) -> -7.48 | U44: =N("Audible")-IF(DAY(A44)=Budget!$Q$12,Budget!$P$12,0) -> 0 | V44: =N("Crunchyroll")-IF(DAY(A44)=Budget!$Q$5,Budget!$P$5,0) -> 0 | W44: =N("HBO Max")-IF(DAY(A44)=Budget!$Q$6,Budget!$P$6,0) -> -11.99 | X44: =N("Netflix")-IF(DAY(A44)=Budget!$Q$7,Budget!$P$7,0) -> 0 | Y44: =N("Spotify")-IF(DAY(A44)=Budget!$Q$8,Budget!$P$8,0) -> 0 | Z44: =N("Truebill")-IF(DAY(A44)=Budget!$Q$9,Budget!$P$9,0) -> 0 | AA44: =SUM(D44:Z44) -> -19.47
A45: =A44+1 -> 45697 | B45: =1479.77 -> 1479.77 | C45: =IF(B45>B44,2,IF(B45=B44, 1,0)) -> 0 | D45: 0 | E45: =N("PAY-LM")+IF(WEEKDAY(A45)=Budget!$C$3,Budget!$B$3,0) -> 0 | F45: =N("Rent")-IF(DAY(A45)=Budget!$G$3,Budget!$F$3,0) -> 0 | G45: =N("Car")-IF(DAY(A45)=Budget!$G$4,Budget!$F$4+Budget!$H$4,0) -> 0 | H45: =N("Mom Rent")-IF(DAY(A45)=Budget!$G$5,Budget!$F$5,0) -> 0 | I45: =N("AT&T")-IF(DAY(A45)=Budget!$G$8,Budget!$F$8,0) -> 0 | J45: =N("GA Power")-IF(DAY(A45)=Budget!$G$9,Budget!$F$9,0) -> 0 | K45: =N("Haircut")-IF(DAY(A45)=Budget!$G$10,Budget!$F$10,0) -> 0 | L45: =N("Groceries")-IF(DAY(A45)=Budget!$G$6,Budget!$F$6,0) -> 0 | M45: =N("Savings")-IF(DAY(A45)=Budget!$G$7,Budget!$F$7,0) -> 0 | N45: =N("Car Insurance")-COUNTIF(Budget!$G$14, A45)*Budget!$F$14 -> 0 | O45: =N("Phone Bill")-COUNTIF(Budget!$G$15, A45)*Budget!$F$15 -> 0 | Q45: =N("Spotify")-IF(AND(DAY($A45)=Budget!$M$3, MONTH($A45)=Budget!$L$3),Budget!$K$3,0) -> 0 | R45: =N("Spotify")-IF(AND(DAY($A45)=Budget!$M$4, MONTH($A45)=Budget!$L$4),Budget!$K$4,0) -> 0 | S45: =N("Spotify")-IF(AND(DAY($A45)=Budget!$M$5, MONTH($A45)=Budget!$L$5),Budget!$K$5,0) -> 0 | T45: =N("Amazon Prime")-IF(DAY(A45)=Budget!$Q$3,Budget!$P$3,0) -> 0 | U45: =N("Audible")-IF(DAY(A45)=Budget!$Q$12,Budget!$P$12,0) -> 0 | V45: =N("Crunchyroll")-IF(DAY(A45)=Budget!$Q$5,Budget!$P$5,0) -> 0 | W45: =N("HBO Max")-IF(DAY(A45)=Budget!$Q$6,Budget!$P$6,0) -> 0 | X45: =N("Netflix")-IF(DAY(A45)=Budget!$Q$7,Budget!$P$7,0) -> 0 | Y45: =N("Spotify")-IF(DAY(A45)=Budget!$Q$8,Budget!$P$8,0) -> 0 | Z45: =N("Truebill")-IF(DAY(A45)=Budget!$Q$9,Budget!$P$9,0) -> 0 | AA45: =SUM(D45:Z45) -> 0
A46: =A45+1 -> 45698 | B46: =B45+AA46 -> 1318.77 | C46: =IF(B46>B45,2,IF(B46=B45, 1,0)) -> 0 | D46: -161 | E46: =N("PAY-LM")+IF(WEEKDAY(A46)=Budget!$C$3,Budget!$B$3,0) -> 0 | F46: =N("Rent")-IF(DAY(A46)=Budget!$G$3,Budget!$F$3,0) -> 0 | G46: =N("Car")-IF(DAY(A46)=Budget!$G$4,Budget!$F$4+Budget!$H$4,0) -> 0 | H46: =N("Mom Rent")-IF(DAY(A46)=Budget!$G$5,Budget!$F$5,0) -> 0 | I46: =N("AT&T")-IF(DAY(A46)=Budget!$G$8,Budget!$F$8,0) -> 0 | J46: =N("GA Power")-IF(DAY(A46)=Budget!$G$9,Budget!$F$9,0) -> 0 | K46: =N("Haircut")-IF(DAY(A46)=Budget!$G$10,Budget!$F$10,0) -> 0 | L46: =N("Groceries")-IF(DAY(A46)=Budget!$G$6,Budget!$F$6,0) -> 0 | M46: =N("Savings")-IF(DAY(A46)=Budget!$G$7,Budget!$F$7,0) -> 0 | N46: =N("Car Insurance")-COUNTIF(Budget!$G$14, A46)*Budget!$F$14 -> 0 | O46: =N("Phone Bill")-COUNTIF(Budget!$G$15, A46)*Budget!$F$15 -> 0 | Q46: =N("Spotify")-IF(AND(DAY($A46)=Budget!$M$3, MONTH($A46)=Budget!$L$3),Budget!$K$3,0) -> 0 | R46: =N("Spotify")-IF(AND(DAY($A46)=Budget!$M$4, MONTH($A46)=Budget!$L$4),Budget!$K$4,0) -> 0 | S46: =N("Spotify")-IF(AND(DAY($A46)=Budget!$M$5, MONTH($A46)=Budget!$L$5),Budget!$K$5,0) -> 0 | T46: =N("Amazon Prime")-IF(DAY(A46)=Budget!$Q$3,Budget!$P$3,0) -> 0 | U46: =N("Audible")-IF(DAY(A46)=Budget!$Q$12,Budget!$P$12,0) -> 0 | V46: =N("Crunchyroll")-IF(DAY(A46)=Budget!$Q$5,Budget!$P$5,0) -> 0 | W46: =N("HBO Max")-IF(DAY(A46)=Budget!$Q$6,Budget!$P$6,0) -> 0 | X46: =N("Netflix")-IF(DAY(A46)=Budget!$Q$7,Budget!$P$7,0) -> 0 | Y46: =N("Spotify")-IF(DAY(A46)=Budget!$Q$8,Budget!$P$8,0) -> 0 | Z46: =N("Truebill")-IF(DAY(A46)=Budget!$Q$9,Budget!$P$9,0) -> 0 | AA46: =SUM(D46:Z46) -> -161
A47: =A46+1 -> 45699 | B47: =B46+AA47 -> 1318.77 | C47: =IF(B47>B46,2,IF(B47=B46, 1,0)) -> 1 | D47: 0 | E47: =N("PAY-LM")+IF(WEEKDAY(A47)=Budget!$C$3,Budget!$B$3,0) -> 0 | F47: =N("Rent")-IF(DAY(A47)=Budget!$G$3,Budget!$F$3,0) -> 0 | G47: =N("Car")-IF(DAY(A47)=Budget!$G$4,Budget!$F$4+Budget!$H$4,0) -> 0 | H47: =N("Mom Rent")-IF(DAY(A47)=Budget!$G$5,Budget!$F$5,0) -> 0 | I47: =N("AT&T")-IF(DAY(A47)=Budget!$G$8,Budget!$F$8,0) -> 0 | J47: =N("GA Power")-IF(DAY(A47)=Budget!$G$9,Budget!$F$9,0) -> 0 | K47: =N("Haircut")-IF(DAY(A47)=Budget!$G$10,Budget!$F$10,0) -> 0 | L47: =N("Groceries")-IF(DAY(A47)=Budget!$G$6,Budget!$F$6,0) -> 0 | M47: =N("Savings")-IF(DAY(A47)=Budget!$G$7,Budget!$F$7,0) -> 0 | N47: =N("Car Insurance")-COUNTIF(Budget!$G$14, A47)*Budget!$F$14 -> 0 | O47: =N("Phone Bill")-COUNTIF(Budget!$G$15, A47)*Budget!$F$15 -> 0 | Q47: =N("Spotify")-IF(AND(DAY($A47)=Budget!$M$3, MONTH($A47)=Budget!$L$3),Budget!$K$3,0) -> 0 | R47: =N("Spotify")-IF(AND(DAY($A47)=Budget!$M$4, MONTH($A47)=Budget!$L$4),Budget!$K$4,0) -> 0 | S47: =N("Spotify")-IF(AND(DAY($A47)=Budget!$M$5, MONTH($A47)=Budget!$L$5),Budget!$K$5,0) -> 0 | T47: =N("Amazon Prime")-IF(DAY(A47)=Budget!$Q$3,Budget!$P$3,0) -> 0 | U47: =N("Audible")-IF(DAY(A47)=Budget!$Q$12,Budget!$P$12,0) -> 0 | V47: =N("Crunchyroll")-IF(DAY(A47)=Budget!$Q$5,Budget!$P$5,0) -> 0 | W47: =N("HBO Max")-IF(DAY(A47)=Budget!$Q$6,Budget!$P$6,0) -> 0 | X47: =N("Netflix")-IF(DAY(A47)=Budget!$Q$7,Budget!$P$7,0) -> 0 | Y47: =N("Spotify")-IF(DAY(A47)=Budget!$Q$8,Budget!$P$8,0) -> 0 | Z47: =N("Truebill")-IF(DAY(A47)=Budget!$Q$9,Budget!$P$9,0) -> 0 | AA47: =SUM(D47:Z47) -> 0
A48: =A47+1 -> 45700 | B48: =B47+AA48 -> 1312.77 | C48: =IF(B48>B47,2,IF(B48=B47, 1,0)) -> 0 | D48: 0 | E48: =N("PAY-LM")+IF(WEEKDAY(A48)=Budget!$C$3,Budget!$B$3,0) -> 0 | F48: =N("Rent")-IF(DAY(A48)=Budget!$G$3,Budget!$F$3,0) -> 0 | G48: =N("Car")-IF(DAY(A48)=Budget!$G$4,Budget!$F$4+Budget!$H$4,0) -> 0 | H48: =N("Mom Rent")-IF(DAY(A48)=Budget!$G$5,Budget!$F$5,0) -> 0 | I48: =N("AT&T")-IF(DAY(A48)=Budget!$G$8,Budget!$F$8,0) -> 0 | J48: =N("GA Power")-IF(DAY(A48)=Budget!$G$9,Budget!$F$9,0) -> 0 | K48: =N("Haircut")-IF(DAY(A48)=Budget!$G$10,Budget!$F$10,0) -> 0 | L48: =N("Groceries")-IF(DAY(A48)=Budget!$G$6,Budget!$F$6,0) -> 0 | M48: =N("Savings")-IF(DAY(A48)=Budget!$G$7,Budget!$F$7,0) -> 0 | N48: =N("Car Insurance")-COUNTIF(Budget!$G$14, A48)*Budget!$F$14 -> 0 | O48: =N("Phone Bill")-COUNTIF(Budget!$G$15, A48)*Budget!$F$15 -> 0 | Q48: =N("Spotify")-IF(AND(DAY($A48)=Budget!$M$3, MONTH($A48)=Budget!$L$3),Budget!$K$3,0) -> 0 | R48: =N("Spotify")-IF(AND(DAY($A48)=Budget!$M$4, MONTH($A48)=Budget!$L$4),Budget!$K$4,0) -> 0 | S48: =N("Spotify")-IF(AND(DAY($A48)=Budget!$M$5, MONTH($A48)=Budget!$L$5),Budget!$K$5,0) -> 0 | T48: =N("Amazon Prime")-IF(DAY(A48)=Budget!$Q$3,Budget!$P$3,0) -> 0 | U48: =N("Audible")-IF(DAY(A48)=Budget!$Q$12,Budget!$P$12,0) -> 0 | V48: =N("Crunchyroll")-IF(DAY(A48)=Budget!$Q$5,Budget!$P$5,0) -> 0 | W48: =N("HBO Max")-IF(DAY(A48)=Budget!$Q$6,Budget!$P$6,0) -> 0 | X48: =N("Netflix")-IF(DAY(A48)=Budget!$Q$7,Budget!$P$7,0) -> -6 | Y48: =N("Spotify")-IF(DAY(A48)=Budget!$Q$8,Budget!$P$8,0) -> 0 | Z48: =N("Truebill")-IF(DAY(A48)=Budget!$Q$9,Budget!$P$9,0) -> 0 | AA48: =SUM(D48:Z48) -> -6
A49: =A48+1 -> 45701 | B49: =B48+AA49 -> 1312.77 | C49: =IF(B49>B48,2,IF(B49=B48, 1,0)) -> 1 | E49: =N("PAY-LM")+IF(WEEKDAY(A49)=Budget!$C$3,Budget!$B$3,0) -> 0 | F49: =N("Rent")-IF(DAY(A49)=Budget!$G$3,Budget!$F$3,0) -> 0 | G49: =N("Car")-IF(DAY(A49)=Budget!$G$4,Budget!$F$4+Budget!$H$4,0) -> 0 | H49: =N("Mom Rent")-IF(DAY(A49)=Budget!$G$5,Budget!$F$5,0) -> 0 | I49: =N("AT&T")-IF(DAY(A49)=Budget!$G$8,Budget!$F$8,0) -> 0 | J49: =N("GA Power")-IF(DAY(A49)=Budget!$G$9,Budget!$F$9,0) -> 0 | K49: =N("Haircut")-IF(DAY(A49)=Budget!$G$10,Budget!$F$10,0) -> 0 | L49: =N("Groceries")-IF(DAY(A49)=Budget!$G$6,Budget!$F$6,0) -> 0 | M49: =N("Savings")-IF(DAY(A49)=Budget!$G$7,Budget!$F$7,0) -> 0 | N49: =N("Car Insurance")-COUNTIF(Budget!$G$14, A49)*Budget!$F$14 -> 0 | O49: =N("Phone Bill")-COUNTIF(Budget!$G$15, A49)*Budget!$F$15 -> 0 | Q49: =N("Spotify")-IF(AND(DAY($A49)=Budget!$M$3, MONTH($A49)=Budget!$L$3),Budget!$K$3,0) -> 0 | R49: =N("Spotify")-IF(AND(DAY($A49)=Budget!$M$4, MONTH($A49)=Budget!$L$4),Budget!$K$4,0) -> 0 | S49: =N("Spotify")-IF(AND(DAY($A49)=Budget!$M$5, MONTH($A49)=Budget!$L$5),Budget!$K$5,0) -> 0 | T49: =N("Amazon Prime")-IF(DAY(A49)=Budget!$Q$3,Budget!$P$3,0) -> 0 | U49: =N("Audible")-IF(DAY(A49)=Budget!$Q$12,Budget!$P$12,0) -> 0 | V49: =N("Crunchyroll")-IF(DAY(A49)=Budget!$Q$5,Budget!$P$5,0) -> 0 | W49: =N("HBO Max")-IF(DAY(A49)=Budget!$Q$6,Budget!$P$6,0) -> 0 | X49: =N("Netflix")-IF(DAY(A49)=Budget!$Q$7,Budget!$P$7,0) -> 0 | Y49: =N("Spotify")-IF(DAY(A49)=Budget!$Q$8,Budget!$P$8,0) -> 0 | Z49: =N("Truebill")-IF(DAY(A49)=Budget!$Q$9,Budget!$P$9,0) -> 0 | AA49: =SUM(D49:Z49) -> 0
A50: =A49+1 -> 45702 | B50: =B49+AA50 -> 2765.77 | C50: =IF(B50>B49,2,IF(B50=B49, 1,0)) -> 2 | D50: 0 | E50: =N("PAY-LM")+IF(WEEKDAY(A50)=Budget!$C$3,Budget!$B$3,0) -> 1453 | F50: =N("Rent")-IF(DAY(A50)=Budget!$G$3,Budget!$F$3,0) -> 0 | G50: =N("Car")-IF(DAY(A50)=Budget!$G$4,Budget!$F$4+Budget!$H$4,0) -> 0 | H50: =N("Mom Rent")-IF(DAY(A50)=Budget!$G$5,Budget!$F$5,0) -> 0 | I50: =N("AT&T")-IF(DAY(A50)=Budget!$G$8,Budget!$F$8,0) -> 0 | J50: =N("GA Power")-IF(DAY(A50)=Budget!$G$9,Budget!$F$9,0) -> 0 | K50: =N("Haircut")-IF(DAY(A50)=Budget!$G$10,Budget!$F$10,0) -> 0 | L50: =N("Groceries")-IF(DAY(A50)=Budget!$G$6,Budget!$F$6,0) -> 0 | M50: =N("Savings")-IF(DAY(A50)=Budget!$G$7,Budget!$F$7,0) -> 0 | N50: =N("Car Insurance")-COUNTIF(Budget!$G$14, A50)*Budget!$F$14 -> 0 | O50: =N("Phone Bill")-COUNTIF(Budget!$G$15, A50)*Budget!$F$15 -> 0 | Q50: =N("Spotify")-IF(AND(DAY($A50)=Budget!$M$3, MONTH($A50)=Budget!$L$3),Budget!$K$3,0) -> 0 | R50: =N("Spotify")-IF(AND(DAY($A50)=Budget!$M$4, MONTH($A50)=Budget!$L$4),Budget!$K$4,0) -> 0 | S50: =N("Spotify")-IF(AND(DAY($A50)=Budget!$M$5, MONTH($A50)=Budget!$L$5),Budget!$K$5,0) -> 0 | T50: =N("Amazon Prime")-IF(DAY(A50)=Budget!$Q$3,Budget!$P$3,0) -> 0 | U50: =N("Audible")-IF(DAY(A50)=Budget!$Q$12,Budget!$P$12,0) -> 0 | V50: =N("Crunchyroll")-IF(DAY(A50)=Budget!$Q$5,Budget!$P$5,0) -> 0 | W50: =N("HBO Max")-IF(DAY(A50)=Budget!$Q$6,Budget!$P$6,0) -> 0 | X50: =N("Netflix")-IF(DAY(A50)=Budget!$Q$7,Budget!$P$7,0) -> 0 | Y50: =N("Spotify")-IF(DAY(A50)=Budget!$Q$8,Budget!$P$8,0) -> 0 | Z50: =N("Truebill")-IF(DAY(A50)=Budget!$Q$9,Budget!$P$9,0) -> 0 | AA50: =SUM(D50:Z50) -> 1453
A51: =A50+1 -> 45703 | B51: =B50+AA51 -> 2765.77 | C51: =IF(B51>B50,2,IF(B51=B50, 1,0)) -> 1 | D51: 0 | E51: =N("PAY-LM")+IF(WEEKDAY(A51)=Budget!$C$3,Budget!$B$3,0) -> 0 | F51: =N("Rent")-IF(DAY(A51)=Budget!$G$3,Budget!$F$3,0) -> 0 | G51: =N("Car")-IF(DAY(A51)=Budget!$G$4,Budget!$F$4+Budget!$H$4,0) -> 0 | H51: =N("Mom Rent")-IF(DAY(A51)=Budget!$G$5,Budget!$F$5,0) -> 0 | I51: =N("AT&T")-IF(DAY(A51)=Budget!$G$8,Budget!$F$8,0) -> 0 | J51: =N("GA Power")-IF(DAY(A51)=Budget!$G$9,Budget!$F$9,0) -> 0 | K51: =N("Haircut")-IF(DAY(A51)=Budget!$G$10,Budget!$F$10,0) -> 0 | L51: =N("Groceries")-IF(DAY(A51)=Budget!$G$6,Budget!$F$6,0) -> 0 | M51: =N("Savings")-IF(DAY(A51)=Budget!$G$7,Budget!$F$7,0) -> 0 | N51: =N("Car Insurance")-COUNTIF(Budget!$G$14, A51)*Budget!$F$14 -> 0 | O51: =N("Phone Bill")-COUNTIF(Budget!$G$15, A51)*Budget!$F$15 -> 0 | Q51: =N("Spotify")-IF(AND(DAY($A51)=Budget!$M$3, MONTH($A51)=Budget!$L$3),Budget!$K$3,0) -> 0 | R51: =N("Spotify")-IF(AND(DAY($A51)=Budget!$M$4, MONTH($A51)=Budget!$L$4),Budget!$K$4,0) -> 0 | S51: =N("Spotify")-IF(AND(DAY($A51)=Budget!$M$5, MONTH($A51)=Budget!$L$5),Budget!$K$5,0) -> 0 | T51: =N("Amazon Prime")-IF(DAY(A51)=Budget!$Q$3,Budget!$P$3,0) -> 0 | U51: =N("Audible")-IF(DAY(A51)=Budget!$Q$12,Budget!$P$12,0) -> 0 | V51: =N("Crunchyroll")-IF(DAY(A51)=Budget!$Q$5,Budget!$P$5,0) -> 0 | W51: =N("HBO Max")-IF(DAY(A51)=Budget!$Q$6,Budget!$P$6,0) -> 0 | X51: =N("Netflix")-IF(DAY(A51)=Budget!$Q$7,Budget!$P$7,0) -> 0 | Y51: =N("Spotify")-IF(DAY(A51)=Budget!$Q$8,Budget!$P$8,0) -> 0 | Z51: =N("Truebill")-IF(DAY(A51)=Budget!$Q$9,Budget!$P$9,0) -> 0 | AA51: =SUM(D51:Z51) -> 0
A52: =A51+1 -> 45704 | B52: 2462.77 | C52: =IF(B52>B51,2,IF(B52=B51, 1,0)) -> 0 | D52: 0 | E52: =N("PAY-LM")+IF(WEEKDAY(A52)=Budget!$C$3,Budget!$B$3,0) -> 0 | F52: =N("Rent")-IF(DAY(A52)=Budget!$G$3,Budget!$F$3,0) -> 0 | G52: =N("Car")-IF(DAY(A52)=Budget!$G$4,Budget!$F$4+Budget!$H$4,0) -> 0 | H52: =N("Mom Rent")-IF(DAY(A52)=Budget!$G$5,Budget!$F$5,0) -> 0 | I52: =N("AT&T")-IF(DAY(A52)=Budget!$G$8,Budget!$F$8,0) -> 0 | J52: =N("GA Power")-IF(DAY(A52)=Budget!$G$9,Budget!$F$9,0) -> 0 | K52: =N("Haircut")-IF(DAY(A52)=Budget!$G$10,Budget!$F$10,0) -> 0 | L52: =N("Groceries")-IF(DAY(A52)=Budget!$G$6,Budget!$F$6,0) -> 0 | M52: =N("Savings")-IF(DAY(A52)=Budget!$G$7,Budget!$F$7,0) -> 0 | N52: =N("Car Insurance")-COUNTIF(Budget!$G$14, A52)*Budget!$F$14 -> 0 | O52: =N("Phone Bill")-COUNTIF(Budget!$G$15, A52)*Budget!$F$15 -> 0 | Q52: =N("Spotify")-IF(AND(DAY($A52)=Budget!$M$3, MONTH($A52)=Budget!$L$3),Budget!$K$3,0) -> 0 | R52: =N("Spotify")-IF(AND(DAY($A52)=Budget!$M$4, MONTH($A52)=Budget!$L$4),Budget!$K$4,0) -> 0 | S52: =N("Spotify")-IF(AND(DAY($A52)=Budget!$M$5, MONTH($A52)=Budget!$L$5),Budget!$K$5,0) -> 0 | T52: =N("Amazon Prime")-IF(DAY(A52)=Budget!$Q$3,Budget!$P$3,0) -> 0 | U52: =N("Audible")-IF(DAY(A52)=Budget!$Q$12,Budget!$P$12,0) -> 0 | V52: =N("Crunchyroll")-IF(DAY(A52)=Budget!$Q$5,Budget!$P$5,0) -> 0 | W52: =N("HBO Max")-IF(DAY(A52)=Budget!$Q$6,Budget!$P$6,0) -> 0 | X52: =N("Netflix")-IF(DAY(A52)=Budget!$Q$7,Budget!$P$7,0) -> 0 | Y52: =N("Spotify")-IF(DAY(A52)=Budget!$Q$8,Budget!$P$8,0) -> 0 | Z52: =N("Truebill")-IF(DAY(A52)=Budget!$Q$9,Budget!$P$9,0) -> 0 | AA52: =SUM(D52:Z52) -> 0
A53: =A52+1 -> 45705 | B53: =B52+AA53 -> 2462.77 | C53: =IF(B53>B52,2,IF(B53=B52, 1,0)) -> 1 | D53: 0 | E53: =N("PAY-LM")+IF(WEEKDAY(A53)=Budget!$C$3,Budget!$B$3,0) -> 0 | F53: =N("Rent")-IF(DAY(A53)=Budget!$G$3,Budget!$F$3,0) -> 0 | G53: =N("Car")-IF(DAY(A53)=Budget!$G$4,Budget!$F$4+Budget!$H$4,0) -> 0 | H53: =N("Mom Rent")-IF(DAY(A53)=Budget!$G$5,Budget!$F$5,0) -> 0 | I53: =N("AT&T")-IF(DAY(A53)=Budget!$G$8,Budget!$F$8,0) -> 0 | J53: =N("GA Power")-IF(DAY(A53)=Budget!$G$9,Budget!$F$9,0) -> 0 | K53: =N("Haircut")-IF(DAY(A53)=Budget!$G$10,Budget!$F$10,0) -> 0 | L53: =N("Groceries")-IF(DAY(A53)=Budget!$G$6,Budget!$F$6,0) -> 0 | M53: =N("Savings")-IF(DAY(A53)=Budget!$G$7,Budget!$F$7,0) -> 0 | N53: =N("Car Insurance")-COUNTIF(Budget!$G$14, A53)*Budget!$F$14 -> 0 | O53: =N("Phone Bill")-COUNTIF(Budget!$G$15, A53)*Budget!$F$15 -> 0 | Q53: =N("Spotify")-IF(AND(DAY($A53)=Budget!$M$3, MONTH($A53)=Budget!$L$3),Budget!$K$3,0) -> 0 | R53: =N("Spotify")-IF(AND(DAY($A53)=Budget!$M$4, MONTH($A53)=Budget!$L$4),Budget!$K$4,0) -> 0 | S53: =N("Spotify")-IF(AND(DAY($A53)=Budget!$M$5, MONTH($A53)=Budget!$L$5),Budget!$K$5,0) -> 0 | T53: =N("Amazon Prime")-IF(DAY(A53)=Budget!$Q$3,Budget!$P$3,0) -> 0 | U53: =N("Audible")-IF(DAY(A53)=Budget!$Q$12,Budget!$P$12,0) -> 0 | V53: =N("Crunchyroll")-IF(DAY(A53)=Budget!$Q$5,Budget!$P$5,0) -> 0 | W53: =N("HBO Max")-IF(DAY(A53)=Budget!$Q$6,Budget!$P$6,0) -> 0 | X53: =N("Netflix")-IF(DAY(A53)=Budget!$Q$7,Budget!$P$7,0) -> 0 | Y53: =N("Spotify")-IF(DAY(A53)=Budget!$Q$8,Budget!$P$8,0) -> 0 | Z53: =N("Truebill")-IF(DAY(A53)=Budget!$Q$9,Budget!$P$9,0) -> 0 | AA53: =SUM(D53:Z53) -> 0
A54: =A53+1 -> 45706 | B54: =B53+AA54 -> 2397.77 | C54: =IF(B54>B53,2,IF(B54=B53, 1,0)) -> 0 | D54: 0 | E54: =N("PAY-LM")+IF(WEEKDAY(A54)=Budget!$C$3,Budget!$B$3,0) -> 0 | F54: =N("Rent")-IF(DAY(A54)=Budget!$G$3,Budget!$F$3,0) -> 0 | G54: =N("Car")-IF(DAY(A54)=Budget!$G$4,Budget!$F$4+Budget!$H$4,0) -> 0 | H54: =N("Mom Rent")-IF(DAY(A54)=Budget!$G$5,Budget!$F$5,0) -> 0 | I54: =N("AT&T")-IF(DAY(A54)=Budget!$G$8,Budget!$F$8,0) -> -65 | J54: =N("GA Power")-IF(DAY(A54)=Budget!$G$9,Budget!$F$9,0) -> 0 | K54: =N("Haircut")-IF(DAY(A54)=Budget!$G$10,Budget!$F$10,0) -> 0 | L54: =N("Groceries")-IF(DAY(A54)=Budget!$G$6,Budget!$F$6,0) -> 0 | M54: =N("Savings")-IF(DAY(A54)=Budget!$G$7,Budget!$F$7,0) -> 0 | N54: =N("Car Insurance")-COUNTIF(Budget!$G$14, A54)*Budget!$F$14 -> 0 | O54: =N("Phone Bill")-COUNTIF(Budget!$G$15, A54)*Budget!$F$15 -> 0 | Q54: =N("Spotify")-IF(AND(DAY($A54)=Budget!$M$3, MONTH($A54)=Budget!$L$3),Budget!$K$3,0) -> 0 | R54: =N("Spotify")-IF(AND(DAY($A54)=Budget!$M$4, MONTH($A54)=Budget!$L$4),Budget!$K$4,0) -> 0 | S54: =N("Spotify")-IF(AND(DAY($A54)=Budget!$M$5, MONTH($A54)=Budget!$L$5),Budget!$K$5,0) -> 0 | T54: =N("Amazon Prime")-IF(DAY(A54)=Budget!$Q$3,Budget!$P$3,0) -> 0 | U54: =N("Audible")-IF(DAY(A54)=Budget!$Q$12,Budget!$P$12,0) -> 0 | V54: =N("Crunchyroll")-IF(DAY(A54)=Budget!$Q$5,Budget!$P$5,0) -> 0 | W54: =N("HBO Max")-IF(DAY(A54)=Budget!$Q$6,Budget!$P$6,0) -> 0 | X54: =N("Netflix")-IF(DAY(A54)=Budget!$Q$7,Budget!$P$7,0) -> 0 | Y54: =N("Spotify")-IF(DAY(A54)=Budget!$Q$8,Budget!$P$8,0) -> 0 | Z54: =N("Truebill")-IF(DAY(A54)=Budget!$Q$9,Budget!$P$9,0) -> 0 | AA54: =SUM(D54:Z54) -> -65
A55: =A54+1 -> 45707 | B55: =B54+AA55 -> 2397.77 | C55: =IF(B55>B54,2,IF(B55=B54, 1,0)) -> 1 | D55: 0 | E55: =N("PAY-LM")+IF(WEEKDAY(A55)=Budget!$C$3,Budget!$B$3,0) -> 0 | F55: =N("Rent")-IF(DAY(A55)=Budget!$G$3,Budget!$F$3,0) -> 0 | G55: =N("Car")-IF(DAY(A55)=Budget!$G$4,Budget!$F$4+Budget!$H$4,0) -> 0 | H55: =N("Mom Rent")-IF(DAY(A55)=Budget!$G$5,Budget!$F$5,0) -> 0 | I55: =N("AT&T")-IF(DAY(A55)=Budget!$G$8,Budget!$F$8,0) -> 0 | J55: =N("GA Power")-IF(DAY(A55)=Budget!$G$9,Budget!$F$9,0) -> 0 | K55: =N("Haircut")-IF(DAY(A55)=Budget!$G$10,Budget!$F$10,0) -> 0 | L55: =N("Groceries")-IF(DAY(A55)=Budget!$G$6,Budget!$F$6,0) -> 0 | M55: =N("Savings")-IF(DAY(A55)=Budget!$G$7,Budget!$F$7,0) -> 0 | N55: =N("Car Insurance")-COUNTIF(Budget!$G$14, A55)*Budget!$F$14 -> 0 | O55: =N("Phone Bill")-COUNTIF(Budget!$G$15, A55)*Budget!$F$15 -> 0 | Q55: =N("Spotify")-IF(AND(DAY($A55)=Budget!$M$3, MONTH($A55)=Budget!$L$3),Budget!$K$3,0) -> 0 | R55: =N("Spotify")-IF(AND(DAY($A55)=Budget!$M$4, MONTH($A55)=Budget!$L$4),Budget!$K$4,0) -> 0 | S55: =N("Spotify")-IF(AND(DAY($A55)=Budget!$M$5, MONTH($A55)=Budget!$L$5),Budget!$K$5,0) -> 0 | T55: =N("Amazon Prime")-IF(DAY(A55)=Budget!$Q$3,Budget!$P$3,0) -> 0 | U55: =N("Audible")-IF(DAY(A55)=Budget!$Q$12,Budget!$P$12,0) -> 0 | V55: =N("Crunchyroll")-IF(DAY(A55)=Budget!$Q$5,Budget!$P$5,0) -> 0 | W55: =N("HBO Max")-IF(DAY(A55)=Budget!$Q$6,Budget!$P$6,0) -> 0 | X55: =N("Netflix")-IF(DAY(A55)=Budget!$Q$7,Budget!$P$7,0) -> 0 | Y55: =N("Spotify")-IF(DAY(A55)=Budget!$Q$8,Budget!$P$8,0) -> 0 | Z55: =N("Truebill")-IF(DAY(A55)=Budget!$Q$9,Budget!$P$9,0) -> 0 | AA55: =SUM(D55:Z55) -> 0
A56: =A55+1 -> 45708 | B56: =B55+AA56 -> 1547.77 | C56: =IF(B56>B55,2,IF(B56=B55, 1,0)) -> 0 | D56: 0 | E56: =N("PAY-LM")+IF(WEEKDAY(A56)=Budget!$C$3,Budget!$B$3,0) -> 0 | F56: =N("Rent")-IF(DAY(A56)=Budget!$G$3,Budget!$F$3,0) -> 0 | G56: =N("Car")-IF(DAY(A56)=Budget!$G$4,Budget!$F$4+Budget!$H$4,0) -> 0 | H56: =N("Mom Rent")-IF(DAY(A56)=Budget!$G$5,Budget!$F$5,0) -> -850 | I56: =N("AT&T")-IF(DAY(A56)=Budget!$G$8,Budget!$F$8,0) -> 0 | J56: =N("GA Power")-IF(DAY(A56)=Budget!$G$9,Budget!$F$9,0) -> 0 | K56: =N("Haircut")-IF(DAY(A56)=Budget!$G$10,Budget!$F$10,0) -> 0 | L56: =N("Groceries")-IF(DAY(A56)=Budget!$G$6,Budget!$F$6,0) -> 0 | M56: =N("Savings")-IF(DAY(A56)=Budget!$G$7,Budget!$F$7,0) -> 0 | N56: =N("Car Insurance")-COUNTIF(Budget!$G$14, A56)*Budget!$F$14 -> 0 | O56: =N("Phone Bill")-COUNTIF(Budget!$G$15, A56)*Budget!$F$15 -> 0 | Q56: =N("Spotify")-IF(AND(DAY($A56)=Budget!$M$3, MONTH($A56)=Budget!$L$3),Budget!$K$3,0) -> 0 | R56: =N("Spotify")-IF(AND(DAY($A56)=Budget!$M$4, MONTH($A56)=Budget!$L$4),Budget!$K$4,0) -> 0 | S56: =N("Spotify")-IF(AND(DAY($A56)=Budget!$M$5, MONTH($A56)=Budget!$L$5),Budget!$K$5,0) -> 0 | T56: =N("Amazon Prime")-IF(DAY(A56)=Budget!$Q$3,Budget!$P$3,0) -> 0 | U56: =N("Audible")-IF(DAY(A56)=Budget!$Q$12,Budget!$P$12,0) -> 0 | V56: =N("Crunchyroll")-IF(DAY(A56)=Budget!$Q$5,Budget!$P$5,0) -> 0 | W56: =N("HBO Max")-IF(DAY(A56)=Budget!$Q$6,Budget!$P$6,0) -> 0 | X56: =N("Netflix")-IF(DAY(A56)=Budget!$Q$7,Budget!$P$7,0) -> 0 | Y56: =N("Spotify")-IF(DAY(A56)=Budget!$Q$8,Budget!$P$8,0) -> 0 | Z56: =N("Truebill")-IF(DAY(A56)=Budget!$Q$9,Budget!$P$9,0) -> 0 | AA56: =SUM(D56:Z56) -> -850
A57: =A56+1 -> 45709 | B57: =B56+AA57 -> 3000.77 | C57: =IF(B57>B56,2,IF(B57=B56, 1,0)) -> 2 | D57: 0 | E57: =N("PAY-LM")+IF(WEEKDAY(A57)=Budget!$C$3,Budget!$B$3,0) -> 1453 | F57: =N("Rent")-IF(DAY(A57)=Budget!$G$3,Budget!$F$3,0) -> 0 | G57: =N("Car")-IF(DAY(A57)=Budget!$G$4,Budget!$F$4+Budget!$H$4,0) -> 0 | H57: =N("Mom Rent")-IF(DAY(A57)=Budget!$G$5,Budget!$F$5,0) -> 0 | I57: =N("AT&T")-IF(DAY(A57)=Budget!$G$8,Budget!$F$8,0) -> 0 | J57: =N("GA Power")-IF(DAY(A57)=Budget!$G$9,Budget!$F$9,0) -> 0 | K57: =N("Haircut")-IF(DAY(A57)=Budget!$G$10,Budget!$F$10,0) -> 0 | L57: =N("Groceries")-IF(DAY(A57)=Budget!$G$6,Budget!$F$6,0) -> 0 | M57: =N("Savings")-IF(DAY(A57)=Budget!$G$7,Budget!$F$7,0) -> 0 | N57: =N("Car Insurance")-COUNTIF(Budget!$G$14, A57)*Budget!$F$14 -> 0 | O57: =N("Phone Bill")-COUNTIF(Budget!$G$15, A57)*Budget!$F$15 -> 0 | Q57: =N("Spotify")-IF(AND(DAY($A57)=Budget!$M$3, MONTH($A57)=Budget!$L$3),Budget!$K$3,0) -> 0 | R57: =N("Spotify")-IF(AND(DAY($A57)=Budget!$M$4, MONTH($A57)=Budget!$L$4),Budget!$K$4,0) -> 0 | S57: =N("Spotify")-IF(AND(DAY($A57)=Budget!$M$5, MONTH($A57)=Budget!$L$5),Budget!$K$5,0) -> 0 | T57: =N("Amazon Prime")-IF(DAY(A57)=Budget!$Q$3,Budget!$P$3,0) -> 0 | U57: =N("Audible")-IF(DAY(A57)=Budget!$Q$12,Budget!$P$12,0) -> 0 | V57: =N("Crunchyroll")-IF(DAY(A57)=Budget!$Q$5,Budget!$P$5,0) -> 0 | W57: =N("HBO Max")-IF(DAY(A57)=Budget!$Q$6,Budget!$P$6,0) -> 0 | X57: =N("Netflix")-IF(DAY(A57)=Budget!$Q$7,Budget!$P$7,0) -> 0 | Y57: =N("Spotify")-IF(DAY(A57)=Budget!$Q$8,Budget!$P$8,0) -> 0 | Z57: =N("Truebill")-IF(DAY(A57)=Budget!$Q$9,Budget!$P$9,0) -> 0 | AA57: =SUM(D57:Z57) -> 1453
A58: =A57+1 -> 45710 | B58: =B57+AA58 -> 3000.77 | C58: =IF(B58>B57,2,IF(B58=B57, 1,0)) -> 1 | D58: 0 | E58: =N("PAY-LM")+IF(WEEKDAY(A58)=Budget!$C$3,Budget!$B$3,0) -> 0 | F58: =N("Rent")-IF(DAY(A58)=Budget!$G$3,Budget!$F$3,0) -> 0 | G58: =N("Car")-IF(DAY(A58)=Budget!$G$4,Budget!$F$4+Budget!$H$4,0) -> 0 | H58: =N("Mom Rent")-IF(DAY(A58)=Budget!$G$5,Budget!$F$5,0) -> 0 | I58: =N("AT&T")-IF(DAY(A58)=Budget!$G$8,Budget!$F$8,0) -> 0 | J58: =N("GA Power")-IF(DAY(A58)=Budget!$G$9,Budget!$F$9,0) -> 0 | K58: =N("Haircut")-IF(DAY(A58)=Budget!$G$10,Budget!$F$10,0) -> 0 | L58: =N("Groceries")-IF(DAY(A58)=Budget!$G$6,Budget!$F$6,0) -> 0 | M58: =N("Savings")-IF(DAY(A58)=Budget!$G$7,Budget!$F$7,0) -> 0 | N58: =N("Car Insurance")-COUNTIF(Budget!$G$14, A58)*Budget!$F$14 -> 0 | O58: =N("Phone Bill")-COUNTIF(Budget!$G$15, A58)*Budget!$F$15 -> 0 | Q58: =N("Spotify")-IF(AND(DAY($A58)=Budget!$M$3, MONTH($A58)=Budget!$L$3),Budget!$K$3,0) -> 0 | R58: =N("Spotify")-IF(AND(DAY($A58)=Budget!$M$4, MONTH($A58)=Budget!$L$4),Budget!$K$4,0) -> 0 | S58: =N("Spotify")-IF(AND(DAY($A58)=Budget!$M$5, MONTH($A58)=Budget!$L$5),Budget!$K$5,0) -> 0 | T58: =N("Amazon Prime")-IF(DAY(A58)=Budget!$Q$3,Budget!$P$3,0) -> 0 | U58: =N("Audible")-IF(DAY(A58)=Budget!$Q$12,Budget!$P$12,0) -> 0 | V58: =N("Crunchyroll")-IF(DAY(A58)=Budget!$Q$5,Budget!$P$5,0) -> 0 | W58: =N("HBO Max")-IF(DAY(A58)=Budget!$Q$6,Budget!$P$6,0) -> 0 | X58: =N("Netflix")-IF(DAY(A58)=Budget!$Q$7,Budget!$P$7,0) -> 0 | Y58: =N("Spotify")-IF(DAY(A58)=Budget!$Q$8,Budget!$P$8,0) -> 0 | Z58: =N("Truebill")-IF(DAY(A58)=Budget!$Q$9,Budget!$P$9,0) -> 0 | AA58: =SUM(D58:Z58) -> 0
A59: =A58+1 -> 45711 | B59: =B58+AA59 -> 3000.77 | C59: =IF(B59>B58,2,IF(B59=B58, 1,0)) -> 1 | D59: 0 | E59: =N("PAY-LM")+IF(WEEKDAY(A59)=Budget!$C$3,Budget!$B$3,0) -> 0 | F59: =N("Rent")-IF(DAY(A59)=Budget!$G$3,Budget!$F$3,0) -> 0 | G59: =N("Car")-IF(DAY(A59)=Budget!$G$4,Budget!$F$4+Budget!$H$4,0) -> 0 | H59: =N("Mom Rent")-IF(DAY(A59)=Budget!$G$5,Budget!$F$5,0) -> 0 | I59: =N("AT&T")-IF(DAY(A59)=Budget!$G$8,Budget!$F$8,0) -> 0 | J59: =N("GA Power")-IF(DAY(A59)=Budget!$G$9,Budget!$F$9,0) -> 0 | K59: =N("Haircut")-IF(DAY(A59)=Budget!$G$10,Budget!$F$10,0) -> 0 | L59: =N("Groceries")-IF(DAY(A59)=Budget!$G$6,Budget!$F$6,0) -> 0 | M59: =N("Savings")-IF(DAY(A59)=Budget!$G$7,Budget!$F$7,0) -> 0 | N59: =N("Car Insurance")-COUNTIF(Budget!$G$14, A59)*Budget!$F$14 -> 0 | O59: =N("Phone Bill")-COUNTIF(Budget!$G$15, A59)*Budget!$F$15 -> 0 | Q59: =N("Spotify")-IF(AND(DAY($A59)=Budget!$M$3, MONTH($A59)=Budget!$L$3),Budget!$K$3,0) -> 0 | R59: =N("Spotify")-IF(AND(DAY($A59)=Budget!$M$4, MONTH($A59)=Budget!$L$4),Budget!$K$4,0) -> 0 | S59: =N("Spotify")-IF(AND(DAY($A59)=Budget!$M$5, MONTH($A59)=Budget!$L$5),Budget!$K$5,0) -> 0 | T59: =N("Amazon Prime")-IF(DAY(A59)=Budget!$Q$3,Budget!$P$3,0) -> 0 | U59: =N("Audible")-IF(DAY(A59)=Budget!$Q$12,Budget!$P$12,0) -> 0 | V59: =N("Crunchyroll")-IF(DAY(A59)=Budget!$Q$5,Budget!$P$5,0) -> 0 | W59: =N("HBO Max")-IF(DAY(A59)=Budget!$Q$6,Budget!$P$6,0) -> 0 | X59: =N("Netflix")-IF(DAY(A59)=Budget!$Q$7,Budget!$P$7,0) -> 0 | Y59: =N("Spotify")-IF(DAY(A59)=Budget!$Q$8,Budget!$P$8,0) -> 0 | Z59: =N("Truebill")-IF(DAY(A59)=Budget!$Q$9,Budget!$P$9,0) -> 0 | AA59: =SUM(D59:Z59) -> 0
A60: =A59+1 -> 45712 | B60: =B59+AA60 -> 3000.77 | C60: =IF(B60>B59,2,IF(B60=B59, 1,0)) -> 1 | D60: 0 | E60: =N("PAY-LM")+IF(WEEKDAY(A60)=Budget!$C$3,Budget!$B$3,0) -> 0 | F60: =N("Rent")-IF(DAY(A60)=Budget!$G$3,Budget!$F$3,0) -> 0 | G60: =N("Car")-IF(DAY(A60)=Budget!$G$4,Budget!$F$4+Budget!$H$4,0) -> 0 | H60: =N("Mom Rent")-IF(DAY(A60)=Budget!$G$5,Budget!$F$5,0) -> 0 | I60: =N("AT&T")-IF(DAY(A60)=Budget!$G$8,Budget!$F$8,0) -> 0 | J60: =N("GA Power")-IF(DAY(A60)=Budget!$G$9,Budget!$F$9,0) -> 0 | K60: =N("Haircut")-IF(DAY(A60)=Budget!$G$10,Budget!$F$10,0) -> 0 | L60: =N("Groceries")-IF(DAY(A60)=Budget!$G$6,Budget!$F$6,0) -> 0 | M60: =N("Savings")-IF(DAY(A60)=Budget!$G$7,Budget!$F$7,0) -> 0 | N60: =N("Car Insurance")-COUNTIF(Budget!$G$14, A60)*Budget!$F$14 -> 0 | O60: =N("Phone Bill")-COUNTIF(Budget!$G$15, A60)*Budget!$F$15 -> 0 | Q60: =N("Spotify")-IF(AND(DAY($A60)=Budget!$M$3, MONTH($A60)=Budget!$L$3),Budget!$K$3,0) -> 0 | R60: =N("Spotify")-IF(AND(DAY($A60)=Budget!$M$4, MONTH($A60)=Budget!$L$4),Budget!$K$4,0) -> 0 | S60: =N("Spotify")-IF(AND(DAY($A60)=Budget!$M$5, MONTH($A60)=Budget!$L$5),Budget!$K$5,0) -> 0 | T60: =N("Amazon Prime")-IF(DAY(A60)=Budget!$Q$3,Budget!$P$3,0) -> 0 | U60: =N("Audible")-IF(DAY(A60)=Budget!$Q$12,Budget!$P$12,0) -> 0 | V60: =N("Crunchyroll")-IF(DAY(A60)=Budget!$Q$5,Budget!$P$5,0) -> 0 | W60: =N("HBO Max")-IF(DAY(A60)=Budget!$Q$6,Budget!$P$6,0) -> 0 | X60: =N("Netflix")-IF(DAY(A60)=Budget!$Q$7,Budget!$P$7,0) -> 0 | Y60: =N("Spotify")-IF(DAY(A60)=Budget!$Q$8,Budget!$P$8,0) -> 0 | Z60: =N("Truebill")-IF(DAY(A60)=Budget!$Q$9,Budget!$P$9,0) -> 0 | AA60: =SUM(D60:Z60) -> 0
A61: =A60+1 -> 45713 | B61: =2681.33 -> 2681.33 | C61: =IF(B61>B60,2,IF(B61=B60, 1,0)) -> 0 | D61: 0 | E61: =N("PAY-LM")+IF(WEEKDAY(A61)=Budget!$C$3,Budget!$B$3,0) -> 0 | F61: =N("Rent")-IF(DAY(A61)=Budget!$G$3,Budget!$F$3,0) -> 0 | G61: =N("Car")-IF(DAY(A61)=Budget!$G$4,Budget!$F$4+Budget!$H$4,0) -> 0 | H61: =N("Mom Rent")-IF(DAY(A61)=Budget!$G$5,Budget!$F$5,0) -> 0 | I61: =N("AT&T")-IF(DAY(A61)=Budget!$G$8,Budget!$F$8,0) -> 0 | J61: =N("GA Power")-IF(DAY(A61)=Budget!$G$9,Budget!$F$9,0) -> 0 | K61: =N("Haircut")-IF(DAY(A61)=Budget!$G$10,Budget!$F$10,0) -> 0 | L61: =N("Groceries")-IF(DAY(A61)=Budget!$G$6,Budget!$F$6,0) -> 0 | M61: =N("Savings")-IF(DAY(A61)=Budget!$G$7,Budget!$F$7,0) -> 0 | N61: =N("Car Insurance")-COUNTIF(Budget!$G$14, A61)*Budget!$F$14 -> 0 | O61: =N("Phone Bill")-COUNTIF(Budget!$G$15, A61)*Budget!$F$15 -> 0 | Q61: =N("Spotify")-IF(AND(DAY($A61)=Budget!$M$3, MONTH($A61)=Budget!$L$3),Budget!$K$3,0) -> 0 | R61: =N("Spotify")-IF(AND(DAY($A61)=Budget!$M$4, MONTH($A61)=Budget!$L$4),Budget!$K$4,0) -> 0 | S61: =N("Spotify")-IF(AND(DAY($A61)=Budget!$M$5, MONTH($A61)=Budget!$L$5),Budget!$K$5,0) -> 0 | T61: =N("Amazon Prime")-IF(DAY(A61)=Budget!$Q$3,Budget!$P$3,0) -> 0 | U61: =N("Audible")-IF(DAY(A61)=Budget!$Q$12,Budget!$P$12,0) -> 0 | V61: =N("Crunchyroll")-IF(DAY(A61)=Budget!$Q$5,Budget!$P$5,0) -> 0 | W61: =N("HBO Max")-IF(DAY(A61)=Budget!$Q$6,Budget!$P$6,0) -> 0 | X61: =N("Netflix")-IF(DAY(A61)=Budget!$Q$7,Budget!$P$7,0) -> 0 | Y61: =N("Spotify")-IF(DAY(A61)=Budget!$Q$8,Budget!$P$8,0) -> 0 | Z61: =N("Truebill")-IF(DAY(A61)=Budget!$Q$9,Budget!$P$9,0) -> 0 | AA61: =SUM(D61:Z61) -> 0
A62: =A61+1 -> 45714 | B62: =B61+AA62 -> 2281.33 | C62: =IF(B62>B61,2,IF(B62=B61, 1,0)) -> 0 | D62: 0 | E62: =N("PAY-LM")+IF(WEEKDAY(A62)=Budget!$C$3,Budget!$B$3,0) -> 0 | F62: =N("Rent")-IF(DAY(A62)=Budget!$G$3,Budget!$F$3,0) -> 0 | G62: =N("Car")-IF(DAY(A62)=Budget!$G$4,Budget!$F$4+Budget!$H$4,0) -> 0 | H62: =N("Mom Rent")-IF(DAY(A62)=Budget!$G$5,Budget!$F$5,0) -> 0 | I62: =N("AT&T")-IF(DAY(A62)=Budget!$G$8,Budget!$F$8,0) -> 0 | J62: =N("GA Power")-IF(DAY(A62)=Budget!$G$9,Budget!$F$9,0) -> 0 | K62: =N("Haircut")-IF(DAY(A62)=Budget!$G$10,Budget!$F$10,0) -> -400 | L62: =N("Groceries")-IF(DAY(A62)=Budget!$G$6,Budget!$F$6,0) -> 0 | M62: =N("Savings")-IF(DAY(A62)=Budget!$G$7,Budget!$F$7,0) -> 0 | N62: =N("Car Insurance")-COUNTIF(Budget!$G$14, A62)*Budget!$F$14 -> 0 | O62: =N("Phone Bill")-COUNTIF(Budget!$G$15, A62)*Budget!$F$15 -> 0 | Q62: =N("Spotify")-IF(AND(DAY($A62)=Budget!$M$3, MONTH($A62)=Budget!$L$3),Budget!$K$3,0) -> 0 | R62: =N("Spotify")-IF(AND(DAY($A62)=Budget!$M$4, MONTH($A62)=Budget!$L$4),Budget!$K$4,0) -> 0 | S62: =N("Spotify")-IF(AND(DAY($A62)=Budget!$M$5, MONTH($A62)=Budget!$L$5),Budget!$K$5,0) -> 0 | T62: =N("Amazon Prime")-IF(DAY(A62)=Budget!$Q$3,Budget!$P$3,0) -> 0 | U62: =N("Audible")-IF(DAY(A62)=Budget!$Q$12,Budget!$P$12,0) -> 0 | V62: =N("Crunchyroll")-IF(DAY(A62)=Budget!$Q$5,Budget!$P$5,0) -> 0 | W62: =N("HBO Max")-IF(DAY(A62)=Budget!$Q$6,Budget!$P$6,0) -> 0 | X62: =N("Netflix")-IF(DAY(A62)=Budget!$Q$7,Budget!$P$7,0) -> 0 | Y62: =N("Spotify")-IF(DAY(A62)=Budget!$Q$8,Budget!$P$8,0) -> 0 | Z62: =N("Truebill")-IF(DAY(A62)=Budget!$Q$9,Budget!$P$9,0) -> 0 | AA62: =SUM(D62:Z62) -> -400
A63: =A62+1 -> 45715 | B63: =B62+AA63 -> 2281.33 | C63: =IF(B63>B62,2,IF(B63=B62, 1,0)) -> 1 | D63: 0 | E63: =N("PAY-LM")+IF(WEEKDAY(A63)=Budget!$C$3,Budget!$B$3,0) -> 0 | F63: =N("Rent")-IF(DAY(A63)=Budget!$G$3,Budget!$F$3,0) -> 0 | G63: =N("Car")-IF(DAY(A63)=Budget!$G$4,Budget!$F$4+Budget!$H$4,0) -> 0 | H63: =N("Mom Rent")-IF(DAY(A63)=Budget!$G$5,Budget!$F$5,0) -> 0 | I63: =N("AT&T")-IF(DAY(A63)=Budget!$G$8,Budget!$F$8,0) -> 0 | J63: =N("GA Power")-IF(DAY(A63)=Budget!$G$9,Budget!$F$9,0) -> 0 | K63: =N("Haircut")-IF(DAY(A63)=Budget!$G$10,Budget!$F$10,0) -> 0 | L63: =N("Groceries")-IF(DAY(A63)=Budget!$G$6,Budget!$F$6,0) -> 0 | M63: =N("Savings")-IF(DAY(A63)=Budget!$G$7,Budget!$F$7,0) -> 0 | N63: =N("Car Insurance")-COUNTIF(Budget!$G$14, A63)*Budget!$F$14 -> 0 | O63: =N("Phone Bill")-COUNTIF(Budget!$G$15, A63)*Budget!$F$15 -> 0 | Q63: =N("Spotify")-IF(AND(DAY($A63)=Budget!$M$3, MONTH($A63)=Budget!$L$3),Budget!$K$3,0) -> 0 | R63: =N("Spotify")-IF(AND(DAY($A63)=Budget!$M$4, MONTH($A63)=Budget!$L$4),Budget!$K$4,0) -> 0 | S63: =N("Spotify")-IF(AND(DAY($A63)=Budget!$M$5, MONTH($A63)=Budget!$L$5),Budget!$K$5,0) -> 0 | T63: =N("Amazon Prime")-IF(DAY(A63)=Budget!$Q$3,Budget!$P$3,0) -> 0 | U63: =N("Audible")-IF(DAY(A63)=Budget!$Q$12,Budget!$P$12,0) -> 0 | V63: =N("Crunchyroll")-IF(DAY(A63)=Budget!$Q$5,Budget!$P$5,0) -> 0 | W63: =N("HBO Max")-IF(DAY(A63)=Budget!$Q$6,Budget!$P$6,0) -> 0 | X63: =N("Netflix")-IF(DAY(A63)=Budget!$Q$7,Budget!$P$7,0) -> 0 | Y63: =N("Spotify")-IF(DAY(A63)=Budget!$Q$8,Budget!$P$8,0) -> 0 | Z63: =N("Truebill")-IF(DAY(A63)=Budget!$Q$9,Budget!$P$9,0) -> 0 | AA63: =SUM(D63:Z63) -> 0
A64: =A63+1 -> 45716 | B64: =B63+AA64 -> 2584.33 | C64: =IF(B64>B63,2,IF(B64=B63, 1,0)) -> 2 | D64: 0 | E64: =N("PAY-LM")+IF(WEEKDAY(A64)=Budget!$C$3,Budget!$B$3,0) -> 1453 | F64: =N("Rent")-IF(DAY(A64)=Budget!$G$3,Budget!$F$3,0) -> 0 | G64: =N("Car")-IF(DAY(A64)=Budget!$G$4,Budget!$F$4+Budget!$H$4,0) -> 0 | H64: =N("Mom Rent")-IF(DAY(A64)=Budget!$G$5,Budget!$F$5,0) -> 0 | I64: =N("AT&T")-IF(DAY(A64)=Budget!$G$8,Budget!$F$8,0) -> 0 | J64: =N("GA Power")-IF(DAY(A64)=Budget!$G$9,Budget!$F$9,0) -> 0 | K64: =N("Haircut")-IF(DAY(A64)=Budget!$G$10,Budget!$F$10,0) -> 0 | L64: =N("Groceries")-IF(DAY(A64)=Budget!$G$6,Budget!$F$6,0) -> 0 | M64: =N("Savings")-IF(DAY(A64)=Budget!$G$7,Budget!$F$7,0) -> -1000 | N64: =N("Car Insurance")-COUNTIF(Budget!$G$14, A64)*Budget!$F$14 -> 0 | O64: =N("Phone Bill")-COUNTIF(Budget!$G$15, A64)*Budget!$F$15 -> 0 | Q64: =N("Spotify")-IF(AND(DAY($A64)=Budget!$M$3, MONTH($A64)=Budget!$L$3),Budget!$K$3,0) -> 0 | R64: =N("Spotify")-IF(AND(DAY($A64)=Budget!$M$4, MONTH($A64)=Budget!$L$4),Budget!$K$4,0) -> 0 | S64: =N("Spotify")-IF(AND(DAY($A64)=Budget!$M$5, MONTH($A64)=Budget!$L$5),Budget!$K$5,0) -> 0 | T64: =N("Amazon Prime")-IF(DAY(A64)=Budget!$Q$3,Budget!$P$3,0) -> 0 | U64: =N("Audible")-IF(DAY(A64)=Budget!$Q$12,Budget!$P$12,0) -> 0 | V64: =N("Crunchyroll")-IF(DAY(A64)=Budget!$Q$5,Budget!$P$5,0) -> 0 | W64: =N("HBO Max")-IF(DAY(A64)=Budget!$Q$6,Budget!$P$6,0) -> 0 | X64: =N("Netflix")-IF(DAY(A64)=Budget!$Q$7,Budget!$P$7,0) -> 0 | Y64: =N("Spotify")-IF(DAY(A64)=Budget!$Q$8,Budget!$P$8,0) -> -150 | Z64: =N("Truebill")-IF(DAY(A64)=Budget!$Q$9,Budget!$P$9,0) -> 0 | AA64: =SUM(D64:Z64) -> 303
D67: Miscellaneous | E67: Monthly Expenses | N67: =Budget!$E$12 -> Annual Expenses | Q67: Credit Card | T67: Subscriptions | AA67: TOTAL | AC67: =SUMIF(D69:Z99,"<0") -> -5121.42 | AD67: =SUM(E69:E99) -> 5812
A68: =EDATE(A36,1) -> 45717 | E68: =Budget!$A$3 -> PAY-LM | F68: =Budget!$E$3 -> Rent | G68: =Budget!$E$4 -> Car | H68: =Budget!$E$5 -> Mom Rent | I68: =Budget!$E$8 -> AT&T | J68: =Budget!$E$9 -> GA Power | K68: =Budget!$E$10 -> TH | L68: =Budget!$E$6 -> Groceries | M68: =Budget!$E$7 -> Savings | N68: =Budget!$E$14 -> Car Insurance | O68: =Budget!$E$15 -> Phone Bill | Q68: =Budget!$J$3 -> Capital One | R68: =Budget!$J$4 -> Chase | S68: =Budget!$J$5 -> NFCU | T68: =Budget!$O$3 -> Amazon Prime | U68: =Budget!$O$12 -> Audible | V68: =Budget!$O$5 -> Netflix | W68: =Budget!$O$6 -> Spotify | X68: =Budget!$O$7 -> Rocket Money | Y68: =Budget!$O$8 -> Little4Much | Z68: =Budget!$O$9 -> None | AC68: =AD67+AC67 -> 690.58
A69: =A68 -> 45717 | B69: =B64+AA69 -> 961.33 | C69: =IF(B69>B64,2,IF(B69=B64, 1,0)) -> 0 | D69: 110 | E69: =N("PAY-LM")+IF(WEEKDAY(A69)=Budget!$C$3,Budget!$B$3,0) -> 0 | F69: =N("Rent")-IF(DAY(A69)=Budget!$G$3,Budget!$F$3,0) -> -1733 | G69: =N("Car")-IF(DAY(A69)=Budget!$G$4,Budget!$F$4+Budget!$H$4,0) -> 0 | H69: =N("Mom Rent")-IF(DAY(A69)=Budget!$G$5,Budget!$F$5,0) -> 0 | I69: =N("AT&T")-IF(DAY(A69)=Budget!$G$8,Budget!$F$8,0) -> 0 | J69: =N("GA Power")-IF(DAY(A69)=Budget!$G$9,Budget!$F$9,0) -> 0 | K69: =N("Haircut")-IF(DAY(A69)=Budget!$G$10,Budget!$F$10,0) -> 0 | L69: =N("Groceries")-IF(DAY(A69)=Budget!$G$6,Budget!$F$6,0) -> 0 | M69: =N("Savings")-IF(DAY(A69)=Budget!$G$7,Budget!$F$7,0) -> 0 | N69: =N("Car Insurance")-COUNTIF(Budget!$G$14, A69)*Budget!$F$14 -> 0 | O69: =N("Phone Bill")-COUNTIF(Budget!$G$15, A69)*Budget!$F$15 -> 0 | Q69: =N("Spotify")-IF(AND(DAY($A69)=Budget!$M$3, MONTH($A69)=Budget!$L$3),Budget!$K$3,0) -> 0 | R69: =N("Spotify")-IF(AND(DAY($A69)=Budget!$M$4, MONTH($A69)=Budget!$L$4),Budget!$K$4,0) -> 0 | S69: =N("Spotify")-IF(AND(DAY($A69)=Budget!$M$5, MONTH($A69)=Budget!$L$5),Budget!$K$5,0) -> 0 | T69: =N("Amazon Prime")-IF(DAY(A69)=Budget!$Q$3,Budget!$P$3,0) -> 0 | U69: =N("Audible")-IF(DAY(A69)=Budget!$Q$12,Budget!$P$12,0) -> 0 | V69: =N("Crunchyroll")-IF(DAY(A69)=Budget!$Q$5,Budget!$P$5,0) -> 0 | W69: =N("HBO Max")-IF(DAY(A69)=Budget!$Q$6,Budget!$P$6,0) -> 0 | X69: =N("Netflix")-IF(DAY(A69)=Budget!$Q$7,Budget!$P$7,0) -> 0 | Y69: =N("Spotify")-IF(DAY(A69)=Budget!$Q$8,Budget!$P$8,0) -> 0 | Z69: =N("Truebill")-IF(DAY(A69)=Budget!$Q$9,Budget!$P$9,0) -> 0 | AA69: =SUM(D69:Z69) -> -1623
A70: =A69+1 -> 45718 | B70: =B69+AA70 -> 157.98 | C70: =IF(B70>B69,2,IF(B70=B69, 1,0)) -> 0 | D70: 0 | E70: =N("PAY-LM")+IF(WEEKDAY(A70)=Budget!$C$3,Budget!$B$3,0) -> 0 | F70: =N("Rent")-IF(DAY(A70)=Budget!$G$3,Budget!$F$3,0) -> 0 | G70: =N("Car")-IF(DAY(A70)=Budget!$G$4,Budget!$F$4+Budget!$H$4,0) -> -503.35 | H70: =N("Mom Rent")-IF(DAY(A70)=Budget!$G$5,Budget!$F$5,0) -> 0 | I70: =N("AT&T")-IF(DAY(A70)=Budget!$G$8,Budget!$F$8,0) -> 0 | J70: =N("GA Power")-IF(DAY(A70)=Budget!$G$9,Budget!$F$9,0) -> 0 | K70: =N("Haircut")-IF(DAY(A70)=Budget!$G$10,Budget!$F$10,0) -> 0 | L70: =N("Groceries")-IF(DAY(A70)=Budget!$G$6,Budget!$F$6,0) -> -300 | M70: =N("Savings")-IF(DAY(A70)=Budget!$G$7,Budget!$F$7,0) -> 0 | N70: =N("Car Insurance")-COUNTIF(Budget!$G$14, A70)*Budget!$F$14 -> 0 | O70: =N("Phone Bill")-COUNTIF(Budget!$G$15, A70)*Budget!$F$15 -> 0 | Q70: =N("Spotify")-IF(AND(DAY($A70)=Budget!$M$3, MONTH($A70)=Budget!$L$3),Budget!$K$3,0) -> 0 | R70: =N("Spotify")-IF(AND(DAY($A70)=Budget!$M$4, MONTH($A70)=Budget!$L$4),Budget!$K$4,0) -> 0 | S70: =N("Spotify")-IF(AND(DAY($A70)=Budget!$M$5, MONTH($A70)=Budget!$L$5),Budget!$K$5,0) -> 0 | T70: =N("Amazon Prime")-IF(DAY(A70)=Budget!$Q$3,Budget!$P$3,0) -> 0 | U70: =N("Audible")-IF(DAY(A70)=Budget!$Q$12,Budget!$P$12,0) -> 0 | V70: =N("Crunchyroll")-IF(DAY(A70)=Budget!$Q$5,Budget!$P$5,0) -> 0 | W70: =N("HBO Max")-IF(DAY(A70)=Budget!$Q$6,Budget!$P$6,0) -> 0 | X70: =N("Netflix")-IF(DAY(A70)=Budget!$Q$7,Budget!$P$7,0) -> 0 | Y70: =N("Spotify")-IF(DAY(A70)=Budget!$Q$8,Budget!$P$8,0) -> 0 | Z70: =N("Truebill")-IF(DAY(A70)=Budget!$Q$9,Budget!$P$9,0) -> 0 | AA70: =SUM(D70:Z70) -> -803.35
A71: =A70+1 -> 45719 | B71: =B70+AA71 -> 157.98 | C71: =IF(B71>B70,2,IF(B71=B70, 1,0)) -> 1 | D71: 0 | E71: =N("PAY-LM")+IF(WEEKDAY(A71)=Budget!$C$3,Budget!$B$3,0) -> 0 | F71: =N("Rent")-IF(DAY(A71)=Budget!$G$3,Budget!$F$3,0) -> 0 | G71: =N("Car")-IF(DAY(A71)=Budget!$G$4,Budget!$F$4+Budget!$H$4,0) -> 0 | H71: =N("Mom Rent")-IF(DAY(A71)=Budget!$G$5,Budget!$F$5,0) -> 0 | I71: =N("AT&T")-IF(DAY(A71)=Budget!$G$8,Budget!$F$8,0) -> 0 | J71: =N("GA Power")-IF(DAY(A71)=Budget!$G$9,Budget!$F$9,0) -> 0 | K71: =N("Haircut")-IF(DAY(A71)=Budget!$G$10,Budget!$F$10,0) -> 0 | L71: =N("Groceries")-IF(DAY(A71)=Budget!$G$6,Budget!$F$6,0) -> 0 | M71: =N("Savings")-IF(DAY(A71)=Budget!$G$7,Budget!$F$7,0) -> 0 | N71: =N("Car Insurance")-COUNTIF(Budget!$G$14, A71)*Budget!$F$14 -> 0 | O71: =N("Phone Bill")-COUNTIF(Budget!$G$15, A71)*Budget!$F$15 -> 0 | Q71: =N("Spotify")-IF(AND(DAY($A71)=Budget!$M$3, MONTH($A71)=Budget!$L$3),Budget!$K$3,0) -> 0 | R71: =N("Spotify")-IF(AND(DAY($A71)=Budget!$M$4, MONTH($A71)=Budget!$L$4),Budget!$K$4,0) -> 0 | S71: =N("Spotify")-IF(AND(DAY($A71)=Budget!$M$5, MONTH($A71)=Budget!$L$5),Budget!$K$5,0) -> 0 | T71: =N("Amazon Prime")-IF(DAY(A71)=Budget!$Q$3,Budget!$P$3,0) -> 0 | U71: =N("Audible")-IF(DAY(A71)=Budget!$Q$12,Budget!$P$12,0) -> 0 | V71: =N("Crunchyroll")-IF(DAY(A71)=Budget!$Q$5,Budget!$P$5,0) -> 0 | W71: =N("HBO Max")-IF(DAY(A71)=Budget!$Q$6,Budget!$P$6,0) -> 0 | X71: =N("Netflix")-IF(DAY(A71)=Budget!$Q$7,Budget!$P$7,0) -> 0 | Y71: =N("Spotify")-IF(DAY(A71)=Budget!$Q$8,Budget!$P$8,0) -> 0 | Z71: =N("Truebill")-IF(DAY(A71)=Budget!$Q$9,Budget!$P$9,0) -> 0 | AA71: =SUM(D71:Z71) -> 0
A72: =A71+1 -> 45720 | B72: =B71+AA72 -> 157.98 | C72: =IF(B72>B71,2,IF(B72=B71, 1,0)) -> 1 | D72: 0 | E72: =N("PAY-LM")+IF(WEEKDAY(A72)=Budget!$C$3,Budget!$B$3,0) -> 0 | F72: =N("Rent")-IF(DAY(A72)=Budget!$G$3,Budget!$F$3,0) -> 0 | G72: =N("Car")-IF(DAY(A72)=Budget!$G$4,Budget!$F$4+Budget!$H$4,0) -> 0 | H72: =N("Mom Rent")-IF(DAY(A72)=Budget!$G$5,Budget!$F$5,0) -> 0 | I72: =N("AT&T")-IF(DAY(A72)=Budget!$G$8,Budget!$F$8,0) -> 0 | J72: =N("GA Power")-IF(DAY(A72)=Budget!$G$9,Budget!$F$9,0) -> 0 | K72: =N("Haircut")-IF(DAY(A72)=Budget!$G$10,Budget!$F$10,0) -> 0 | L72: =N("Groceries")-IF(DAY(A72)=Budget!$G$6,Budget!$F$6,0) -> 0 | M72: =N("Savings")-IF(DAY(A72)=Budget!$G$7,Budget!$F$7,0) -> 0 | N72: =N("Car Insurance")-COUNTIF(Budget!$G$14, A72)*Budget!$F$14 -> 0 | O72: =N("Phone Bill")-COUNTIF(Budget!$G$15, A72)*Budget!$F$15 -> 0 | Q72: =N("Spotify")-IF(AND(DAY($A72)=Budget!$M$3, MONTH($A72)=Budget!$L$3),Budget!$K$3,0) -> 0 | R72: =N("Spotify")-IF(AND(DAY($A72)=Budget!$M$4, MONTH($A72)=Budget!$L$4),Budget!$K$4,0) -> 0 | S72: =N("Spotify")-IF(AND(DAY($A72)=Budget!$M$5, MONTH($A72)=Budget!$L$5),Budget!$K$5,0) -> 0 | T72: =N("Amazon Prime")-IF(DAY(A72)=Budget!$Q$3,Budget!$P$3,0) -> 0 | U72: =N("Audible")-IF(DAY(A72)=Budget!$Q$12,Budget!$P$12,0) -> 0 | V72: =N("Crunchyroll")-IF(DAY(A72)=Budget!$Q$5,Budget!$P$5,0) -> 0 | W72: =N("HBO Max")-IF(DAY(A72)=Budget!$Q$6,Budget!$P$6,0) -> 0 | X72: =N("Netflix")-IF(DAY(A72)=Budget!$Q$7,Budget!$P$7,0) -> 0 | Y72: =N("Spotify")-IF(DAY(A72)=Budget!$Q$8,Budget!$P$8,0) -> 0 | Z72: =N("Truebill")-IF(DAY(A72)=Budget!$Q$9,Budget!$P$9,0) -> 0 | AA72: =SUM(D72:Z72) -> 0
A73: =A72+1 -> 45721 | B73: =B72+AA73 -> 87.98 | C73: =IF(B73>B72,2,IF(B73=B72, 1,0)) -> 0 | D73: 0 | E73: =N("PAY-LM")+IF(WEEKDAY(A73)=Budget!$C$3,Budget!$B$3,0) -> 0 | F73: =N("Rent")-IF(DAY(A73)=Budget!$G$3,Budget!$F$3,0) -> 0 | G73: =N("Car")-IF(DAY(A73)=Budget!$G$4,Budget!$F$4+Budget!$H$4,0) -> 0 | H73: =N("Mom Rent")-IF(DAY(A73)=Budget!$G$5,Budget!$F$5,0) -> 0 | I73: =N("AT&T")-IF(DAY(A73)=Budget!$G$8,Budget!$F$8,0) -> 0 | J73: =N("GA Power")-IF(DAY(A73)=Budget!$G$9,Budget!$F$9,0) -> -70 | K73: =N("Haircut")-IF(DAY(A73)=Budget!$G$10,Budget!$F$10,0) -> 0 | L73: =N("Groceries")-IF(DAY(A73)=Budget!$G$6,Budget!$F$6,0) -> 0 | M73: =N("Savings")-IF(DAY(A73)=Budget!$G$7,Budget!$F$7,0) -> 0 | N73: =N("Car Insurance")-COUNTIF(Budget!$G$14, A73)*Budget!$F$14 -> 0 | O73: =N("Phone Bill")-COUNTIF(Budget!$G$15, A73)*Budget!$F$15 -> 0 | Q73: =N("Spotify")-IF(AND(DAY($A73)=Budget!$M$3, MONTH($A73)=Budget!$L$3),Budget!$K$3,0) -> 0 | R73: =N("Spotify")-IF(AND(DAY($A73)=Budget!$M$4, MONTH($A73)=Budget!$L$4),Budget!$K$4,0) -> 0 | S73: =N("Spotify")-IF(AND(DAY($A73)=Budget!$M$5, MONTH($A73)=Budget!$L$5),Budget!$K$5,0) -> 0 | T73: =N("Amazon Prime")-IF(DAY(A73)=Budget!$Q$3,Budget!$P$3,0) -> 0 | U73: =N("Audible")-IF(DAY(A73)=Budget!$Q$12,Budget!$P$12,0) -> 0 | V73: =N("Crunchyroll")-IF(DAY(A73)=Budget!$Q$5,Budget!$P$5,0) -> 0 | W73: =N("HBO Max")-IF(DAY(A73)=Budget!$Q$6,Budget!$P$6,0) -> 0 | X73: =N("Netflix")-IF(DAY(A73)=Budget!$Q$7,Budget!$P$7,0) -> 0 | Y73: =N("Spotify")-IF(DAY(A73)=Budget!$Q$8,Budget!$P$8,0) -> 0 | Z73: =N("Truebill")-IF(DAY(A73)=Budget!$Q$9,Budget!$P$9,0) -> 0 | AA73: =SUM(D73:Z73) -> -70
A74: =A73+1 -> 45722 | B74: =B73+AA74 -> 87.98 | C74: =IF(B74>B73,2,IF(B74=B73, 1,0)) -> 1 | D74: 0 | E74: =N("PAY-LM")+IF(WEEKDAY(A74)=Budget!$C$3,Budget!$B$3,0) -> 0 | F74: =N("Rent")-IF(DAY(A74)=Budget!$G$3,Budget!$F$3,0) -> 0 | G74: =N("Car")-IF(DAY(A74)=Budget!$G$4,Budget!$F$4+Budget!$H$4,0) -> 0 | H74: =N("Mom Rent")-IF(DAY(A74)=Budget!$G$5,Budget!$F$5,0) -> 0 | I74: =N("AT&T")-IF(DAY(A74)=Budget!$G$8,Budget!$F$8,0) -> 0 | J74: =N("GA Power")-IF(DAY(A74)=Budget!$G$9,Budget!$F$9,0) -> 0 | K74: =N("Haircut")-IF(DAY(A74)=Budget!$G$10,Budget!$F$10,0) -> 0 | L74: =N("Groceries")-IF(DAY(A74)=Budget!$G$6,Budget!$F$6,0) -> 0 | M74: =N("Savings")-IF(DAY(A74)=Budget!$G$7,Budget!$F$7,0) -> 0 | N74: =N("Car Insurance")-COUNTIF(Budget!$G$14, A74)*Budget!$F$14 -> 0 | O74: =N("Phone Bill")-COUNTIF(Budget!$G$15, A74)*Budget!$F$15 -> 0 | Q74: =N("Spotify")-IF(AND(DAY($A74)=Budget!$M$3, MONTH($A74)=Budget!$L$3),Budget!$K$3,0) -> 0 | R74: =N("Spotify")-IF(AND(DAY($A74)=Budget!$M$4, MONTH($A74)=Budget!$L$4),Budget!$K$4,0) -> 0 | S74: =N("Spotify")-IF(AND(DAY($A74)=Budget!$M$5, MONTH($A74)=Budget!$L$5),Budget!$K$5,0) -> 0 | T74: =N("Amazon Prime")-IF(DAY(A74)=Budget!$Q$3,Budget!$P$3,0) -> 0 | U74: =N("Audible")-IF(DAY(A74)=Budget!$Q$12,Budget!$P$12,0) -> 0 | V74: =N("Crunchyroll")-IF(DAY(A74)=Budget!$Q$5,Budget!$P$5,0) -> 0 | W74: =N("HBO Max")-IF(DAY(A74)=Budget!$Q$6,Budget!$P$6,0) -> 0 | X74: =N("Netflix")-IF(DAY(A74)=Budget!$Q$7,Budget!$P$7,0) -> 0 | Y74: =N("Spotify")-IF(DAY(A74)=Budget!$Q$8,Budget!$P$8,0) -> 0 | Z74: =N("Truebill")-IF(DAY(A74)=Budget!$Q$9,Budget!$P$9,0) -> 0 | AA74: =SUM(D74:Z74) -> 0
A75: =A74+1 -> 45723 | B75: =B74+AA75 -> 5791.98 | C75: =IF(B75>B74,2,IF(B75=B74, 1,0)) -> 2 | D75: 4251 | E75: =N("PAY-LM")+IF(WEEKDAY(A75)=Budget!$C$3,Budget!$B$3,0) -> 1453 | F75: =N("Rent")-IF(DAY(A75)=Budget!$G$3,Budget!$F$3,0) -> 0 | G75: =N("Car")-IF(DAY(A75)=Budget!$G$4,Budget!$F$4+Budget!$H$4,0) -> 0 | H75: =N("Mom Rent")-IF(DAY(A75)=Budget!$G$5,Budget!$F$5,0) -> 0 | I75: =N("AT&T")-IF(DAY(A75)=Budget!$G$8,Budget!$F$8,0) -> 0 | J75: =N("GA Power")-IF(DAY(A75)=Budget!$G$9,Budget!$F$9,0) -> 0 | K75: =N("Haircut")-IF(DAY(A75)=Budget!$G$10,Budget!$F$10,0) -> 0 | L75: =N("Groceries")-IF(DAY(A75)=Budget!$G$6,Budget!$F$6,0) -> 0 | M75: =N("Savings")-IF(DAY(A75)=Budget!$G$7,Budget!$F$7,0) -> 0 | N75: =N("Car Insurance")-COUNTIF(Budget!$G$14, A75)*Budget!$F$14 -> 0 | O75: =N("Phone Bill")-COUNTIF(Budget!$G$15, A75)*Budget!$F$15 -> 0 | Q75: =N("Spotify")-IF(AND(DAY($A75)=Budget!$M$3, MONTH($A75)=Budget!$L$3),Budget!$K$3,0) -> 0 | R75: =N("Spotify")-IF(AND(DAY($A75)=Budget!$M$4, MONTH($A75)=Budget!$L$4),Budget!$K$4,0) -> 0 | S75: =N("Spotify")-IF(AND(DAY($A75)=Budget!$M$5, MONTH($A75)=Budget!$L$5),Budget!$K$5,0) -> 0 | T75: =N("Amazon Prime")-IF(DAY(A75)=Budget!$Q$3,Budget!$P$3,0) -> 0 | U75: =N("Audible")-IF(DAY(A75)=Budget!$Q$12,Budget!$P$12,0) -> 0 | V75: =N("Crunchyroll")-IF(DAY(A75)=Budget!$Q$5,Budget!$P$5,0) -> 0 | W75: =N("HBO Max")-IF(DAY(A75)=Budget!$Q$6,Budget!$P$6,0) -> 0 | X75: =N("Netflix")-IF(DAY(A75)=Budget!$Q$7,Budget!$P$7,0) -> 0 | Y75: =N("Spotify")-IF(DAY(A75)=Budget!$Q$8,Budget!$P$8,0) -> 0 | Z75: =N("Truebill")-IF(DAY(A75)=Budget!$Q$9,Budget!$P$9,0) -> 0 | AA75: =SUM(D75:Z75) -> 5704
A76: =A75+1 -> 45724 | B76: =B75+AA76 -> 5772.51 | C76: =IF(B76>B75,2,IF(B76=B75, 1,0)) -> 0 | D76: 0 | E76: =N("PAY-LM")+IF(WEEKDAY(A76)=Budget!$C$3,Budget!$B$3,0) -> 0 | F76: =N("Rent")-IF(DAY(A76)=Budget!$G$3,Budget!$F$3,0) -> 0 | G76: =N("Car")-IF(DAY(A76)=Budget!$G$4,Budget!$F$4+Budget!$H$4,0) -> 0 | H76: =N("Mom Rent")-IF(DAY(A76)=Budget!$G$5,Budget!$F$5,0) -> 0 | I76: =N("AT&T")-IF(DAY(A76)=Budget!$G$8,Budget!$F$8,0) -> 0 | J76: =N("GA Power")-IF(DAY(A76)=Budget!$G$9,Budget!$F$9,0) -> 0 | K76: =N("Haircut")-IF(DAY(A76)=Budget!$G$10,Budget!$F$10,0) -> 0 | L76: =N("Groceries")-IF(DAY(A76)=Budget!$G$6,Budget!$F$6,0) -> 0 | M76: =N("Savings")-IF(DAY(A76)=Budget!$G$7,Budget!$F$7,0) -> 0 | N76: =N("Car Insurance")-COUNTIF(Budget!$G$14, A76)*Budget!$F$14 -> 0 | O76: =N("Phone Bill")-COUNTIF(Budget!$G$15, A76)*Budget!$F$15 -> 0 | Q76: =N("Spotify")-IF(AND(DAY($A76)=Budget!$M$3, MONTH($A76)=Budget!$L$3),Budget!$K$3,0) -> 0 | R76: =N("Spotify")-IF(AND(DAY($A76)=Budget!$M$4, MONTH($A76)=Budget!$L$4),Budget!$K$4,0) -> 0 | S76: =N("Spotify")-IF(AND(DAY($A76)=Budget!$M$5, MONTH($A76)=Budget!$L$5),Budget!$K$5,0) -> 0 | T76: =N("Amazon Prime")-IF(DAY(A76)=Budget!$Q$3,Budget!$P$3,0) -> -7.48 | U76: =N("Audible")-IF(DAY(A76)=Budget!$Q$12,Budget!$P$12,0) -> 0 | V76: =N("Crunchyroll")-IF(DAY(A76)=Budget!$Q$5,Budget!$P$5,0) -> 0 | W76: =N("HBO Max")-IF(DAY(A76)=Budget!$Q$6,Budget!$P$6,0) -> -11.99 | X76: =N("Netflix")-IF(DAY(A76)=Budget!$Q$7,Budget!$P$7,0) -> 0 | Y76: =N("Spotify")-IF(DAY(A76)=Budget!$Q$8,Budget!$P$8,0) -> 0 | Z76: =N("Truebill")-IF(DAY(A76)=Budget!$Q$9,Budget!$P$9,0) -> 0 | AA76: =SUM(D76:Z76) -> -19.47
A77: =A76+1 -> 45725 | B77: =B76+AA77 -> 5772.51 | C77: =IF(B77>B76,2,IF(B77=B76, 1,0)) -> 1 | D77: 0 | E77: =N("PAY-LM")+IF(WEEKDAY(A77)=Budget!$C$3,Budget!$B$3,0) -> 0 | F77: =N("Rent")-IF(DAY(A77)=Budget!$G$3,Budget!$F$3,0) -> 0 | G77: =N("Car")-IF(DAY(A77)=Budget!$G$4,Budget!$F$4+Budget!$H$4,0) -> 0 | H77: =N("Mom Rent")-IF(DAY(A77)=Budget!$G$5,Budget!$F$5,0) -> 0 | I77: =N("AT&T")-IF(DAY(A77)=Budget!$G$8,Budget!$F$8,0) -> 0 | J77: =N("GA Power")-IF(DAY(A77)=Budget!$G$9,Budget!$F$9,0) -> 0 | K77: =N("Haircut")-IF(DAY(A77)=Budget!$G$10,Budget!$F$10,0) -> 0 | L77: =N("Groceries")-IF(DAY(A77)=Budget!$G$6,Budget!$F$6,0) -> 0 | M77: =N("Savings")-IF(DAY(A77)=Budget!$G$7,Budget!$F$7,0) -> 0 | N77: =N("Car Insurance")-COUNTIF(Budget!$G$14, A77)*Budget!$F$14 -> 0 | O77: =N("Phone Bill")-COUNTIF(Budget!$G$15, A77)*Budget!$F$15 -> 0 | Q77: =N("Spotify")-IF(AND(DAY($A77)=Budget!$M$3, MONTH($A77)=Budget!$L$3),Budget!$K$3,0) -> 0 | R77: =N("Spotify")-IF(AND(DAY($A77)=Budget!$M$4, MONTH($A77)=Budget!$L$4),Budget!$K$4,0) -> 0 | S77: =N("Spotify")-IF(AND(DAY($A77)=Budget!$M$5, MONTH($A77)=Budget!$L$5),Budget!$K$5,0) -> 0 | T77: =N("Amazon Prime")-IF(DAY(A77)=Budget!$Q$3,Budget!$P$3,0) -> 0 | U77: =N("Audible")-IF(DAY(A77)=Budget!$Q$12,Budget!$P$12,0) -> 0 | V77: =N("Crunchyroll")-IF(DAY(A77)=Budget!$Q$5,Budget!$P$5,0) -> 0 | W77: =N("HBO Max")-IF(DAY(A77)=Budget!$Q$6,Budget!$P$6,0) -> 0 | X77: =N("Netflix")-IF(DAY(A77)=Budget!$Q$7,Budget!$P$7,0) -> 0 | Y77: =N("Spotify")-IF(DAY(A77)=Budget!$Q$8,Budget!$P$8,0) -> 0 | Z77: =N("Truebill")-IF(DAY(A77)=Budget!$Q$9,Budget!$P$9,0) -> 0 | AA77: =SUM(D77:Z77) -> 0
A78: =A77+1 -> 45726 | B78: =B77+AA78 -> 5772.51 | C78: =IF(B78>B77,2,IF(B78=B77, 1,0)) -> 1 | D78: 0 | E78: =N("PAY-LM")+IF(WEEKDAY(A78)=Budget!$C$3,Budget!$B$3,0) -> 0 | F78: =N("Rent")-IF(DAY(A78)=Budget!$G$3,Budget!$F$3,0) -> 0 | G78: =N("Car")-IF(DAY(A78)=Budget!$G$4,Budget!$F$4+Budget!$H$4,0) -> 0 | H78: =N("Mom Rent")-IF(DAY(A78)=Budget!$G$5,Budget!$F$5,0) -> 0 | I78: =N("AT&T")-IF(DAY(A78)=Budget!$G$8,Budget!$F$8,0) -> 0 | J78: =N("GA Power")-IF(DAY(A78)=Budget!$G$9,Budget!$F$9,0) -> 0 | K78: =N("Haircut")-IF(DAY(A78)=Budget!$G$10,Budget!$F$10,0) -> 0 | L78: =N("Groceries")-IF(DAY(A78)=Budget!$G$6,Budget!$F$6,0) -> 0 | M78: =N("Savings")-IF(DAY(A78)=Budget!$G$7,Budget!$F$7,0) -> 0 | N78: =N("Car Insurance")-COUNTIF(Budget!$G$14, A78)*Budget!$F$14 -> 0 | O78: =N("Phone Bill")-COUNTIF(Budget!$G$15, A78)*Budget!$F$15 -> 0 | Q78: =N("Spotify")-IF(AND(DAY($A78)=Budget!$M$3, MONTH($A78)=Budget!$L$3),Budget!$K$3,0) -> 0 | R78: =N("Spotify")-IF(AND(DAY($A78)=Budget!$M$4, MONTH($A78)=Budget!$L$4),Budget!$K$4,0) -> 0 | S78: =N("Spotify")-IF(AND(DAY($A78)=Budget!$M$5, MONTH($A78)=Budget!$L$5),Budget!$K$5,0) -> 0 | T78: =N("Amazon Prime")-IF(DAY(A78)=Budget!$Q$3,Budget!$P$3,0) -> 0 | U78: =N("Audible")-IF(DAY(A78)=Budget!$Q$12,Budget!$P$12,0) -> 0 | V78: =N("Crunchyroll")-IF(DAY(A78)=Budget!$Q$5,Budget!$P$5,0) -> 0 | W78: =N("HBO Max")-IF(DAY(A78)=Budget!$Q$6,Budget!$P$6,0) -> 0 | X78: =N("Netflix")-IF(DAY(A78)=Budget!$Q$7,Budget!$P$7,0) -> 0 | Y78: =N("Spotify")-IF(DAY(A78)=Budget!$Q$8,Budget!$P$8,0) -> 0 | Z78: =N("Truebill")-IF(DAY(A78)=Budget!$Q$9,Budget!$P$9,0) -> 0 | AA78: =SUM(D78:Z78) -> 0
A79: =A78+1 -> 45727 | B79: =B78+AA79 -> 5772.51 | C79: =IF(B79>B78,2,IF(B79=B78, 1,0)) -> 1 | D79: 0 | E79: =N("PAY-LM")+IF(WEEKDAY(A79)=Budget!$C$3,Budget!$B$3,0) -> 0 | F79: =N("Rent")-IF(DAY(A79)=Budget!$G$3,Budget!$F$3,0) -> 0 | G79: =N("Car")-IF(DAY(A79)=Budget!$G$4,Budget!$F$4+Budget!$H$4,0) -> 0 | H79: =N("Mom Rent")-IF(DAY(A79)=Budget!$G$5,Budget!$F$5,0) -> 0 | I79: =N("AT&T")-IF(DAY(A79)=Budget!$G$8,Budget!$F$8,0) -> 0 | J79: =N("GA Power")-IF(DAY(A79)=Budget!$G$9,Budget!$F$9,0) -> 0 | K79: =N("Haircut")-IF(DAY(A79)=Budget!$G$10,Budget!$F$10,0) -> 0 | L79: =N("Groceries")-IF(DAY(A79)=Budget!$G$6,Budget!$F$6,0) -> 0 | M79: =N("Savings")-IF(DAY(A79)=Budget!$G$7,Budget!$F$7,0) -> 0 | N79: =N("Car Insurance")-COUNTIF(Budget!$G$14, A79)*Budget!$F$14 -> 0 | O79: =N("Phone Bill")-COUNTIF(Budget!$G$15, A79)*Budget!$F$15 -> 0 | Q79: =N("Spotify")-IF(AND(DAY($A79)=Budget!$M$3, MONTH($A79)=Budget!$L$3),Budget!$K$3,0) -> 0 | R79: =N("Spotify")-IF(AND(DAY($A79)=Budget!$M$4, MONTH($A79)=Budget!$L$4),Budget!$K$4,0) -> 0 | S79: =N("Spotify")-IF(AND(DAY($A79)=Budget!$M$5, MONTH($A79)=Budget!$L$5),Budget!$K$5,0) -> 0 | T79: =N("Amazon Prime")-IF(DAY(A79)=Budget!$Q$3,Budget!$P$3,0) -> 0 | U79: =N("Audible")-IF(DAY(A79)=Budget!$Q$12,Budget!$P$12,0) -> 0 | V79: =N("Crunchyroll")-IF(DAY(A79)=Budget!$Q$5,Budget!$P$5,0) -> 0 | W79: =N("HBO Max")-IF(DAY(A79)=Budget!$Q$6,Budget!$P$6,0) -> 0 | X79: =N("Netflix")-IF(DAY(A79)=Budget!$Q$7,Budget!$P$7,0) -> 0 | Y79: =N("Spotify")-IF(DAY(A79)=Budget!$Q$8,Budget!$P$8,0) -> 0 | Z79: =N("Truebill")-IF(DAY(A79)=Budget!$Q$9,Budget!$P$9,0) -> 0 | AA79: =SUM(D79:Z79) -> 0
A80: =A79+1 -> 45728 | B80: =B79+AA80 -> 5766.51 | C80: =IF(B80>B79,2,IF(B80=B79, 1,0)) -> 0 | D80: 0 | E80: =N("PAY-LM")+IF(WEEKDAY(A80)=Budget!$C$3,Budget!$B$3,0) -> 0 | F80: =N("Rent")-IF(DAY(A80)=Budget!$G$3,Budget!$F$3,0) -> 0 | G80: =N("Car")-IF(DAY(A80)=Budget!$G$4,Budget!$F$4+Budget!$H$4,0) -> 0 | H80: =N("Mom Rent")-IF(DAY(A80)=Budget!$G$5,Budget!$F$5,0) -> 0 | I80: =N("AT&T")-IF(DAY(A80)=Budget!$G$8,Budget!$F$8,0) -> 0 | J80: =N("GA Power")-IF(DAY(A80)=Budget!$G$9,Budget!$F$9,0) -> 0 | K80: =N("Haircut")-IF(DAY(A80)=Budget!$G$10,Budget!$F$10,0) -> 0 | L80: =N("Groceries")-IF(DAY(A80)=Budget!$G$6,Budget!$F$6,0) -> 0 | M80: =N("Savings")-IF(DAY(A80)=Budget!$G$7,Budget!$F$7,0) -> 0 | N80: =N("Car Insurance")-COUNTIF(Budget!$G$14, A80)*Budget!$F$14 -> 0 | O80: =N("Phone Bill")-COUNTIF(Budget!$G$15, A80)*Budget!$F$15 -> 0 | Q80: =N("Spotify")-IF(AND(DAY($A80)=Budget!$M$3, MONTH($A80)=Budget!$L$3),Budget!$K$3,0) -> 0 | R80: =N("Spotify")-IF(AND(DAY($A80)=Budget!$M$4, MONTH($A80)=Budget!$L$4),Budget!$K$4,0) -> 0 | S80: =N("Spotify")-IF(AND(DAY($A80)=Budget!$M$5, MONTH($A80)=Budget!$L$5),Budget!$K$5,0) -> 0 | T80: =N("Amazon Prime")-IF(DAY(A80)=Budget!$Q$3,Budget!$P$3,0) -> 0 | U80: =N("Audible")-IF(DAY(A80)=Budget!$Q$12,Budget!$P$12,0) -> 0 | V80: =N("Crunchyroll")-IF(DAY(A80)=Budget!$Q$5,Budget!$P$5,0) -> 0 | W80: =N("HBO Max")-IF(DAY(A80)=Budget!$Q$6,Budget!$P$6,0) -> 0 | X80: =N("Netflix")-IF(DAY(A80)=Budget!$Q$7,Budget!$P$7,0) -> -6 | Y80: =N("Spotify")-IF(DAY(A80)=Budget!$Q$8,Budget!$P$8,0) -> 0 | Z80: =N("Truebill")-IF(DAY(A80)=Budget!$Q$9,Budget!$P$9,0) -> 0 | AA80: =SUM(D80:Z80) -> -6
A81: =A80+1 -> 45729 | B81: =B80+AA81 -> 5766.51 | C81: =IF(B81>B80,2,IF(B81=B80, 1,0)) -> 1 | D81: 0 | E81: =N("PAY-LM")+IF(WEEKDAY(A81)=Budget!$C$3,Budget!$B$3,0) -> 0 | F81: =N("Rent")-IF(DAY(A81)=Budget!$G$3,Budget!$F$3,0) -> 0 | G81: =N("Car")-IF(DAY(A81)=Budget!$G$4,Budget!$F$4+Budget!$H$4,0) -> 0 | H81: =N("Mom Rent")-IF(DAY(A81)=Budget!$G$5,Budget!$F$5,0) -> 0 | I81: =N("AT&T")-IF(DAY(A81)=Budget!$G$8,Budget!$F$8,0) -> 0 | J81: =N("GA Power")-IF(DAY(A81)=Budget!$G$9,Budget!$F$9,0) -> 0 | K81: =N("Haircut")-IF(DAY(A81)=Budget!$G$10,Budget!$F$10,0) -> 0 | L81: =N("Groceries")-IF(DAY(A81)=Budget!$G$6,Budget!$F$6,0) -> 0 | M81: =N("Savings")-IF(DAY(A81)=Budget!$G$7,Budget!$F$7,0) -> 0 | N81: =N("Car Insurance")-COUNTIF(Budget!$G$14, A81)*Budget!$F$14 -> 0 | O81: =N("Phone Bill")-COUNTIF(Budget!$G$15, A81)*Budget!$F$15 -> 0 | Q81: =N("Spotify")-IF(AND(DAY($A81)=Budget!$M$3, MONTH($A81)=Budget!$L$3),Budget!$K$3,0) -> 0 | R81: =N("Spotify")-IF(AND(DAY($A81)=Budget!$M$4, MONTH($A81)=Budget!$L$4),Budget!$K$4,0) -> 0 | S81: =N("Spotify")-IF(AND(DAY($A81)=Budget!$M$5, MONTH($A81)=Budget!$L$5),Budget!$K$5,0) -> 0 | T81: =N("Amazon Prime")-IF(DAY(A81)=Budget!$Q$3,Budget!$P$3,0) -> 0 | U81: =N("Audible")-IF(DAY(A81)=Budget!$Q$12,Budget!$P$12,0) -> 0 | V81: =N("Crunchyroll")-IF(DAY(A81)=Budget!$Q$5,Budget!$P$5,0) -> 0 | W81: =N("HBO Max")-IF(DAY(A81)=Budget!$Q$6,Budget!$P$6,0) -> 0 | X81: =N("Netflix")-IF(DAY(A81)=Budget!$Q$7,Budget!$P$7,0) -> 0 | Y81: =N("Spotify")-IF(DAY(A81)=Budget!$Q$8,Budget!$P$8,0) -> 0 | Z81: =N("Truebill")-IF(DAY(A81)=Budget!$Q$9,Budget!$P$9,0) -> 0 | AA81: =SUM(D81:Z81) -> 0
... A84: =A83+1 -> 45732 | B84: =B83+AA84 -> 7219.51 | C84: =IF(B84>B83,2,IF(B84=B83, 1,0)) -> 1 | D84: 0 | E84: =N("PAY-LM")+IF(WEEKDAY(A84)=Budget!$C$3,Budget!$B$3,0) -> 0 | F84: =N("Rent")-IF(DAY(A84)=Budget!$G$3,Budget!$F$3,0) -> 0 | G84: =N("Car")-IF(DAY(A84)=Budget!$G$4,Budget!$F$4+Budget!$H$4,0) -> 0 | H84: =N("Mom Rent")-IF(DAY(A84)=Budget!$G$5,Budget!$F$5,0) -> 0 | I84: =N("AT&T")-IF(DAY(A84)=Budget!$G$8,Budget!$F$8,0) -> 0 | J84: =N("GA Power")-IF(DAY(A84)=Budget!$G$9,Budget!$F$9,0) -> 0 | K84: =N("Haircut")-IF(DAY(A84)=Budget!$G$10,Budget!$F$10,0) -> 0 | L84: =N("Groceries")-IF(DAY(A84)=Budget!$G$6,Budget!$F$6,0) -> 0 | M84: =N("Savings")-IF(DAY(A84)=Budget!$G$7,Budget!$F$7,0) -> 0 | N84: =N("Car Insurance")-COUNTIF(Budget!$G$14, A84)*Budget!$F$14 -> 0 | O84: =N("Phone Bill")-COUNTIF(Budget!$G$15, A84)*Budget!$F$15 -> 0 | Q84: =N("Spotify")-IF(AND(DAY($A84)=Budget!$M$3, MONTH($A84)=Budget!$L$3),Budget!$K$3,0) -> 0 | R84: =N("Spotify")-IF(AND(DAY($A84)=Budget!$M$4, MONTH($A84)=Budget!$L$4),Budget!$K$4,0) -> 0 | S84: =N("Spotify")-IF(AND(DAY($A84)=Budget!$M$5, MONTH($A84)=Budget!$L$5),Budget!$K$5,0) -> 0 | T84: =N("Amazon Prime")-IF(DAY(A84)=Budget!$Q$3,Budget!$P$3,0) -> 0 | U84: =N("Audible")-IF(DAY(A84)=Budget!$Q$12,Budget!$P$12,0) -> 0 | V84: =N("Crunchyroll")-IF(DAY(A84)=Budget!$Q$5,Budget!$P$5,0) -> 0 | W84: =N("HBO Max")-IF(DAY(A84)=Budget!$Q$6,Budget!$P$6,0) -> 0 | X84: =N("Netflix")-IF(DAY(A84)=Budget!$Q$7,Budget!$P$7,0) -> 0 | Y84: =N("Spotify")-IF(DAY(A84)=Budget!$Q$8,Budget!$P$8,0) -> 0 | Z84: =N("Truebill")-IF(DAY(A84)=Budget!$Q$9,Budget!$P$9,0) -> 0 | AA84: =SUM(D84:Z84) -> 0
A85: =A84+1 -> 45733 | B85: 4347 | C85: =IF(B85>B84,2,IF(B85=B84, 1,0)) -> 0 | D85: 0 | E85: =N("PAY-LM")+IF(WEEKDAY(A85)=Budget!$C$3,Budget!$B$3,0) -> 0 | F85: =N("Rent")-IF(DAY(A85)=Budget!$G$3,Budget!$F$3,0) -> 0 | G85: =N("Car")-IF(DAY(A85)=Budget!$G$4,Budget!$F$4+Budget!$H$4,0) -> 0 | H85: =N("Mom Rent")-IF(DAY(A85)=Budget!$G$5,Budget!$F$5,0) -> 0 | I85: =N("AT&T")-IF(DAY(A85)=Budget!$G$8,Budget!$F$8,0) -> 0 | J85: =N("GA Power")-IF(DAY(A85)=Budget!$G$9,Budget!$F$9,0) -> 0 | K85: =N("Haircut")-IF(DAY(A85)=Budget!$G$10,Budget!$F$10,0) -> 0 | L85: =N("Groceries")-IF(DAY(A85)=Budget!$G$6,Budget!$F$6,0) -> 0 | M85: =N("Savings")-IF(DAY(A85)=Budget!$G$7,Budget!$F$7,0) -> 0 | N85: =N("Car Insurance")-COUNTIF(Budget!$G$14, A85)*Budget!$F$14 -> 0 | O85: =N("Phone Bill")-COUNTIF(Budget!$G$15, A85)*Budget!$F$15 -> 0 | Q85: =N("Spotify")-IF(AND(DAY($A85)=Budget!$M$3, MONTH($A85)=Budget!$L$3),Budget!$K$3,0) -> 0 | R85: =N("Spotify")-IF(AND(DAY($A85)=Budget!$M$4, MONTH($A85)=Budget!$L$4),Budget!$K$4,0) -> 0 | S85: =N("Spotify")-IF(AND(DAY($A85)=Budget!$M$5, MONTH($A85)=Budget!$L$5),Budget!$K$5,0) -> 0 | T85: =N("Amazon Prime")-IF(DAY(A85)=Budget!$Q$3,Budget!$P$3,0) -> 0 | U85: =N("Audible")-IF(DAY(A85)=Budget!$Q$12,Budget!$P$12,0) -> 0 | V85: =N("Crunchyroll")-IF(DAY(A85)=Budget!$Q$5,Budget!$P$5,0) -> 0 | W85: =N("HBO Max")-IF(DAY(A85)=Budget!$Q$6,Budget!$P$6,0) -> 0 | X85: =N("Netflix")-IF(DAY(A85)=Budget!$Q$7,Budget!$P$7,0) -> 0 | Y85: =N("Spotify")-IF(DAY(A85)=Budget!$Q$8,Budget!$P$8,0) -> 0 | Z85: =N("Truebill")-IF(DAY(A85)=Budget!$Q$9,Budget!$P$9,0) -> 0 | AA85: =SUM(D85:Z85) -> 0
A86: =A85+1 -> 45734 | B86: =B85+AA86 -> 4282 | C86: =IF(B86>B85,2,IF(B86=B85, 1,0)) -> 0 | D86: 0 | E86: =N("PAY-LM")+IF(WEEKDAY(A86)=Budget!$C$3,Budget!$B$3,0) -> 0 | F86: =N("Rent")-IF(DAY(A86)=Budget!$G$3,Budget!$F$3,0) -> 0 | G86: =N("Car")-IF(DAY(A86)=Budget!$G$4,Budget!$F$4+Budget!$H$4,0) -> 0 | H86: =N("Mom Rent")-IF(DAY(A86)=Budget!$G$5,Budget!$F$5,0) -> 0 | I86: =N("AT&T")-IF(DAY(A86)=Budget!$G$8,Budget!$F$8,0) -> -65 | J86: =N("GA Power")-IF(DAY(A86)=Budget!$G$9,Budget!$F$9,0) -> 0 | K86: =N("Haircut")-IF(DAY(A86)=Budget!$G$10,Budget!$F$10,0) -> 0 | L86: =N("Groceries")-IF(DAY(A86)=Budget!$G$6,Budget!$F$6,0) -> 0 | M86: =N("Savings")-IF(DAY(A86)=Budget!$G$7,Budget!$F$7,0) -> 0 | N86: =N("Car Insurance")-COUNTIF(Budget!$G$14, A86)*Budget!$F$14 -> 0 | O86: =N("Phone Bill")-COUNTIF(Budget!$G$15, A86)*Budget!$F$15 -> 0 | Q86: =N("Spotify")-IF(AND(DAY($A86)=Budget!$M$3, MONTH($A86)=Budget!$L$3),Budget!$K$3,0) -> 0 | R86: =N("Spotify")-IF(AND(DAY($A86)=Budget!$M$4, MONTH($A86)=Budget!$L$4),Budget!$K$4,0) -> 0 | S86: =N("Spotify")-IF(AND(DAY($A86)=Budget!$M$5, MONTH($A86)=Budget!$L$5),Budget!$K$5,0) -> 0 | T86: =N("Amazon Prime")-IF(DAY(A86)=Budget!$Q$3,Budget!$P$3,0) -> 0 | U86: =N("Audible")-IF(DAY(A86)=Budget!$Q$12,Budget!$P$12,0) -> 0 | V86: =N("Crunchyroll")-IF(DAY(A86)=Budget!$Q$5,Budget!$P$5,0) -> 0 | W86: =N("HBO Max")-IF(DAY(A86)=Budget!$Q$6,Budget!$P$6,0) -> 0 | X86: =N("Netflix")-IF(DAY(A86)=Budget!$Q$7,Budget!$P$7,0) -> 0 | Y86: =N("Spotify")-IF(DAY(A86)=Budget!$Q$8,Budget!$P$8,0) -> 0 | Z86: =N("Truebill")-IF(DAY(A86)=Budget!$Q$9,Budget!$P$9,0) -> 0 | AA86: =SUM(D86:Z86) -> -65
A87: =A86+1 -> 45735 | B87: =B86+AA87 -> 4282 | C87: =IF(B87>B86,2,IF(B87=B86, 1,0)) -> 1 | D87: 0 | E87: =N("PAY-LM")+IF(WEEKDAY(A87)=Budget!$C$3,Budget!$B$3,0) -> 0 | F87: =N("Rent")-IF(DAY(A87)=Budget!$G$3,Budget!$F$3,0) -> 0 | G87: =N("Car")-IF(DAY(A87)=Budget!$G$4,Budget!$F$4+Budget!$H$4,0) -> 0 | H87: =N("Mom Rent")-IF(DAY(A87)=Budget!$G$5,Budget!$F$5,0) -> 0 | I87: =N("AT&T")-IF(DAY(A87)=Budget!$G$8,Budget!$F$8,0) -> 0 | J87: =N("GA Power")-IF(DAY(A87)=Budget!$G$9,Budget!$F$9,0) -> 0 | K87: =N("Haircut")-IF(DAY(A87)=Budget!$G$10,Budget!$F$10,0) -> 0 | L87: =N("Groceries")-IF(DAY(A87)=Budget!$G$6,Budget!$F$6,0) -> 0 | M87: =N("Savings")-IF(DAY(A87)=Budget!$G$7,Budget!$F$7,0) -> 0 | N87: =N("Car Insurance")-COUNTIF(Budget!$G$14, A87)*Budget!$F$14 -> 0 | O87: =N("Phone Bill")-COUNTIF(Budget!$G$15, A87)*Budget!$F$15 -> 0 | Q87: =N("Spotify")-IF(AND(DAY($A87)=Budget!$M$3, MONTH($A87)=Budget!$L$3),Budget!$K$3,0) -> 0 | R87: =N("Spotify")-IF(AND(DAY($A87)=Budget!$M$4, MONTH($A87)=Budget!$L$4),Budget!$K$4,0) -> 0 | S87: =N("Spotify")-IF(AND(DAY($A87)=Budget!$M$5, MONTH($A87)=Budget!$L$5),Budget!$K$5,0) -> 0 | T87: =N("Amazon Prime")-IF(DAY(A87)=Budget!$Q$3,Budget!$P$3,0) -> 0 | U87: =N("Audible")-IF(DAY(A87)=Budget!$Q$12,Budget!$P$12,0) -> 0 | V87: =N("Crunchyroll")-IF(DAY(A87)=Budget!$Q$5,Budget!$P$5,0) -> 0 | W87: =N("HBO Max")-IF(DAY(A87)=Budget!$Q$6,Budget!$P$6,0) -> 0 | X87: =N("Netflix")-IF(DAY(A87)=Budget!$Q$7,Budget!$P$7,0) -> 0 | Y87: =N("Spotify")-IF(DAY(A87)=Budget!$Q$8,Budget!$P$8,0) -> 0 | Z87: =N("Truebill")-IF(DAY(A87)=Budget!$Q$9,Budget!$P$9,0) -> 0 | AA87: =SUM(D87:Z87) -> 0
A88: =A87+1 -> 45736 | B88: =B87+AA88 -> 3432 | C88: =IF(B88>B87,2,IF(B88=B87, 1,0)) -> 0 | D88: 0 | E88: =N("PAY-LM")+IF(WEEKDAY(A88)=Budget!$C$3,Budget!$B$3,0) -> 0 | F88: =N("Rent")-IF(DAY(A88)=Budget!$G$3,Budget!$F$3,0) -> 0 | G88: =N("Car")-IF(DAY(A88)=Budget!$G$4,Budget!$F$4+Budget!$H$4,0) -> 0 | H88: =N("Mom Rent")-IF(DAY(A88)=Budget!$G$5,Budget!$F$5,0) -> -850 | I88: =N("AT&T")-IF(DAY(A88)=Budget!$G$8,Budget!$F$8,0) -> 0 | J88: =N("GA Power")-IF(DAY(A88)=Budget!$G$9,Budget!$F$9,0) -> 0 | K88: =N("Haircut")-IF(DAY(A88)=Budget!$G$10,Budget!$F$10,0) -> 0 | L88: =N("Groceries")-IF(DAY(A88)=Budget!$G$6,Budget!$F$6,0) -> 0 | M88: =N("Savings")-IF(DAY(A88)=Budget!$G$7,Budget!$F$7,0) -> 0 | N88: =N("Car Insurance")-COUNTIF(Budget!$G$14, A88)*Budget!$F$14 -> 0 | O88: =N("Phone Bill")-COUNTIF(Budget!$G$15, A88)*Budget!$F$15 -> 0 | Q88: =N("Spotify")-IF(AND(DAY($A88)=Budget!$M$3, MONTH($A88)=Budget!$L$3),Budget!$K$3,0) -> 0 | R88: =N("Spotify")-IF(AND(DAY($A88)=Budget!$M$4, MONTH($A88)=Budget!$L$4),Budget!$K$4,0) -> 0 | S88: =N("Spotify")-IF(AND(DAY($A88)=Budget!$M$5, MONTH($A88)=Budget!$L$5),Budget!$K$5,0) -> 0 | T88: =N("Amazon Prime")-IF(DAY(A88)=Budget!$Q$3,Budget!$P$3,0) -> 0 | U88: =N("Audible")-IF(DAY(A88)=Budget!$Q$12,Budget!$P$12,0) -> 0 | V88: =N("Crunchyroll")-IF(DAY(A88)=Budget!$Q$5,Budget!$P$5,0) -> 0 | W88: =N("HBO Max")-IF(DAY(A88)=Budget!$Q$6,Budget!$P$6,0) -> 0 | X88: =N("Netflix")-IF(DAY(A88)=Budget!$Q$7,Budget!$P$7,0) -> 0 | Y88: =N("Spotify")-IF(DAY(A88)=Budget!$Q$8,Budget!$P$8,0) -> 0 | Z88: =N("Truebill")-IF(DAY(A88)=Budget!$Q$9,Budget!$P$9,0) -> 0 | AA88: =SUM(D88:Z88) -> -850
A89: =A88+1 -> 45737 | B89: =B88+AA89 -> 4885 | C89: =IF(B89>B88,2,IF(B89=B88, 1,0)) -> 2 | D89: 0 | E89: =N("PAY-LM")+IF(WEEKDAY(A89)=Budget!$C$3,Budget!$B$3,0) -> 1453 | F89: =N("Rent")-IF(DAY(A89)=Budget!$G$3,Budget!$F$3,0) -> 0 | G89: =N("Car")-IF(DAY(A89)=Budget!$G$4,Budget!$F$4+Budget!$H$4,0) -> 0 | H89: =N("Mom Rent")-IF(DAY(A89)=Budget!$G$5,Budget!$F$5,0) -> 0 | I89: =N("AT&T")-IF(DAY(A89)=Budget!$G$8,Budget!$F$8,0) -> 0 | J89: =N("GA Power")-IF(DAY(A89)=Budget!$G$9,Budget!$F$9,0) -> 0 | K89: =N("Haircut")-IF(DAY(A89)=Budget!$G$10,Budget!$F$10,0) -> 0 | L89: =N("Groceries")-IF(DAY(A89)=Budget!$G$6,Budget!$F$6,0) -> 0 | M89: =N("Savings")-IF(DAY(A89)=Budget!$G$7,Budget!$F$7,0) -> 0 | N89: =N("Car Insurance")-COUNTIF(Budget!$G$14, A89)*Budget!$F$14 -> 0 | O89: =N("Phone Bill")-COUNTIF(Budget!$G$15, A89)*Budget!$F$15 -> 0 | Q89: =N("Spotify")-IF(AND(DAY($A89)=Budget!$M$3, MONTH($A89)=Budget!$L$3),Budget!$K$3,0) -> 0 | R89: =N("Spotify")-IF(AND(DAY($A89)=Budget!$M$4, MONTH($A89)=Budget!$L$4),Budget!$K$4,0) -> 0 | S89: =N("Spotify")-IF(AND(DAY($A89)=Budget!$M$5, MONTH($A89)=Budget!$L$5),Budget!$K$5,0) -> 0 | T89: =N("Amazon Prime")-IF(DAY(A89)=Budget!$Q$3,Budget!$P$3,0) -> 0 | U89: =N("Audible")-IF(DAY(A89)=Budget!$Q$12,Budget!$P$12,0) -> 0 | V89: =N("Crunchyroll")-IF(DAY(A89)=Budget!$Q$5,Budget!$P$5,0) -> 0 | W89: =N("HBO Max")-IF(DAY(A89)=Budget!$Q$6,Budget!$P$6,0) -> 0 | X89: =N("Netflix")-IF(DAY(A89)=Budget!$Q$7,Budget!$P$7,0) -> 0 | Y89: =N("Spotify")-IF(DAY(A89)=Budget!$Q$8,Budget!$P$8,0) -> 0 | Z89: =N("Truebill")-IF(DAY(A89)=Budget!$Q$9,Budget!$P$9,0) -> 0 | AA89: =SUM(D89:Z89) -> 1453
A90: =A89+1 -> 45738 | B90: =B89+AA90 -> 4885 | C90: =IF(B90>B89,2,IF(B90=B89, 1,0)) -> 1 | D90: 0 | E90: =N("PAY-LM")+IF(WEEKDAY(A90)=Budget!$C$3,Budget!$B$3,0) -> 0 | F90: =N("Rent")-IF(DAY(A90)=Budget!$G$3,Budget!$F$3,0) -> 0 | G90: =N("Car")-IF(DAY(A90)=Budget!$G$4,Budget!$F$4+Budget!$H$4,0) -> 0 | H90: =N("Mom Rent")-IF(DAY(A90)=Budget!$G$5,Budget!$F$5,0) -> 0 | I90: =N("AT&T")-IF(DAY(A90)=Budget!$G$8,Budget!$F$8,0) -> 0 | J90: =N("GA Power")-IF(DAY(A90)=Budget!$G$9,Budget!$F$9,0) -> 0 | K90: =N("Haircut")-IF(DAY(A90)=Budget!$G$10,Budget!$F$10,0) -> 0 | L90: =N("Groceries")-IF(DAY(A90)=Budget!$G$6,Budget!$F$6,0) -> 0 | M90: =N("Savings")-IF(DAY(A90)=Budget!$G$7,Budget!$F$7,0) -> 0 | N90: =N("Car Insurance")-COUNTIF(Budget!$G$14, A90)*Budget!$F$14 -> 0 | O90: =N("Phone Bill")-COUNTIF(Budget!$G$15, A90)*Budget!$F$15 -> 0 | Q90: =N("Spotify")-IF(AND(DAY($A90)=Budget!$M$3, MONTH($A90)=Budget!$L$3),Budget!$K$3,0) -> 0 | R90: =N("Spotify")-IF(AND(DAY($A90)=Budget!$M$4, MONTH($A90)=Budget!$L$4),Budget!$K$4,0) -> 0 | S90: =N("Spotify")-IF(AND(DAY($A90)=Budget!$M$5, MONTH($A90)=Budget!$L$5),Budget!$K$5,0) -> 0 | T90: =N("Amazon Prime")-IF(DAY(A90)=Budget!$Q$3,Budget!$P$3,0) -> 0 | U90: =N("Audible")-IF(DAY(A90)=Budget!$Q$12,Budget!$P$12,0) -> 0 | V90: =N("Crunchyroll")-IF(DAY(A90)=Budget!$Q$5,Budget!$P$5,0) -> 0 | W90: =N("HBO Max")-IF(DAY(A90)=Budget!$Q$6,Budget!$P$6,0) -> 0 | X90: =N("Netflix")-IF(DAY(A90)=Budget!$Q$7,Budget!$P$7,0) -> 0 | Y90: =N("Spotify")-IF(DAY(A90)=Budget!$Q$8,Budget!$P$8,0) -> 0 | Z90: =N("Truebill")-IF(DAY(A90)=Budget!$Q$9,Budget!$P$9,0) -> 0 | AA90: =SUM(D90:Z90) -> 0
A91: =A90+1 -> 45739 | B91: =B90+AA91 -> 4885 | C91: =IF(B91>B90,2,IF(B91=B90, 1,0)) -> 1 | D91: 0 | E91: =N("PAY-LM")+IF(WEEKDAY(A91)=Budget!$C$3,Budget!$B$3,0) -> 0 | F91: =N("Rent")-IF(DAY(A91)=Budget!$G$3,Budget!$F$3,0) -> 0 | G91: =N("Car")-IF(DAY(A91)=Budget!$G$4,Budget!$F$4+Budget!$H$4,0) -> 0 | H91: =N("Mom Rent")-IF(DAY(A91)=Budget!$G$5,Budget!$F$5,0) -> 0 | I91: =N("AT&T")-IF(DAY(A91)=Budget!$G$8,Budget!$F$8,0) -> 0 | J91: =N("GA Power")-IF(DAY(A91)=Budget!$G$9,Budget!$F$9,0) -> 0 | K91: =N("Haircut")-IF(DAY(A91)=Budget!$G$10,Budget!$F$10,0) -> 0 | L91: =N("Groceries")-IF(DAY(A91)=Budget!$G$6,Budget!$F$6,0) -> 0 | M91: =N("Savings")-IF(DAY(A91)=Budget!$G$7,Budget!$F$7,0) -> 0 | N91: =N("Car Insurance")-COUNTIF(Budget!$G$14, A91)*Budget!$F$14 -> 0 | O91: =N("Phone Bill")-COUNTIF(Budget!$G$15, A91)*Budget!$F$15 -> 0 | Q91: =N("Spotify")-IF(AND(DAY($A91)=Budget!$M$3, MONTH($A91)=Budget!$L$3),Budget!$K$3,0) -> 0 | R91: =N("Spotify")-IF(AND(DAY($A91)=Budget!$M$4, MONTH($A91)=Budget!$L$4),Budget!$K$4,0) -> 0 | S91: =N("Spotify")-IF(AND(DAY($A91)=Budget!$M$5, MONTH($A91)=Budget!$L$5),Budget!$K$5,0) -> 0 | T91: =N("Amazon Prime")-IF(DAY(A91)=Budget!$Q$3,Budget!$P$3,0) -> 0 | U91: =N("Audible")-IF(DAY(A91)=Budget!$Q$12,Budget!$P$12,0) -> 0 | V91: =N("Crunchyroll")-IF(DAY(A91)=Budget!$Q$5,Budget!$P$5,0) -> 0 | W91: =N("HBO Max")-IF(DAY(A91)=Budget!$Q$6,Budget!$P$6,0) -> 0 | X91: =N("Netflix")-IF(DAY(A91)=Budget!$Q$7,Budget!$P$7,0) -> 0 | Y91: =N("Spotify")-IF(DAY(A91)=Budget!$Q$8,Budget!$P$8,0) -> 0 | Z91: =N("Truebill")-IF(DAY(A91)=Budget!$Q$9,Budget!$P$9,0) -> 0 | AA91: =SUM(D91:Z91) -> 0
A92: =A91+1 -> 45740 | B92: =B91+AA92 -> 4885 | C92: =IF(B92>B91,2,IF(B92=B91, 1,0)) -> 1 | D92: 0 | E92: =N("PAY-LM")+IF(WEEKDAY(A92)=Budget!$C$3,Budget!$B$3,0) -> 0 | F92: =N("Rent")-IF(DAY(A92)=Budget!$G$3,Budget!$F$3,0) -> 0 | G92: =N("Car")-IF(DAY(A92)=Budget!$G$4,Budget!$F$4+Budget!$H$4,0) -> 0 | H92: =N("Mom Rent")-IF(DAY(A92)=Budget!$G$5,Budget!$F$5,0) -> 0 | I92: =N("AT&T")-IF(DAY(A92)=Budget!$G$8,Budget!$F$8,0) -> 0 | J92: =N("GA Power")-IF(DAY(A92)=Budget!$G$9,Budget!$F$9,0) -> 0 | K92: =N("Haircut")-IF(DAY(A92)=Budget!$G$10,Budget!$F$10,0) -> 0 | L92: =N("Groceries")-IF(DAY(A92)=Budget!$G$6,Budget!$F$6,0) -> 0 | M92: =N("Savings")-IF(DAY(A92)=Budget!$G$7,Budget!$F$7,0) -> 0 | N92: =N("Car Insurance")-COUNTIF(Budget!$G$14, A92)*Budget!$F$14 -> 0 | O92: =N("Phone Bill")-COUNTIF(Budget!$G$15, A92)*Budget!$F$15 -> 0 | Q92: =N("Spotify")-IF(AND(DAY($A92)=Budget!$M$3, MONTH($A92)=Budget!$L$3),Budget!$K$3,0) -> 0 | R92: =N("Spotify")-IF(AND(DAY($A92)=Budget!$M$4, MONTH($A92)=Budget!$L$4),Budget!$K$4,0) -> 0 | S92: =N("Spotify")-IF(AND(DAY($A92)=Budget!$M$5, MONTH($A92)=Budget!$L$5),Budget!$K$5,0) -> 0 | T92: =N("Amazon Prime")-IF(DAY(A92)=Budget!$Q$3,Budget!$P$3,0) -> 0 | U92: =N("Audible")-IF(DAY(A92)=Budget!$Q$12,Budget!$P$12,0) -> 0 | V92: =N("Crunchyroll")-IF(DAY(A92)=Budget!$Q$5,Budget!$P$5,0) -> 0 | W92: =N("HBO Max")-IF(DAY(A92)=Budget!$Q$6,Budget!$P$6,0) -> 0 | X92: =N("Netflix")-IF(DAY(A92)=Budget!$Q$7,Budget!$P$7,0) -> 0 | Y92: =N("Spotify")-IF(DAY(A92)=Budget!$Q$8,Budget!$P$8,0) -> 0 | Z92: =N("Truebill")-IF(DAY(A92)=Budget!$Q$9,Budget!$P$9,0) -> 0 | AA92: =SUM(D92:Z92) -> 0
A93: =A92+1 -> 45741 | B93: =B92+AA93 -> 4885 | C93: =IF(B93>B92,2,IF(B93=B92, 1,0)) -> 1 | D93: 0 | E93: =N("PAY-LM")+IF(WEEKDAY(A93)=Budget!$C$3,Budget!$B$3,0) -> 0 | F93: =N("Rent")-IF(DAY(A93)=Budget!$G$3,Budget!$F$3,0) -> 0 | G93: =N("Car")-IF(DAY(A93)=Budget!$G$4,Budget!$F$4+Budget!$H$4,0) -> 0 | H93: =N("Mom Rent")-IF(DAY(A93)=Budget!$G$5,Budget!$F$5,0) -> 0 | I93: =N("AT&T")-IF(DAY(A93)=Budget!$G$8,Budget!$F$8,0) -> 0 | J93: =N("GA Power")-IF(DAY(A93)=Budget!$G$9,Budget!$F$9,0) -> 0 | K93: =N("Haircut")-IF(DAY(A93)=Budget!$G$10,Budget!$F$10,0) -> 0 | L93: =N("Groceries")-IF(DAY(A93)=Budget!$G$6,Budget!$F$6,0) -> 0 | M93: =N("Savings")-IF(DAY(A93)=Budget!$G$7,Budget!$F$7,0) -> 0 | N93: =N("Car Insurance")-COUNTIF(Budget!$G$14, A93)*Budget!$F$14 -> 0 | O93: =N("Phone Bill")-COUNTIF(Budget!$G$15, A93)*Budget!$F$15 -> 0 | Q93: =N("Spotify")-IF(AND(DAY($A93)=Budget!$M$3, MONTH($A93)=Budget!$L$3),Budget!$K$3,0) -> 0 | R93: =N("Spotify")-IF(AND(DAY($A93)=Budget!$M$4, MONTH($A93)=Budget!$L$4),Budget!$K$4,0) -> 0 | S93: =N("Spotify")-IF(AND(DAY($A93)=Budget!$M$5, MONTH($A93)=Budget!$L$5),Budget!$K$5,0) -> 0 | T93: =N("Amazon Prime")-IF(DAY(A93)=Budget!$Q$3,Budget!$P$3,0) -> 0 | U93: =N("Audible")-IF(DAY(A93)=Budget!$Q$12,Budget!$P$12,0) -> 0 | V93: =N("Crunchyroll")-IF(DAY(A93)=Budget!$Q$5,Budget!$P$5,0) -> 0 | W93: =N("HBO Max")-IF(DAY(A93)=Budget!$Q$6,Budget!$P$6,0) -> 0 | X93: =N("Netflix")-IF(DAY(A93)=Budget!$Q$7,Budget!$P$7,0) -> 0 | Y93: =N("Spotify")-IF(DAY(A93)=Budget!$Q$8,Budget!$P$8,0) -> 0 | Z93: =N("Truebill")-IF(DAY(A93)=Budget!$Q$9,Budget!$P$9,0) -> 0 | AA93: =SUM(D93:Z93) -> 0
A94: =A93+1 -> 45742 | B94: =B93+AA94 -> 4485 | C94: =IF(B94>B93,2,IF(B94=B93, 1,0)) -> 0 | D94: 0 | E94: =N("PAY-LM")+IF(WEEKDAY(A94)=Budget!$C$3,Budget!$B$3,0) -> 0 | F94: =N("Rent")-IF(DAY(A94)=Budget!$G$3,Budget!$F$3,0) -> 0 | G94: =N("Car")-IF(DAY(A94)=Budget!$G$4,Budget!$F$4+Budget!$H$4,0) -> 0 | H94: =N("Mom Rent")-IF(DAY(A94)=Budget!$G$5,Budget!$F$5,0) -> 0 | I94: =N("AT&T")-IF(DAY(A94)=Budget!$G$8,Budget!$F$8,0) -> 0 | J94: =N("GA Power")-IF(DAY(A94)=Budget!$G$9,Budget!$F$9,0) -> 0 | K94: =N("Haircut")-IF(DAY(A94)=Budget!$G$10,Budget!$F$10,0) -> -400 | L94: =N("Groceries")-IF(DAY(A94)=Budget!$G$6,Budget!$F$6,0) -> 0 | M94: =N("Savings")-IF(DAY(A94)=Budget!$G$7,Budget!$F$7,0) -> 0 | N94: =N("Car Insurance")-COUNTIF(Budget!$G$14, A94)*Budget!$F$14 -> 0 | O94: =N("Phone Bill")-COUNTIF(Budget!$G$15, A94)*Budget!$F$15 -> 0 | Q94: =N("Spotify")-IF(AND(DAY($A94)=Budget!$M$3, MONTH($A94)=Budget!$L$3),Budget!$K$3,0) -> 0 | R94: =N("Spotify")-IF(AND(DAY($A94)=Budget!$M$4, MONTH($A94)=Budget!$L$4),Budget!$K$4,0) -> 0 | S94: =N("Spotify")-IF(AND(DAY($A94)=Budget!$M$5, MONTH($A94)=Budget!$L$5),Budget!$K$5,0) -> 0 | T94: =N("Amazon Prime")-IF(DAY(A94)=Budget!$Q$3,Budget!$P$3,0) -> 0 | U94: =N("Audible")-IF(DAY(A94)=Budget!$Q$12,Budget!$P$12,0) -> 0 | V94: =N("Crunchyroll")-IF(DAY(A94)=Budget!$Q$5,Budget!$P$5,0) -> 0 | W94: =N("HBO Max")-IF(DAY(A94)=Budget!$Q$6,Budget!$P$6,0) -> 0 | X94: =N("Netflix")-IF(DAY(A94)=Budget!$Q$7,Budget!$P$7,0) -> 0 | Y94: =N("Spotify")-IF(DAY(A94)=Budget!$Q$8,Budget!$P$8,0) -> 0 | Z94: =N("Truebill")-IF(DAY(A94)=Budget!$Q$9,Budget!$P$9,0) -> 0 | AA94: =SUM(D94:Z94) -> -400
A95: =A94+1 -> 45743 | B95: =B94+AA95 -> 4485 | C95: =IF(B95>B94,2,IF(B95=B94, 1,0)) -> 1 | D95: 0 | E95: =N("PAY-LM")+IF(WEEKDAY(A95)=Budget!$C$3,Budget!$B$3,0) -> 0 | F95: =N("Rent")-IF(DAY(A95)=Budget!$G$3,Budget!$F$3,0) -> 0 | G95: =N("Car")-IF(DAY(A95)=Budget!$G$4,Budget!$F$4+Budget!$H$4,0) -> 0 | H95: =N("Mom Rent")-IF(DAY(A95)=Budget!$G$5,Budget!$F$5,0) -> 0 | I95: =N("AT&T")-IF(DAY(A95)=Budget!$G$8,Budget!$F$8,0) -> 0 | J95: =N("GA Power")-IF(DAY(A95)=Budget!$G$9,Budget!$F$9,0) -> 0 | K95: =N("Haircut")-IF(DAY(A95)=Budget!$G$10,Budget!$F$10,0) -> 0 | L95: =N("Groceries")-IF(DAY(A95)=Budget!$G$6,Budget!$F$6,0) -> 0 | M95: =N("Savings")-IF(DAY(A95)=Budget!$G$7,Budget!$F$7,0) -> 0 | N95: =N("Car Insurance")-COUNTIF(Budget!$G$14, A95)*Budget!$F$14 -> 0 | O95: =N("Phone Bill")-COUNTIF(Budget!$G$15, A95)*Budget!$F$15 -> 0 | Q95: =N("Spotify")-IF(AND(DAY($A95)=Budget!$M$3, MONTH($A95)=Budget!$L$3),Budget!$K$3,0) -> 0 | R95: =N("Spotify")-IF(AND(DAY($A95)=Budget!$M$4, MONTH($A95)=Budget!$L$4),Budget!$K$4,0) -> 0 | S95: =N("Spotify")-IF(AND(DAY($A95)=Budget!$M$5, MONTH($A95)=Budget!$L$5),Budget!$K$5,0) -> 0 | T95: =N("Amazon Prime")-IF(DAY(A95)=Budget!$Q$3,Budget!$P$3,0) -> 0 | U95: =N("Audible")-IF(DAY(A95)=Budget!$Q$12,Budget!$P$12,0) -> 0 | V95: =N("Crunchyroll")-IF(DAY(A95)=Budget!$Q$5,Budget!$P$5,0) -> 0 | W95: =N("HBO Max")-IF(DAY(A95)=Budget!$Q$6,Budget!$P$6,0) -> 0 | X95: =N("Netflix")-IF(DAY(A95)=Budget!$Q$7,Budget!$P$7,0) -> 0 | Y95: =N("Spotify")-IF(DAY(A95)=Budget!$Q$8,Budget!$P$8,0) -> 0 | Z95: =N("Truebill")-IF(DAY(A95)=Budget!$Q$9,Budget!$P$9,0) -> 0 | AA95: =SUM(D95:Z95) -> 0
A96: =A95+1 -> 45744 | B96: =B95+AA96 -> 4788 | C96: =IF(B96>B95,2,IF(B96=B95, 1,0)) -> 2 | D96: 0 | E96: =N("PAY-LM")+IF(WEEKDAY(A96)=Budget!$C$3,Budget!$B$3,0) -> 1453 | F96: =N("Rent")-IF(DAY(A96)=Budget!$G$3,Budget!$F$3,0) -> 0 | G96: =N("Car")-IF(DAY(A96)=Budget!$G$4,Budget!$F$4+Budget!$H$4,0) -> 0 | H96: =N("Mom Rent")-IF(DAY(A96)=Budget!$G$5,Budget!$F$5,0) -> 0 | I96: =N("AT&T")-IF(DAY(A96)=Budget!$G$8,Budget!$F$8,0) -> 0 | J96: =N("GA Power")-IF(DAY(A96)=Budget!$G$9,Budget!$F$9,0) -> 0 | K96: =N("Haircut")-IF(DAY(A96)=Budget!$G$10,Budget!$F$10,0) -> 0 | L96: =N("Groceries")-IF(DAY(A96)=Budget!$G$6,Budget!$F$6,0) -> 0 | M96: =N("Savings")-IF(DAY(A96)=Budget!$G$7,Budget!$F$7,0) -> -1000 | N96: =N("Car Insurance")-COUNTIF(Budget!$G$14, A96)*Budget!$F$14 -> 0 | O96: =N("Phone Bill")-COUNTIF(Budget!$G$15, A96)*Budget!$F$15 -> 0 | Q96: =N("Spotify")-IF(AND(DAY($A96)=Budget!$M$3, MONTH($A96)=Budget!$L$3),Budget!$K$3,0) -> 0 | R96: =N("Spotify")-IF(AND(DAY($A96)=Budget!$M$4, MONTH($A96)=Budget!$L$4),Budget!$K$4,0) -> 0 | S96: =N("Spotify")-IF(AND(DAY($A96)=Budget!$M$5, MONTH($A96)=Budget!$L$5),Budget!$K$5,0) -> 0 | T96: =N("Amazon Prime")-IF(DAY(A96)=Budget!$Q$3,Budget!$P$3,0) -> 0 | U96: =N("Audible")-IF(DAY(A96)=Budget!$Q$12,Budget!$P$12,0) -> 0 | V96: =N("Crunchyroll")-IF(DAY(A96)=Budget!$Q$5,Budget!$P$5,0) -> 0 | W96: =N("HBO Max")-IF(DAY(A96)=Budget!$Q$6,Budget!$P$6,0) -> 0 | X96: =N("Netflix")-IF(DAY(A96)=Budget!$Q$7,Budget!$P$7,0) -> 0 | Y96: =N("Spotify")-IF(DAY(A96)=Budget!$Q$8,Budget!$P$8,0) -> -150 | Z96: =N("Truebill")-IF(DAY(A96)=Budget!$Q$9,Budget!$P$9,0) -> 0 | AA96: =SUM(D96:Z96) -> 303
A97: =A96+1 -> 45745 | B97: =B96+AA97 -> 4763.4 | C97: =IF(B97>B96,2,IF(B97=B96, 1,0)) -> 0 | D97: 0 | E97: =N("PAY-LM")+IF(WEEKDAY(A97)=Budget!$C$3,Budget!$B$3,0) -> 0 | F97: =N("Rent")-IF(DAY(A97)=Budget!$G$3,Budget!$F$3,0) -> 0 | G97: =N("Car")-IF(DAY(A97)=Budget!$G$4,Budget!$F$4+Budget!$H$4,0) -> 0 | H97: =N("Mom Rent")-IF(DAY(A97)=Budget!$G$5,Budget!$F$5,0) -> 0 | I97: =N("AT&T")-IF(DAY(A97)=Budget!$G$8,Budget!$F$8,0) -> 0 | J97: =N("GA Power")-IF(DAY(A97)=Budget!$G$9,Budget!$F$9,0) -> 0 | K97: =N("Haircut")-IF(DAY(A97)=Budget!$G$10,Budget!$F$10,0) -> 0 | L97: =N("Groceries")-IF(DAY(A97)=Budget!$G$6,Budget!$F$6,0) -> 0 | M97: =N("Savings")-IF(DAY(A97)=Budget!$G$7,Budget!$F$7,0) -> 0 | N97: =N("Car Insurance")-COUNTIF(Budget!$G$14, A97)*Budget!$F$14 -> 0 | O97: =N("Phone Bill")-COUNTIF(Budget!$G$15, A97)*Budget!$F$15 -> 0 | Q97: =N("Spotify")-IF(AND(DAY($A97)=Budget!$M$3, MONTH($A97)=Budget!$L$3),Budget!$K$3,0) -> 0 | R97: =N("Spotify")-IF(AND(DAY($A97)=Budget!$M$4, MONTH($A97)=Budget!$L$4),Budget!$K$4,0) -> 0 | S97: =N("Spotify")-IF(AND(DAY($A97)=Budget!$M$5, MONTH($A97)=Budget!$L$5),Budget!$K$5,0) -> 0 | T97: =N("Amazon Prime")-IF(DAY(A97)=Budget!$Q$3,Budget!$P$3,0) -> 0 | U97: =N("Audible")-IF(DAY(A97)=Budget!$Q$12,Budget!$P$12,0) -> 0 | V97: =N("Crunchyroll")-IF(DAY(A97)=Budget!$Q$5,Budget!$P$5,0) -> -24.6 | W97: =N("HBO Max")-IF(DAY(A97)=Budget!$Q$6,Budget!$P$6,0) -> 0 | X97: =N("Netflix")-IF(DAY(A97)=Budget!$Q$7,Budget!$P$7,0) -> 0 | Y97: =N("Spotify")-IF(DAY(A97)=Budget!$Q$8,Budget!$P$8,0) -> 0 | Z97: =N("Truebill")-IF(DAY(A97)=Budget!$Q$9,Budget!$P$9,0) -> 0 | AA97: =SUM(D97:Z97) -> -24.6
... A99: =A98+1 -> 45747 | B99: =B98+AA99 -> 4763.4 | C99: =IF(B99>B98,2,IF(B99=B98, 1,0)) -> 1 | D99: 0 | E99: =N("PAY-LM")+IF(WEEKDAY(A99)=Budget!$C$3,Budget!$B$3,0) -> 0 | F99: =N("Rent")-IF(DAY(A99)=Budget!$G$3,Budget!$F$3,0) -> 0 | G99: =N("Car")-IF(DAY(A99)=Budget!$G$4,Budget!$F$4+Budget!$H$4,0) -> 0 | H99: =N("Mom Rent")-IF(DAY(A99)=Budget!$G$5,Budget!$F$5,0) -> 0 | I99: =N("AT&T")-IF(DAY(A99)=Budget!$G$8,Budget!$F$8,0) -> 0 | J99: =N("GA Power")-IF(DAY(A99)=Budget!$G$9,Budget!$F$9,0) -> 0 | K99: =N("Haircut")-IF(DAY(A99)=Budget!$G$10,Budget!$F$10,0) -> 0 | L99: =N("Groceries")-IF(DAY(A99)=Budget!$G$6,Budget!$F$6,0) -> 0 | M99: =N("Savings")-IF(DAY(A99)=Budget!$G$7,Budget!$F$7,0) -> 0 | N99: =N("Car Insurance")-COUNTIF(Budget!$G$14, A99)*Budget!$F$14 -> 0 | O99: =N("Phone Bill")-COUNTIF(Budget!$G$15, A99)*Budget!$F$15 -> 0 | Q99: =N("Spotify")-IF(AND(DAY($A99)=Budget!$M$3, MONTH($A99)=Budget!$L$3),Budget!$K$3,0) -> 0 | R99: =N("Spotify")-IF(AND(DAY($A99)=Budget!$M$4, MONTH($A99)=Budget!$L$4),Budget!$K$4,0) -> 0 | S99: =N("Spotify")-IF(AND(DAY($A99)=Budget!$M$5, MONTH($A99)=Budget!$L$5),Budget!$K$5,0) -> 0 | T99: =N("Amazon Prime")-IF(DAY(A99)=Budget!$Q$3,Budget!$P$3,0) -> 0 | U99: =N("Audible")-IF(DAY(A99)=Budget!$Q$12,Budget!$P$12,0) -> 0 | V99: =N("Crunchyroll")-IF(DAY(A99)=Budget!$Q$5,Budget!$P$5,0) -> 0 | W99: =N("HBO Max")-IF(DAY(A99)=Budget!$Q$6,Budget!$P$6,0) -> 0 | X99: =N("Netflix")-IF(DAY(A99)=Budget!$Q$7,Budget!$P$7,0) -> 0 | Y99: =N("Spotify")-IF(DAY(A99)=Budget!$Q$8,Budget!$P$8,0) -> 0 | Z99: =N("Truebill")-IF(DAY(A99)=Budget!$Q$9,Budget!$P$9,0) -> 0 | AA99: =SUM(D99:Z99) -> 0
D102: Miscellaneous | E102: Monthly Expenses | N102: =Budget!$E$12 -> Annual Expenses | Q102: Credit Card | T102: Subscriptions | AA102: TOTAL | AC102: =SUMIF(D104:Z133,"<0") -> -5121.42 | AD102: =SUM(E104:E133) -> 5812
A103: =EDATE(A68,1) -> 45748 | E103: =Budget!$A$3 -> PAY-LM | F103: =Budget!$E$3 -> Rent | G103: =Budget!$E$4 -> Car | H103: =Budget!$E$5 -> Mom Rent | I103: =Budget!$E$8 -> AT&T | J103: =Budget!$E$9 -> GA Power | K103: =Budget!$E$10 -> TH | L103: =Budget!$E$6 -> Groceries | M103: =Budget!$E$7 -> Savings | N103: =Budget!$E$14 -> Car Insurance | O103: =Budget!$E$15 -> Phone Bill | Q103: =Budget!$J$3 -> Capital One | R103: =Budget!$J$4 -> Chase | S103: =Budget!$J$5 -> NFCU | T103: =Budget!$O$3 -> Amazon Prime | U103: =Budget!$O$12 -> Audible | V103: =Budget!$O$5 -> Netflix | W103: =Budget!$O$6 -> Spotify | X103: =Budget!$O$7 -> Rocket Money | Y103: =Budget!$O$8 -> Little4Much | Z103: =Budget!$O$9 -> None | AC103: =AD102+AC102 -> 690.58
A104: =A103 -> 45748 | B104: =B99+AA104 -> 3030.4 | C104: =IF(B104>B99,2,IF(B104=B99, 1,0)) -> 0 | D104: 0 | E104: =N("PAY-LM")+IF(WEEKDAY(A104)=Budget!$C$3,Budget!$B$3,0) -> 0 | F104: =N("Rent")-IF(DAY(A104)=Budget!$G$3,Budget!$F$3,0) -> -1733 | G104: =N("Car")-IF(DAY(A104)=Budget!$G$4,Budget!$F$4+Budget!$H$4,0) -> 0 | H104: =N("Mom Rent")-IF(DAY(A104)=Budget!$G$5,Budget!$F$5,0) -> 0 | I104: =N("AT&T")-IF(DAY(A104)=Budget!$G$8,Budget!$F$8,0) -> 0 | J104: =N("GA Power")-IF(DAY(A104)=Budget!$G$9,Budget!$F$9,0) -> 0 | K104: =N("Haircut")-IF(DAY(A104)=Budget!$G$10,Budget!$F$10,0) -> 0 | L104: =N("Groceries")-IF(DAY(A104)=Budget!$G$6,Budget!$F$6,0) -> 0 | M104: =N("Savings")-IF(DAY(A104)=Budget!$G$7,Budget!$F$7,0) -> 0 | N104: =N("Car Insurance")-COUNTIF(Budget!$G$14, A104)*Budget!$F$14 -> 0 | O104: =N("Phone Bill")-COUNTIF(Budget!$G$15, A104)*Budget!$F$15 -> 0 | Q104: =N("Spotify")-IF(AND(DAY($A104)=Budget!$M$3, MONTH($A104)=Budget!$L$3),Budget!$K$3,0) -> 0 | R104: =N("Spotify")-IF(AND(DAY($A104)=Budget!$M$4, MONTH($A104)=Budget!$L$4),Budget!$K$4,0) -> 0 | S104: =N("Spotify")-IF(AND(DAY($A104)=Budget!$M$5, MONTH($A104)=Budget!$L$5),Budget!$K$5,0) -> 0 | T104: =N("Amazon Prime")-IF(DAY(A104)=Budget!$Q$3,Budget!$P$3,0) -> 0 | U104: =N("Audible")-IF(DAY(A104)=Budget!$Q$12,Budget!$P$12,0) -> 0 | V104: =N("Crunchyroll")-IF(DAY(A104)=Budget!$Q$5,Budget!$P$5,0) -> 0 | W104: =N("HBO Max")-IF(DAY(A104)=Budget!$Q$6,Budget!$P$6,0) -> 0 | X104: =N("Netflix")-IF(DAY(A104)=Budget!$Q$7,Budget!$P$7,0) -> 0 | Y104: =N("Spotify")-IF(DAY(A104)=Budget!$Q$8,Budget!$P$8,0) -> 0 | Z104: =N("Truebill")-IF(DAY(A104)=Budget!$Q$9,Budget!$P$9,0) -> 0 | AA104: =SUM(D104:Z104) -> -1733
A105: =A104+1 -> 45749 | B105: =B104+AA105 -> 2227.05 | C105: =IF(B105>B104,2,IF(B105=B104, 1,0)) -> 0 | D105: 0 | E105: =N("PAY-LM")+IF(WEEKDAY(A105)=Budget!$C$3,Budget!$B$3,0) -> 0 | F105: =N("Rent")-IF(DAY(A105)=Budget!$G$3,Budget!$F$3,0) -> 0 | G105: =N("Car")-IF(DAY(A105)=Budget!$G$4,Budget!$F$4+Budget!$H$4,0) -> -503.35 | H105: =N("Mom Rent")-IF(DAY(A105)=Budget!$G$5,Budget!$F$5,0) -> 0 | I105: =N("AT&T")-IF(DAY(A105)=Budget!$G$8,Budget!$F$8,0) -> 0 | J105: =N("GA Power")-IF(DAY(A105)=Budget!$G$9,Budget!$F$9,0) -> 0 | K105: =N("Haircut")-IF(DAY(A105)=Budget!$G$10,Budget!$F$10,0) -> 0 | L105: =N("Groceries")-IF(DAY(A105)=Budget!$G$6,Budget!$F$6,0) -> -300 | M105: =N("Savings")-IF(DAY(A105)=Budget!$G$7,Budget!$F$7,0) -> 0 | N105: =N("Car Insurance")-COUNTIF(Budget!$G$14, A105)*Budget!$F$14 -> 0 | O105: =N("Phone Bill")-COUNTIF(Budget!$G$15, A105)*Budget!$F$15 -> 0 | Q105: =N("Spotify")-IF(AND(DAY($A105)=Budget!$M$3, MONTH($A105)=Budget!$L$3),Budget!$K$3,0) -> 0 | R105: =N("Spotify")-IF(AND(DAY($A105)=Budget!$M$4, MONTH($A105)=Budget!$L$4),Budget!$K$4,0) -> 0 | S105: =N("Spotify")-IF(AND(DAY($A105)=Budget!$M$5, MONTH($A105)=Budget!$L$5),Budget!$K$5,0) -> 0 | T105: =N("Amazon Prime")-IF(DAY(A105)=Budget!$Q$3,Budget!$P$3,0) -> 0 | U105: =N("Audible")-IF(DAY(A105)=Budget!$Q$12,Budget!$P$12,0) -> 0 | V105: =N("Crunchyroll")-IF(DAY(A105)=Budget!$Q$5,Budget!$P$5,0) -> 0 | W105: =N("HBO Max")-IF(DAY(A105)=Budget!$Q$6,Budget!$P$6,0) -> 0 | X105: =N("Netflix")-IF(DAY(A105)=Budget!$Q$7,Budget!$P$7,0) -> 0 | Y105: =N("Spotify")-IF(DAY(A105)=Budget!$Q$8,Budget!$P$8,0) -> 0 | Z105: =N("Truebill")-IF(DAY(A105)=Budget!$Q$9,Budget!$P$9,0) -> 0 | AA105: =SUM(D105:Z105) -> -803.35
A106: =A105+1 -> 45750 | B106: =B105+AA106 -> 2227.05 | C106: =IF(B106>B105,2,IF(B106=B105, 1,0)) -> 1 | D106: 0 | E106: =N("PAY-LM")+IF(WEEKDAY(A106)=Budget!$C$3,Budget!$B$3,0) -> 0 | F106: =N("Rent")-IF(DAY(A106)=Budget!$G$3,Budget!$F$3,0) -> 0 | G106: =N("Car")-IF(DAY(A106)=Budget!$G$4,Budget!$F$4+Budget!$H$4,0) -> 0 | H106: =N("Mom Rent")-IF(DAY(A106)=Budget!$G$5,Budget!$F$5,0) -> 0 | I106: =N("AT&T")-IF(DAY(A106)=Budget!$G$8,Budget!$F$8,0) -> 0 | J106: =N("GA Power")-IF(DAY(A106)=Budget!$G$9,Budget!$F$9,0) -> 0 | K106: =N("Haircut")-IF(DAY(A106)=Budget!$G$10,Budget!$F$10,0) -> 0 | L106: =N("Groceries")-IF(DAY(A106)=Budget!$G$6,Budget!$F$6,0) -> 0 | M106: =N("Savings")-IF(DAY(A106)=Budget!$G$7,Budget!$F$7,0) -> 0 | N106: =N("Car Insurance")-COUNTIF(Budget!$G$14, A106)*Budget!$F$14 -> 0 | O106: =N("Phone Bill")-COUNTIF(Budget!$G$15, A106)*Budget!$F$15 -> 0 | Q106: =N("Spotify")-IF(AND(DAY($A106)=Budget!$M$3, MONTH($A106)=Budget!$L$3),Budget!$K$3,0) -> 0 | R106: =N("Spotify")-IF(AND(DAY($A106)=Budget!$M$4, MONTH($A106)=Budget!$L$4),Budget!$K$4,0) -> 0 | S106: =N("Spotify")-IF(AND(DAY($A106)=Budget!$M$5, MONTH($A106)=Budget!$L$5),Budget!$K$5,0) -> 0 | T106: =N("Amazon Prime")-IF(DAY(A106)=Budget!$Q$3,Budget!$P$3,0) -> 0 | U106: =N("Audible")-IF(DAY(A106)=Budget!$Q$12,Budget!$P$12,0) -> 0 | V106: =N("Crunchyroll")-IF(DAY(A106)=Budget!$Q$5,Budget!$P$5,0) -> 0 | W106: =N("HBO Max")-IF(DAY(A106)=Budget!$Q$6,Budget!$P$6,0) -> 0 | X106: =N("Netflix")-IF(DAY(A106)=Budget!$Q$7,Budget!$P$7,0) -> 0 | Y106: =N("Spotify")-IF(DAY(A106)=Budget!$Q$8,Budget!$P$8,0) -> 0 | Z106: =N("Truebill")-IF(DAY(A106)=Budget!$Q$9,Budget!$P$9,0) -> 0 | AA106: =SUM(D106:Z106) -> 0
A107: =A106+1 -> 45751 | B107: =B106+AA107 -> 3680.05 | C107: =IF(B107>B106,2,IF(B107=B106, 1,0)) -> 2 | D107: 0 | E107: =N("PAY-LM")+IF(WEEKDAY(A107)=Budget!$C$3,Budget!$B$3,0) -> 1453 | F107: =N("Rent")-IF(DAY(A107)=Budget!$G$3,Budget!$F$3,0) -> 0 | G107: =N("Car")-IF(DAY(A107)=Budget!$G$4,Budget!$F$4+Budget!$H$4,0) -> 0 | H107: =N("Mom Rent")-IF(DAY(A107)=Budget!$G$5,Budget!$F$5,0) -> 0 | I107: =N("AT&T")-IF(DAY(A107)=Budget!$G$8,Budget!$F$8,0) -> 0 | J107: =N("GA Power")-IF(DAY(A107)=Budget!$G$9,Budget!$F$9,0) -> 0 | K107: =N("Haircut")-IF(DAY(A107)=Budget!$G$10,Budget!$F$10,0) -> 0 | L107: =N("Groceries")-IF(DAY(A107)=Budget!$G$6,Budget!$F$6,0) -> 0 | M107: =N("Savings")-IF(DAY(A107)=Budget!$G$7,Budget!$F$7,0) -> 0 | N107: =N("Car Insurance")-COUNTIF(Budget!$G$14, A107)*Budget!$F$14 -> 0 | O107: =N("Phone Bill")-COUNTIF(Budget!$G$15, A107)*Budget!$F$15 -> 0 | Q107: =N("Spotify")-IF(AND(DAY($A107)=Budget!$M$3, MONTH($A107)=Budget!$L$3),Budget!$K$3,0) -> 0 | R107: =N("Spotify")-IF(AND(DAY($A107)=Budget!$M$4, MONTH($A107)=Budget!$L$4),Budget!$K$4,0) -> 0 | S107: =N("Spotify")-IF(AND(DAY($A107)=Budget!$M$5, MONTH($A107)=Budget!$L$5),Budget!$K$5,0) -> 0 | T107: =N("Amazon Prime")-IF(DAY(A107)=Budget!$Q$3,Budget!$P$3,0) -> 0 | U107: =N("Audible")-IF(DAY(A107)=Budget!$Q$12,Budget!$P$12,0) -> 0 | V107: =N("Crunchyroll")-IF(DAY(A107)=Budget!$Q$5,Budget!$P$5,0) -> 0 | W107: =N("HBO Max")-IF(DAY(A107)=Budget!$Q$6,Budget!$P$6,0) -> 0 | X107: =N("Netflix")-IF(DAY(A107)=Budget!$Q$7,Budget!$P$7,0) -> 0 | Y107: =N("Spotify")-IF(DAY(A107)=Budget!$Q$8,Budget!$P$8,0) -> 0 | Z107: =N("Truebill")-IF(DAY(A107)=Budget!$Q$9,Budget!$P$9,0) -> 0 | AA107: =SUM(D107:Z107) -> 1453
A108: =A107+1 -> 45752 | B108: =B107+AA108 -> 3610.05 | C108: =IF(B108>B107,2,IF(B108=B107, 1,0)) -> 0 | D108: 0 | E108: =N("PAY-LM")+IF(WEEKDAY(A108)=Budget!$C$3,Budget!$B$3,0) -> 0 | F108: =N("Rent")-IF(DAY(A108)=Budget!$G$3,Budget!$F$3,0) -> 0 | G108: =N("Car")-IF(DAY(A108)=Budget!$G$4,Budget!$F$4+Budget!$H$4,0) -> 0 | H108: =N("Mom Rent")-IF(DAY(A108)=Budget!$G$5,Budget!$F$5,0) -> 0 | I108: =N("AT&T")-IF(DAY(A108)=Budget!$G$8,Budget!$F$8,0) -> 0 | J108: =N("GA Power")-IF(DAY(A108)=Budget!$G$9,Budget!$F$9,0) -> -70 | K108: =N("Haircut")-IF(DAY(A108)=Budget!$G$10,Budget!$F$10,0) -> 0 | L108: =N("Groceries")-IF(DAY(A108)=Budget!$G$6,Budget!$F$6,0) -> 0 | M108: =N("Savings")-IF(DAY(A108)=Budget!$G$7,Budget!$F$7,0) -> 0 | N108: =N("Car Insurance")-COUNTIF(Budget!$G$14, A108)*Budget!$F$14 -> 0 | O108: =N("Phone Bill")-COUNTIF(Budget!$G$15, A108)*Budget!$F$15 -> 0 | Q108: =N("Spotify")-IF(AND(DAY($A108)=Budget!$M$3, MONTH($A108)=Budget!$L$3),Budget!$K$3,0) -> 0 | R108: =N("Spotify")-IF(AND(DAY($A108)=Budget!$M$4, MONTH($A108)=Budget!$L$4),Budget!$K$4,0) -> 0 | S108: =N("Spotify")-IF(AND(DAY($A108)=Budget!$M$5, MONTH($A108)=Budget!$L$5),Budget!$K$5,0) -> 0 | T108: =N("Amazon Prime")-IF(DAY(A108)=Budget!$Q$3,Budget!$P$3,0) -> 0 | U108: =N("Audible")-IF(DAY(A108)=Budget!$Q$12,Budget!$P$12,0) -> 0 | V108: =N("Crunchyroll")-IF(DAY(A108)=Budget!$Q$5,Budget!$P$5,0) -> 0 | W108: =N("HBO Max")-IF(DAY(A108)=Budget!$Q$6,Budget!$P$6,0) -> 0 | X108: =N("Netflix")-IF(DAY(A108)=Budget!$Q$7,Budget!$P$7,0) -> 0 | Y108: =N("Spotify")-IF(DAY(A108)=Budget!$Q$8,Budget!$P$8,0) -> 0 | Z108: =N("Truebill")-IF(DAY(A108)=Budget!$Q$9,Budget!$P$9,0) -> 0 | AA108: =SUM(D108:Z108) -> -70
...
